Workbook

Sheet Composición
A1: Código | B1: Grupo alimentario | C1: Subgrupo alimentario | D1: Nombre | E1: Sinonimo | F1: Precio por libra | G1: P. comestible (por 1 g) | H1: Energía (kcal) | I1: Agua (g) | J1: Alcohol (g) | K1: Proteínas (g) | L1: H. de Carbono (g) | M1: Almidón (g) | N1: Azúcares sencillos (g) | O1: Azúcares libres (g) | P1: Fibra vegetal (g) | Q1: Grasa total (g) | R1: AGS (g) | S1: AGM (g) | T1: AGP (g) | U1: Colesterol (mg) | V1: Vitamina A Eq. Retinol (µg) | W1: Retinol (µg) | X1: Carotenoides Eq. ß-caroteno (µg) | Y1: Vit. D (µg) | Z1: Vit. E Eq. a-tocoferol (mg) | AA1: Vit. K (µg) | AB1: Vitamina B1 (mg) | AC1: Vitamina B2 (mg) | AD1: Eq. de Niacina (mg) | AE1: Vit. B6 (mg) | AF1: Eq. Folato dietético (µg) | AG1: Vit. B12 (µg) | AH1: Pantoténico (mg) | AI1: Biotina (µg) | AJ1: Vit. C (mg) | AK1: Calcio (mg) | AL1: Fósforo (mg) | AM1: Hierro (mg) | AN1: Iodo (µg) | AO1: Cinc (mg) | AP1: Magnesio (mg) | AQ1: Sodio (mg) | AR1: Potasio (mg) | AS1: Manganeso (mg) | AT1: Cobre (mg) | AU1: Selenio (µg) | AV1: Omega-3 (g) | AW1: Tipo_Omega_3 | AX1: Grasas Trans (g) | AY1: Polifenoles (mg) | AZ1: Probióticos (Billones UFC) | BA1: Densidad_Proteica | BB1: Densidad_Fibra | BC1: Densidad_Calcio | BD1: Densidad_Hierro | BE1: Densidad_Sodio | BF1: Relacion_AGP_AGS | BG1: Relacion_Ca_P | BH1: Carga_Grasa_Saturada | BI1: Retención de Líquidos | BJ1: Proporción de Azúcar en el Carbohidrato | BK1: Ratio Fibra | BL1: Porcentaje de Calorías provenientes de las Grasas | BM1: Densidad de Magnesio | BN1: Etiqueta de Densidad Proteica | BO1: Etiqueta Densidad Fibra | BP1: Etiqueta Densidad Calcio | BQ1: Etiqueta Densidad Hierro | BR1: Etiqueta Densidad Sodio | BS1: Etiqueta Relación AGP / AGS | BT1: Etiqueta Porcentaje de Calorías de las Grasas | BU1: Retención de Líquidos (Na / K) | BV1: Etiqueta Densidad Magnesio | BW1: Etiqueta_Omega_3 | BX1: Etiqueta_Grasas_Trans | BY1: Etiqueta_Polifenoles | BZ1: Etiqueta_Probióticos | CA1: Etiqueta_Inflamatorio | CB1: Etiqueta_Irritante | CC1: Índice Inflamatorio de Grasas
A2: 1 | B2: CEREALES | C2: Cereales de desayuno | D2: Malta | F2: 1.5 | G2: 1 | H2: 365 | I2: 9.4 | J2: 0 | K2: 11.2 | L2: 73.1 | M2: 72.4 | N2: 0.66 | O2: 0 | P2: 4.2 | Q2: 2.1 | R2: 0.32 | S2: 0.24 | T2: 0.81 | U2: 0 | V2: 1.8 | W2: 0 | X2: 11 | Y2: 0 | Z2: 2.2 | AA2: 2.8 | AB2: 0.52 | AC2: 0.2 | AD2: 4.7 | AE2: 0.15 | AF2: 57 | AG2: 0 | AH2: 0.68 | AI2: 0 | AJ2: 0 | AK2: 36 | AL2: 349 | AM2: 3.5 | AN2: 0 | AO2: 3.6 | AP2: 111 | AQ2: 17 | AR2: 521 | AS2: 0 | AT2: 0.66 | AU2: 70.7 | AV2: =IFERROR(VLOOKUP(IFERROR(VLOOKUP(D2,Mapa_Similitud!$A$2:$B$2000,2,FALSE()),D2),Hoja1!$A$2:$K$1000,2,FALSE()),IFERROR(VLOOKUP(IFERROR(VLOOKUP(D2,Mapa_Similitud!$A$2:$B$2000,2,FALSE()),D2),Omega3_Referencia!$A$2:$E$100,3,FALSE()),0)) -> 0.03 | AW2: =IFERROR(VLOOKUP(IFERROR(VLOOKUP(D2,Mapa_Similitud!$A$2:$B$2000,2,FALSE()),D2),Hoja1!$A$2:$K$1000,3,FALSE()),IFERROR(VLOOKUP(IFERROR(VLOOKUP(D2,Mapa_Similitud!$A$2:$B$2000,2,FALSE()),D2),Omega3_Referencia!$A$2:$E$100,4,FALSE()),"N/A")) -> ALA | AX2: =IFERROR(VLOOKUP(IFERROR(VLOOKUP(D2,Mapa_Similitud!$A$2:$B$2000,2,FALSE()),D2),Hoja1!$A$2:$K$1000,5,FALSE()),0) -> 0 | AY2: =IFERROR(VLOOKUP(IFERROR(VLOOKUP(D2,Mapa_Similitud!$A$2:$B$2000,2,FALSE()),D2),Hoja1!$A$2:$K$1000,7,FALSE()),0) -> 40 | AZ2: =IFERROR(VLOOKUP(IFERROR(VLOOKUP(D2,Mapa_Similitud!$A$2:$B$2000,2,FALSE()),D2),Hoja1!$A$2:$K$1000,9,FALSE()),0) -> 0 | BA2: =IFERROR(K2/H2,0) -> 0.030684932 | BB2: =IFERROR(P2/H2,0) -> 0.011506849 | BC2: =IFERROR(AK2/H2,0) -> 0.098630137 | BD2: =IFERROR(AM2/H2,0) -> 0.0095890411 | BE2: =IFERROR(AQ2/H2,0) -> 0.046575342 | BF2: =IFERROR(T2/R2,0) -> 2.53125 | BG2: =IFERROR(AK2/AL2,0) -> 0.10315186 | BH2: =IFERROR(R2/Q2,0) -> 0.15238095 | BI2: =IFERROR(AQ2/AR2,0) -> 0.032629559 | BJ2: =IFERROR(N2/L2,0) -> 0.0090287278 | BK2: =IFERROR(P2/L2,0) -> 0.05745554 | BL2: =IFERROR((Q2*9)/H2,0) -> 0.051780822 | BM2: =IFERROR(AP2/H2,0) -> 0.30410959 | BN2: =IF(BA2>0.2,"Muy alta fuente de proteína",IF(BA2>0.15,"Alta fuente de proteína",IF(BA2>0.1,"Media fuente de proteína","Baja fuente de proteína"))) -> Baja fuente de proteína | BO2: =IF(BB2>0.03,"Alta",IF(BB2>0.015,"Media","Baja")) & " fuente de fibra" -> Baja fuente de fibra | BP2: =IF(BC2>1.5,"Alta fuente de calcio",IF(BC2>0.8,"Media fuente de calcio","Baja fuente de calcio")) -> Baja fuente de calcio | BQ2: =IF(BD2>0.015,"Alta fuente de hierro",IF(BD2>0.008,"Media fuente de hierro","Baja fuente de hierro")) -> Media fuente de hierro | BR2: =IF(BE2>2,"Muy alto",IF(BE2>1,"Alto",IF(BE2>0.5,"Moderado","Bajo"))) & " en sodio" -> Bajo en sodio | BS2: =IF(BF2>2,"Altamente antiinflamatorio",IF(BF2>1,"Ligeramente antiinflamatorio",IF(BF2>0.5,"Neutro","Proinflamatorio"))) -> Altamente antiinflamatorio | BT2: =IF(BL2>0.4,"Muy alto en grasas",IF(BL2>0.3,"Alto en grasas",IF(BL2>0.2,"Moderado en grasas","Bajo en grasas"))) -> Bajo en grasas | BU2: =IF(BI2>1,"Alto riesgo de retención de líquidos",IF(BI2>0.5,"Riesgo moderado de retención","Equilibrio de líquidos ideal")) -> Equilibrio de líquidos ideal | BV2: =IF(BM2>0.5,"Alta",IF(BM2>0.2,"Media","Baja")) & " fuente de magnesio" -> Media fuente de magnesio | BW2: =IF(AV2>=0.5,"Alta fuente de Omega 3",IF(AV2>0.1,"Ligera fuente de Omega 3","Sin aporte de Omega 3")) -> Sin aporte de Omega 3 | BX2: =IF(AX2>0.5,"Alerta: Alto en grasas trans",IF(AX2>0,"Contiene grasas trans","Libre de grasas trans")) -> Libre de grasas trans | BY2: =IF(AY2>=50,"Alto",IF(AY2>=10,"Medio","Bajo")) & " poder antioxidante" -> Medio poder antioxidante | BZ2: =IF(AZ2>=1,"Probiótico activo","Sin probióticos") -> Sin probióticos | CA2: =IF(OR(AX2>0.5, O2>15, J2>0), "Altamente inflamatorio", IF(OR(AV2>=0.5, AY2>=50), "Antiinflamatorio", IF(OR(AX2>0, O2>5), "Moderadamente inflamatorio", "Poco inflamatorio"))) -> Poco inflamatorio | CB2: =IF(ISNUMBER(SEARCH("miel", D2)), "No irritante (Uso condicionado SII)", IF(OR(J2>0, ISNUMBER(SEARCH("cacao", D2)), ISNUMBER(SEARCH("chocolate puro", D2))), "Altamente irritante", IF(OR(AND(O2>15, BI2>1), ISNUMBER(SEARCH("chocolate", D2))), "Moderadamente irritante", "No irritante"))) -> No irritante | CC2: =IF(AV2=0,"Sin Omega 3 para evaluar",IFERROR(IF(((T2-AV2)/AV2)>4,"Exceso relativo de Omega 6","Balance de omegas favorable"),"Sin Omega 3 para evaluar")) -> Exceso relativo de Omega 6
A3: =1+A2 -> 2 | B3: CEREALES | C3: Granos y harinas | D3: Arroz | F3: 0.5 | G3: 1 | H3: 364 | I3: 9.4 | J3: 0 | K3: 6.7 | L3: 81.6 | M3: 81.4 | N3: 0.16 | O3: 0 | P3: 1.4 | Q3: 0.9 | R3: 0.19 | S3: 0.23 | T3: 0.32 | U3: 0 | V3: 0 | W3: 0 | X3: 0 | Y3: 0 | Z3: 0.076 | AA3: 1 | AB3: 0.05 | AC3: 0.04 | AD3: 4.9 | AE3: 0.2 | AF3: 20 | AG3: 0 | AH3: 0 | AI3: 3 | AJ3: 20 | AK3: 14 | AL3: 150 | AM3: 0.8 | AN3: 14 | AO3: 1.5 | AP3: 31 | AQ3: 3.9 | AR3: 109 | AS3: 1.2 | AT3: 2 | AU3: 7 | AV3: =IFERROR(VLOOKUP(IFERROR(VLOOKUP(D3,Mapa_Similitud!$A$2:$B$2000,2,FALSE()),D3),Hoja1!$A$2:$K$1000,2,FALSE()),IFERROR(VLOOKUP(IFERROR(VLOOKUP(D3,Mapa_Similitud!$A$2:$B$2000,2,FALSE()),D3),Omega3_Referencia!$A$2:$E$100,3,FALSE()),0)) -> 0.01 | AW3: =IFERROR(VLOOKUP(IFERROR(VLOOKUP(D3,Mapa_Similitud!$A$2:$B$2000,2,FALSE()),D3),Hoja1!$A$2:$K$1000,3,FALSE()),IFERROR(VLOOKUP(IFERROR(VLOOKUP(D3,Mapa_Similitud!$A$2:$B$2000,2,FALSE()),D3),Omega3_Referencia!$A$2:$E$100,4,FALSE()),"N/A")) -> ALA | AX3: =IFERROR(VLOOKUP(IFERROR(VLOOKUP(D3,Mapa_Similitud!$A$2:$B$2000,2,FALSE()),D3),Hoja1!$A$2:$K$1000,5,FALSE()),0) -> 0 | AY3: =IFERROR(VLOOKUP(IFERROR(VLOOKUP(D3,Mapa_Similitud!$A$2:$B$2000,2,FALSE()),D3),Hoja1!$A$2:$K$1000,7,FALSE()),0) -> 1 | AZ3: =IFERROR(VLOOKUP(IFERROR(VLOOKUP(D3,Mapa_Similitud!$A$2:$B$2000,2,FALSE()),D3),Hoja1!$A$2:$K$1000,9,FALSE()),0) -> 0 | BA3: =IFERROR(K3/H3,0) -> 0.018406593 | BB3: =IFERROR(P3/H3,0) -> 0.0038461538 | BC3: =IFERROR(AK3/H3,0) -> 0.038461538 | BD3: =IFERROR(AM3/H3,0) -> 0.0021978022 | BE3: =IFERROR(AQ3/H3,0) -> 0.010714286 | BF3: =IFERROR(T3/R3,0) -> 1.6842105 | BG3: =IFERROR(AK3/AL3,0) -> 0.093333333 | BH3: =IFERROR(R3/Q3,0) -> 0.21111111 | BI3: =IFERROR(AQ3/AR3,0) -> 0.035779817 | BJ3: =IFERROR(N3/L3,0) -> 0.0019607843 | BK3: =IFERROR(P3/L3,0) -> 0.017156863 | BL3: =IFERROR((Q3*9)/H3,0) -> 0.022252747 | BM3: =IFERROR(AP3/H3,0) -> 0.085164835 | BN3: =IF(BA3>0.2,"Muy alta fuente de proteína",IF(BA3>0.15,"Alta fuente de proteína",IF(BA3>0.1,"Media fuente de proteína","Baja fuente de proteína"))) -> Baja fuente de proteína | BO3: =IF(BB3>0.03,"Alta",IF(BB3>0.015,"Media","Baja")) & " fuente de fibra" -> Baja fuente de fibra | BP3: =IF(BC3>1.5,"Alta fuente de calcio",IF(BC3>0.8,"Media fuente de calcio","Baja fuente de calcio")) -> Baja fuente de calcio | BQ3: =IF(BD3>0.015,"Alta fuente de hierro",IF(BD3>0.008,"Media fuente de hierro","Baja fuente de hierro")) -> Baja fuente de hierro | BR3: =IF(BE3>2,"Muy alto",IF(BE3>1,"Alto",IF(BE3>0.5,"Moderado","Bajo"))) & " en sodio" -> Bajo en sodio | BS3: =IF(BF3>2,"Altamente antiinflamatorio",IF(BF3>1,"Ligeramente antiinflamatorio",IF(BF3>0.5,"Neutro","Proinflamatorio"))) -> Ligeramente antiinflamatorio | BT3: =IF(BL3>0.4,"Muy alto en grasas",IF(BL3>0.3,"Alto en grasas",IF(BL3>0.2,"Moderado en grasas","Bajo en grasas"))) -> Bajo en grasas | BU3: =IF(BI3>1,"Alto riesgo de retención de líquidos",IF(BI3>0.5,"Riesgo moderado de retención","Equilibrio de líquidos ideal")) -> Equilibrio de líquidos ideal | BV3: =IF(BM3>0.5,"Alta",IF(BM3>0.2,"Media","Baja")) & " fuente de magnesio" -> Baja fuente de magnesio | BW3: =IF(AV3>=0.5,"Alta fuente de Omega 3",IF(AV3>0.1,"Ligera fuente de Omega 3","Sin aporte de Omega 3")) -> Sin aporte de Omega 3 | BX3: =IF(AX3>0.5,"Alerta: Alto en grasas trans",IF(AX3>0,"Contiene grasas trans","Libre de grasas trans")) -> Libre de grasas trans | BY3: =IF(AY3>=50,"Alto",IF(AY3>=10,"Medio","Bajo")) & " poder antioxidante" -> Bajo poder antioxidante | BZ3: =IF(AZ3>=1,"Probiótico activo","Sin probióticos") -> Sin probióticos | CA3: =IF(OR(AX3>0.5, O3>15, J3>0), "Altamente inflamatorio", IF(OR(AV3>=0.5, AY3>=50), "Antiinflamatorio", IF(OR(AX3>0, O3>5), "Moderadamente inflamatorio", "Poco inflamatorio"))) -> Poco inflamatorio | CB3: =IF(ISNUMBER(SEARCH("miel", D3)), "No irritante (Uso condicionado SII)", IF(OR(J3>0, ISNUMBER(SEARCH("cacao", D3)), ISNUMBER(SEARCH("chocolate puro", D3))), "Altamente irritante", IF(OR(AND(O3>15, BI3>1), ISNUMBER(SEARCH("chocolate", D3))), "Moderadamente irritante", "No irritante"))) -> No irritante | CC3: =IF(AV3=0,"Sin Omega 3 para evaluar",IFERROR(IF(((T3-AV3)/AV3)>4,"Exceso relativo de Omega 6","Balance de omegas favorable"),"Sin Omega 3 para evaluar")) -> Exceso relativo de Omega 6
A4: =1+A3 -> 3 | B4: CEREALES | C4: Granos y harinas | D4: Arroz blanco de cocción rápida | E4: Arroz instantáneo | F4: 0.5 | G4: 1 | H4: 349 | I4: 12.9 | J4: 0 | K4: 6.9 | L4: 78.2 | M4: 78.2 | N4: 0 | O4: 0 | P4: 1.4 | Q4: 0.6 | R4: 0.15 | S4: 0.17 | T4: 0.2 | U4: 0 | V4: 0 | W4: 0 | X4: 0 | Y4: 0 | Z4: 0.1 | AA4: 1 | AB4: 0.22 | AC4: 0.06 | AD4: 4.7 | AE4: 0.38 | AF4: 20 | AG4: 0 | AH4: 1.1 | AI4: 3 | AJ4: 0 | AK4: 34 | AL4: 150 | AM4: 1.4 | AN4: 14 | AO4: 1.8 | AP4: 31 | AQ4: 4 | AR4: 150 | AS4: 1.2 | AT4: 0.37 | AU4: 10 | AV4: =IFERROR(VLOOKUP(IFERROR(VLOOKUP(D4,Mapa_Similitud!$A$2:$B$2000,2,FALSE()),D4),Hoja1!$A$2:$K$1000,2,FALSE()),IFERROR(VLOOKUP(IFERROR(VLOOKUP(D4,Mapa_Similitud!$A$2:$B$2000,2,FALSE()),D4),Omega3_Referencia!$A$2:$E$100,3,FALSE()),0)) -> 0 | AW4: =IFERROR(VLOOKUP(IFERROR(VLOOKUP(D4,Mapa_Similitud!$A$2:$B$2000,2,FALSE()),D4),Hoja1!$A$2:$K$1000,3,FALSE()),IFERROR(VLOOKUP(IFERROR(VLOOKUP(D4,Mapa_Similitud!$A$2:$B$2000,2,FALSE()),D4),Omega3_Referencia!$A$2:$E$100,4,FALSE()),"N/A")) -> N/A | AX4: =IFERROR(VLOOKUP(IFERROR(VLOOKUP(D4,Mapa_Similitud!$A$2:$B$2000,2,FALSE()),D4),Hoja1!$A$2:$K$1000,5,FALSE()),0) -> 0 | AY4: =IFERROR(VLOOKUP(IFERROR(VLOOKUP(D4,Mapa_Similitud!$A$2:$B$2000,2,FALSE()),D4),Hoja1!$A$2:$K$1000,7,FALSE()),0) -> 0 | AZ4: =IFERROR(VLOOKUP(IFERROR(VLOOKUP(D4,Mapa_Similitud!$A$2:$B$2000,2,FALSE()),D4),Hoja1!$A$2:$K$1000,9,FALSE()),0) -> 0 | BA4: =IFERROR(K4/H4,0) -> 0.019770774 | BB4: =IFERROR(P4/H4,0) -> 0.0040114613 | BC4: =IFERROR(AK4/H4,0) -> 0.097421203 | BD4: =IFERROR(AM4/H4,0) -> 0.0040114613 | BE4: =IFERROR(AQ4/H4,0) -> 0.011461318 | BF4: =IFERROR(T4/R4,0) -> 1.3333333 | BG4: =IFERROR(AK4/AL4,0) -> 0.22666667 | BH4: =IFERROR(R4/Q4,0) -> 0.25 | BI4: =IFERROR(AQ4/AR4,0) -> 0.026666667 | BJ4: =IFERROR(N4/L4,0) -> 0 | BK4: =IFERROR(P4/L4,0) -> 0.017902813 | BL4: =IFERROR((Q4*9)/H4,0) -> 0.015472779 | BM4: =IFERROR(AP4/H4,0) -> 0.088825215 | BN4: =IF(BA4>0.2,"Muy alta fuente de proteína",IF(BA4>0.15,"Alta fuente de proteína",IF(BA4>0.1,"Media fuente de proteína","Baja fuente de proteína"))) -> Baja fuente de proteína | BO4: =IF(BB4>0.03,"Alta",IF(BB4>0.015,"Media","Baja")) & " fuente de fibra" -> Baja fuente de fibra | BP4: =IF(BC4>1.5,"Alta fuente de calcio",IF(BC4>0.8,"Media fuente de calcio","Baja fuente de calcio")) -> Baja fuente de calcio | BQ4: =IF(BD4>0.015,"Alta fuente de hierro",IF(BD4>0.008,"Media fuente de hierro","Baja fuente de hierro")) -> Baja fuente de hierro | BR4: =IF(BE4>2,"Muy alto",IF(BE4>1,"Alto",IF(BE4>0.5,"Moderado","Bajo"))) & " en sodio" -> Bajo en sodio | BS4: =IF(BF4>2,"Altamente antiinflamatorio",IF(BF4>1,"Ligeramente antiinflamatorio",IF(BF4>0.5,"Neutro","Proinflamatorio"))) -> Ligeramente antiinflamatorio | BT4: =IF(BL4>0.4,"Muy alto en grasas",IF(BL4>0.3,"Alto en grasas",IF(BL4>0.2,"Moderado en grasas","Bajo en grasas"))) -> Bajo en grasas | BU4: =IF(BI4>1,"Alto riesgo de retención de líquidos",IF(BI4>0.5,"Riesgo moderado de retención","Equilibrio de líquidos ideal")) -> Equilibrio de líquidos ideal | BV4: =IF(BM4>0.5,"Alta",IF(BM4>0.2,"Media","Baja")) & " fuente de magnesio" -> Baja fuente de magnesio | BW4: =IF(AV4>=0.5,"Alta fuente de Omega 3",IF(AV4>0.1,"Ligera fuente de Omega 3","Sin aporte de Omega 3")) -> Sin aporte de Omega 3 | BX4: =IF(AX4>0.5,"Alerta: Alto en grasas trans",IF(AX4>0,"Contiene grasas trans","Libre de grasas trans")) -> Libre de grasas trans | BY4: =IF(AY4>=50,"Alto",IF(AY4>=10,"Medio","Bajo")) & " poder antioxidante" -> Bajo poder antioxidante | BZ4: =IF(AZ4>=1,"Probiótico activo","Sin probióticos") -> Sin probióticos | CA4: =IF(OR(AX4>0.5, O4>15, J4>0), "Altamente inflamatorio", IF(OR(AV4>=0.5, AY4>=50), "Antiinflamatorio", IF(OR(AX4>0, O4>5), "Moderadamente inflamatorio", "Poco inflamatorio"))) -> Poco inflamatorio | CB4: =IF(ISNUMBER(SEARCH("miel", D4)), "No irritante (Uso condicionado SII)", IF(OR(J4>0, ISNUMBER(SEARCH("cacao", D4)), ISNUMBER(SEARCH("chocolate puro", D4))), "Altamente irritante", IF(OR(AND(O4>15, BI4>1), ISNUMBER(SEARCH("chocolate", D4))), "Moderadamente irritante", "No irritante"))) -> No irritante | CC4: =IF(AV4=0,"Sin Omega 3 para evaluar",IFERROR(IF(((T4-AV4)/AV4)>4,"Exceso relativo de Omega 6","Balance de omegas favorable"),"Sin Omega 3 para evaluar")) -> Sin Omega 3 para evaluar
A5: =1+A4 -> 4 | B5: CEREALES | C5: Granos y harinas | D5: Arroz integral | F5: 0.8 | G5: 1 | H5: 350 | I5: 14.2 | J5: 0 | K5: 7.3 | L5: 74.1 | M5: 72.7 | N5: 1.4 | O5: 0 | P5: 2.2 | Q5: 2.2 | R5: 0.61 | S5: 0.55 | T5: 0.81 | U5: 0 | V5: 0 | W5: 0 | X5: 0 | Y5: 0 | Z5: 0.74 | AA5: 1 | AB5: 0.41 | AC5: 0.09 | AD5: 6.6 | AE5: 0.28 | AF5: 49 | AG5: 0 | AH5: 1.5 | AI5: 12 | AJ5: 0 | AK5: 21 | AL5: 310 | AM5: 1.7 | AN5: 2.2 | AO5: 1.6 | AP5: 110 | AQ5: 10 | AR5: 238 | AS5: 2.1 | AT5: 0.29 | AU5: 10 | AV5: =IFERROR(VLOOKUP(IFERROR(VLOOKUP(D5,Mapa_Similitud!$A$2:$B$2000,2,FALSE()),D5),Hoja1!$A$2:$K$1000,2,FALSE()),IFERROR(VLOOKUP(IFERROR(VLOOKUP(D5,Mapa_Similitud!$A$2:$B$2000,2,FALSE()),D5),Omega3_Referencia!$A$2:$E$100,3,FALSE()),0)) -> 0.04 | AW5: =IFERROR(VLOOKUP(IFERROR(VLOOKUP(D5,Mapa_Similitud!$A$2:$B$2000,2,FALSE()),D5),Hoja1!$A$2:$K$1000,3,FALSE()),IFERROR(VLOOKUP(IFERROR(VLOOKUP(D5,Mapa_Similitud!$A$2:$B$2000,2,FALSE()),D5),Omega3_Referencia!$A$2:$E$100,4,FALSE()),"N/A")) -> ALA | AX5: =IFERROR(VLOOKUP(IFERROR(VLOOKUP(D5,Mapa_Similitud!$A$2:$B$2000,2,FALSE()),D5),Hoja1!$A$2:$K$1000,5,FALSE()),0) -> 0 | AY5: =IFERROR(VLOOKUP(IFERROR(VLOOKUP(D5,Mapa_Similitud!$A$2:$B$2000,2,FALSE()),D5),Hoja1!$A$2:$K$1000,7,FALSE()),0) -> 25 | AZ5: =IFERROR(VLOOKUP(IFERROR(VLOOKUP(D5,Mapa_Similitud!$A$2:$B$2000,2,FALSE()),D5),Hoja1!$A$2:$K$1000,9,FALSE()),0) -> 0 | BA5: =IFERROR(K5/H5,0) -> 0.020857143 | BB5: =IFERROR(P5/H5,0) -> 0.0062857143 | BC5: =IFERROR(AK5/H5,0) -> 0.06 | BD5: =IFERROR(AM5/H5,0) -> 0.0048571429 | BE5: =IFERROR(AQ5/H5,0) -> 0.028571429 | BF5: =IFERROR(T5/R5,0) -> 1.3278689 | BG5: =IFERROR(AK5/AL5,0) -> 0.067741935 | BH5: =IFERROR(R5/Q5,0) -> 0.27727273 | BI5: =IFERROR(AQ5/AR5,0) -> 0.042016807 | BJ5: =IFERROR(N5/L5,0) -> 0.018893387 | BK5: =IFERROR(P5/L5,0) -> 0.029689609 | BL5: =IFERROR((Q5*9)/H5,0) -> 0.056571429 | BM5: =IFERROR(AP5/H5,0) -> 0.31428571 | BN5: =IF(BA5>0.2,"Muy alta fuente de proteína",IF(BA5>0.15,"Alta fuente de proteína",IF(BA5>0.1,"Media fuente de proteína","Baja fuente de proteína"))) -> Baja fuente de proteína | BO5: =IF(BB5>0.03,"Alta",IF(BB5>0.015,"Media","Baja")) & " fuente de fibra" -> Baja fuente de fibra | BP5: =IF(BC5>1.5,"Alta fuente de calcio",IF(BC5>0.8,"Media fuente de calcio","Baja fuente de calcio")) -> Baja fuente de calcio | BQ5: =IF(BD5>0.015,"Alta fuente de hierro",IF(BD5>0.008,"Media fuente de hierro","Baja fuente de hierro")) -> Baja fuente de hierro | BR5: =IF(BE5>2,"Muy alto",IF(BE5>1,"Alto",IF(BE5>0.5,"Moderado","Bajo"))) & " en sodio" -> Bajo en sodio | BS5: =IF(BF5>2,"Altamente antiinflamatorio",IF(BF5>1,"Ligeramente antiinflamatorio",IF(BF5>0.5,"Neutro","Proinflamatorio"))) -> Ligeramente antiinflamatorio | BT5: =IF(BL5>0.4,"Muy alto en grasas",IF(BL5>0.3,"Alto en grasas",IF(BL5>0.2,"Moderado en grasas","Bajo en grasas"))) -> Bajo en grasas | BU5: =IF(BI5>1,"Alto riesgo de retención de líquidos",IF(BI5>0.5,"Riesgo moderado de retención","Equilibrio de líquidos ideal")) -> Equilibrio de líquidos ideal | BV5: =IF(BM5>0.5,"Alta",IF(BM5>0.2,"Media","Baja")) & " fuente de magnesio" -> Media fuente de magnesio | BW5: =IF(AV5>=0.5,"Alta fuente de Omega 3",IF(AV5>0.1,"Ligera fuente de Omega 3","Sin aporte de Omega 3")) -> Sin aporte de Omega 3 | BX5: =IF(AX5>0.5,"Alerta: Alto en grasas trans",IF(AX5>0,"Contiene grasas trans","Libre de grasas trans")) -> Libre de grasas trans | BY5: =IF(AY5>=50,"Alto",IF(AY5>=10,"Medio","Bajo")) & " poder antioxidante" -> Medio poder antioxidante | BZ5: =IF(AZ5>=1,"Probiótico activo","Sin probióticos") -> Sin probióticos | CA5: =IF(OR(AX5>0.5, O5>15, J5>0), "Altamente inflamatorio", IF(OR(AV5>=0.5, AY5>=50), "Antiinflamatorio", IF(OR(AX5>0, O5>5), "Moderadamente inflamatorio", "Poco inflamatorio"))) -> Poco inflamatorio | CB5: =IF(ISNUMBER(SEARCH("miel", D5)), "No irritante (Uso condicionado SII)", IF(OR(J5>0, ISNUMBER(SEARCH("cacao", D5)), ISNUMBER(SEARCH("chocolate puro", D5))), "Altamente irritante", IF(OR(AND(O5>15, BI5>1), ISNUMBER(SEARCH("chocolate", D5))), "Moderadamente irritante", "No irritante"))) -> No irritante | CC5: =IF(AV5=0,"Sin Omega 3 para evaluar",IFERROR(IF(((T5-AV5)/AV5)>4,"Exceso relativo de Omega 6","Balance de omegas favorable"),"Sin Omega 3 para evaluar")) -> Exceso relativo de Omega 6
A6: =1+A5 -> 5 | B6: CEREALES | C6: Granos y harinas | D6: Avena | F6: 0.5 | G6: 1 | H6: 353 | I6: 15.8 | J6: 0 | K6: 11.7 | L6: 55.7 | M6: 55.7 | N6: 0 | O6: 0 | P6: 9.7 | Q6: 7.1 | R6: 1.5 | S6: 2.6 | T6: 2.9 | U6: 0 | V6: 0 | W6: 0 | X6: 0 | Y6: 0 | Z6: 0.84 | AA6: 50 | AB6: 0.67 | AC6: 0.17 | AD6: 3.4 | AE6: 0.96 | AF6: 33 | AG6: 0 | AH6: 0.71 | AI6: 13 | AJ6: 0 | AK6: 80 | AL6: 342 | AM6: 5.8 | AN6: 7.7 | AO6: 3.2 | AP6: 129 | AQ6: 8.4 | AR6: 355 | AS6: 3.1 | AT6: 0.42 | AU6: 7.1 | AV6: =IFERROR(VLOOKUP(IFERROR(VLOOKUP(D6,Mapa_Similitud!$A$2:$B$2000,2,FALSE()),D6),Hoja1!$A$2:$K$1000,2,FALSE()),IFERROR(VLOOKUP(IFERROR(VLOOKUP(D6,Mapa_Similitud!$A$2:$B$2000,2,FALSE()),D6),Omega3_Referencia!$A$2:$E$100,3,FALSE()),0)) -> 0.11 | AW6: =IFERROR(VLOOKUP(IFERROR(VLOOKUP(D6,Mapa_Similitud!$A$2:$B$2000,2,FALSE()),D6),Hoja1!$A$2:$K$1000,3,FALSE()),IFERROR(VLOOKUP(IFERROR(VLOOKUP(D6,Mapa_Similitud!$A$2:$B$2000,2,FALSE()),D6),Omega3_Referencia!$A$2:$E$100,4,FALSE()),"N/A")) -> ALA | AX6: =IFERROR(VLOOKUP(IFERROR(VLOOKUP(D6,Mapa_Similitud!$A$2:$B$2000,2,FALSE()),D6),Hoja1!$A$2:$K$1000,5,FALSE()),0) -> 0 | AY6: =IFERROR(VLOOKUP(IFERROR(VLOOKUP(D6,Mapa_Similitud!$A$2:$B$2000,2,FALSE()),D6),Hoja1!$A$2:$K$1000,7,FALSE()),0) -> 80 | AZ6: =IFERROR(VLOOKUP(IFERROR(VLOOKUP(D6,Mapa_Similitud!$A$2:$B$2000,2,FALSE()),D6),Hoja1!$A$2:$K$1000,9,FALSE()),0) -> 0 | BA6: =IFERROR(K6/H6,0) -> 0.033144476 | BB6: =IFERROR(P6/H6,0) -> 0.027478754 | BC6: =IFERROR(AK6/H6,0) -> 0.2266289 | BD6: =IFERROR(AM6/H6,0) -> 0.016430595 | BE6: =IFERROR(AQ6/H6,0) -> 0.023796034 | BF6: =IFERROR(T6/R6,0) -> 1.9333333 | BG6: =IFERROR(AK6/AL6,0) -> 0.23391813 | BH6: =IFERROR(R6/Q6,0) -> 0.21126761 | BI6: =IFERROR(AQ6/AR6,0) -> 0.023661972 | BJ6: =IFERROR(N6/L6,0) -> 0 | BK6: =IFERROR(P6/L6,0) -> 0.17414722 | BL6: =IFERROR((Q6*9)/H6,0) -> 0.18101983 | BM6: =IFERROR(AP6/H6,0) -> 0.36543909 | BN6: =IF(BA6>0.2,"Muy alta fuente de proteína",IF(BA6>0.15,"Alta fuente de proteína",IF(BA6>0.1,"Media fuente de proteína","Baja fuente de proteína"))) -> Baja fuente de proteína | BO6: =IF(BB6>0.03,"Alta",IF(BB6>0.015,"Media","Baja")) & " fuente de fibra" -> Media fuente de fibra | BP6: =IF(BC6>1.5,"Alta fuente de calcio",IF(BC6>0.8,"Media fuente de calcio","Baja fuente de calcio")) -> Baja fuente de calcio | BQ6: =IF(BD6>0.015,"Alta fuente de hierro",IF(BD6>0.008,"Media fuente de hierro","Baja fuente de hierro")) -> Alta fuente de hierro | BR6: =IF(BE6>2,"Muy alto",IF(BE6>1,"Alto",IF(BE6>0.5,"Moderado","Bajo"))) & " en sodio" -> Bajo en sodio | BS6: =IF(BF6>2,"Altamente antiinflamatorio",IF(BF6>1,"Ligeramente antiinflamatorio",IF(BF6>0.5,"Neutro","Proinflamatorio"))) -> Ligeramente antiinflamatorio | BT6: =IF(BL6>0.4,"Muy alto en grasas",IF(BL6>0.3,"Alto en grasas",IF(BL6>0.2,"Moderado en grasas","Bajo en grasas"))) -> Bajo en grasas | BU6: =IF(BI6>1,"Alto riesgo de retención de líquidos",IF(BI6>0.5,"Riesgo moderado de retención","Equilibrio de líquidos ideal")) -> Equilibrio de líquidos ideal | BV6: =IF(BM6>0.5,"Alta",IF(BM6>0.2,"Media","Baja")) & " fuente de magnesio" -> Media fuente de magnesio | BW6: =IF(AV6>=0.5,"Alta fuente de Omega 3",IF(AV6>0.1,"Ligera fuente de Omega 3","Sin aporte de Omega 3")) -> Ligera fuente de Omega 3 | BX6: =IF(AX6>0.5,"Alerta: Alto en grasas trans",IF(AX6>0,"Contiene grasas trans","Libre de grasas trans")) -> Libre de grasas trans | BY6: =IF(AY6>=50,"Alto",IF(AY6>=10,"Medio","Bajo")) & " poder antioxidante" -> Alto poder antioxidante | BZ6: =IF(AZ6>=1,"Probiótico activo","Sin probióticos") -> Sin probióticos | CA6: =IF(OR(AX6>0.5, O6>15, J6>0), "Altamente inflamatorio", IF(OR(AV6>=0.5, AY6>=50), "Antiinflamatorio", IF(OR(AX6>0, O6>5), "Moderadamente inflamatorio", "Poco inflamatorio"))) -> Antiinflamatorio | CB6: =IF(ISNUMBER(SEARCH("miel", D6)), "No irritante (Uso condicionado SII)", IF(OR(J6>0, ISNUMBER(SEARCH("cacao", D6)), ISNUMBER(SEARCH("chocolate puro", D6))), "Altamente irritante", IF(OR(AND(O6>15, BI6>1), ISNUMBER(SEARCH("chocolate", D6))), "Moderadamente irritante", "No irritante"))) -> No irritante | CC6: =IF(AV6=0,"Sin Omega 3 para evaluar",IFERROR(IF(((T6-AV6)/AV6)>4,"Exceso relativo de Omega 6","Balance de omegas favorable"),"Sin Omega 3 para evaluar")) -> Exceso relativo de Omega 6
A7: =1+A6 -> 6 | B7: CEREALES | C7: Granos y harinas | D7: Cebada | F7: 1 | G7: 1 | H7: 330 | I7: 10.1 | J7: 0 | K7: 9.9 | L7: 62.1 | M7: 61.3 | N7: 0.8 | O7: 0 | P7: 15.6 | Q7: 1.2 | R7: 0.24 | S7: 0.15 | T7: 0.56 | U7: 0 | V7: 2.2 | W7: 0 | X7: 13 | Y7: 0 | Z7: 0.02 | AA7: 2.2 | AB7: 0.19 | AC7: 0.11 | AD7: 4.6 | AE7: 0.26 | AF7: 23 | AG7: 0 | AH7: 0.28 | AI7: 0 | AJ7: 0 | AK7: 29 | AL7: 221 | AM7: 2.5 | AN7: 0 | AO7: 2.1 | AP7: 79 | AQ7: 9 | AR7: 280 | AS7: 1.3 | AT7: 0.42 | AU7: 37.7 | AV7: =IFERROR(VLOOKUP(IFERROR(VLOOKUP(D7,Mapa_Similitud!$A$2:$B$2000,2,FALSE()),D7),Hoja1!$A$2:$K$1000,2,FALSE()),IFERROR(VLOOKUP(IFERROR(VLOOKUP(D7,Mapa_Similitud!$A$2:$B$2000,2,FALSE()),D7),Omega3_Referencia!$A$2:$E$100,3,FALSE()),0)) -> 0.08 | AW7: =IFERROR(VLOOKUP(IFERROR(VLOOKUP(D7,Mapa_Similitud!$A$2:$B$2000,2,FALSE()),D7),Hoja1!$A$2:$K$1000,3,FALSE()),IFERROR(VLOOKUP(IFERROR(VLOOKUP(D7,Mapa_Similitud!$A$2:$B$2000,2,FALSE()),D7),Omega3_Referencia!$A$2:$E$100,4,FALSE()),"N/A")) -> ALA | AX7: =IFERROR(VLOOKUP(IFERROR(VLOOKUP(D7,Mapa_Similitud!$A$2:$B$2000,2,FALSE()),D7),Hoja1!$A$2:$K$1000,5,FALSE()),0) -> 0 | AY7: =IFERROR(VLOOKUP(IFERROR(VLOOKUP(D7,Mapa_Similitud!$A$2:$B$2000,2,FALSE()),D7),Hoja1!$A$2:$K$1000,7,FALSE()),0) -> 72.9 | AZ7: =IFERROR(VLOOKUP(IFERROR(VLOOKUP(D7,Mapa_Similitud!$A$2:$B$2000,2,FALSE()),D7),Hoja1!$A$2:$K$1000,9,FALSE()),0) -> 0 | BA7: =IFERROR(K7/H7,0) -> 0.03 | BB7: =IFERROR(P7/H7,0) -> 0.047272727 | BC7: =IFERROR(AK7/H7,0) -> 0.087878788 | BD7: =IFERROR(AM7/H7,0) -> 0.0075757576 | BE7: =IFERROR(AQ7/H7,0) -> 0.027272727 | BF7: =IFERROR(T7/R7,0) -> 2.3333333 | BG7: =IFERROR(AK7/AL7,0) -> 0.13122172 | BH7: =IFERROR(R7/Q7,0) -> 0.2 | BI7: =IFERROR(AQ7/AR7,0) -> 0.032142857 | BJ7: =IFERROR(N7/L7,0) -> 0.012882448 | BK7: =IFERROR(P7/L7,0) -> 0.25120773 | BL7: =IFERROR((Q7*9)/H7,0) -> 0.032727273 | BM7: =IFERROR(AP7/H7,0) -> 0.23939394 | BN7: =IF(BA7>0.2,"Muy alta fuente de proteína",IF(BA7>0.15,"Alta fuente de proteína",IF(BA7>0.1,"Media fuente de proteína","Baja fuente de proteína"))) -> Baja fuente de proteína | BO7: =IF(BB7>0.03,"Alta",IF(BB7>0.015,"Media","Baja")) & " fuente de fibra" -> Alta fuente de fibra | BP7: =IF(BC7>1.5,"Alta fuente de calcio",IF(BC7>0.8,"Media fuente de calcio","Baja fuente de calcio")) -> Baja fuente de calcio | BQ7: =IF(BD7>0.015,"Alta fuente de hierro",IF(BD7>0.008,"Media fuente de hierro","Baja fuente de hierro")) -> Baja fuente de hierro | BR7: =IF(BE7>2,"Muy alto",IF(BE7>1,"Alto",IF(BE7>0.5,"Moderado","Bajo"))) & " en sodio" -> Bajo en sodio | BS7: =IF(BF7>2,"Altamente antiinflamatorio",IF(BF7>1,"Ligeramente antiinflamatorio",IF(BF7>0.5,"Neutro","Proinflamatorio"))) -> Altamente antiinflamatorio | BT7: =IF(BL7>0.4,"Muy alto en grasas",IF(BL7>0.3,"Alto en grasas",IF(BL7>0.2,"Moderado en grasas","Bajo en grasas"))) -> Bajo en grasas | BU7: =IF(BI7>1,"Alto riesgo de retención de líquidos",IF(BI7>0.5,"Riesgo moderado de retención","Equilibrio de líquidos ideal")) -> Equilibrio de líquidos ideal | BV7: =IF(BM7>0.5,"Alta",IF(BM7>0.2,"Media","Baja")) & " fuente de magnesio" -> Media fuente de magnesio | BW7: =IF(AV7>=0.5,"Alta fuente de Omega 3",IF(AV7>0.1,"Ligera fuente de Omega 3","Sin aporte de Omega 3")) -> Sin aporte de Omega 3 | BX7: =IF(AX7>0.5,"Alerta: Alto en grasas trans",IF(AX7>0,"Contiene grasas trans","Libre de grasas trans")) -> Libre de grasas trans | BY7: =IF(AY7>=50,"Alto",IF(AY7>=10,"Medio","Bajo")) & " poder antioxidante" -> Alto poder antioxidante | BZ7: =IF(AZ7>=1,"Probiótico activo","Sin probióticos") -> Sin probióticos | CA7: =IF(OR(AX7>0.5, O7>15, J7>0), "Altamente inflamatorio", IF(OR(AV7>=0.5, AY7>=50), "Antiinflamatorio", IF(OR(AX7>0, O7>5), "Moderadamente inflamatorio", "Poco inflamatorio"))) -> Antiinflamatorio | CB7: =IF(ISNUMBER(SEARCH("miel", D7)), "No irritante (Uso condicionado SII)", IF(OR(J7>0, ISNUMBER(SEARCH("cacao", D7)), ISNUMBER(SEARCH("chocolate puro", D7))), "Altamente irritante", IF(OR(AND(O7>15, BI7>1), ISNUMBER(SEARCH("chocolate", D7))), "Moderadamente irritante", "No irritante"))) -> No irritante | CC7: =IF(AV7=0,"Sin Omega 3 para evaluar",IFERROR(IF(((T7-AV7)/AV7)>4,"Exceso relativo de Omega 6","Balance de omegas favorable"),"Sin Omega 3 para evaluar")) -> Exceso relativo de Omega 6
A8: =1+A7 -> 7 | B8: CEREALES | C8: Granos y harinas | D8: Centeno | F8: 0.7 | G8: 1 | H8: 372 | I8: 0 | J8: 0 | K8: 14.8 | L8: 65.2 | M8: 64.2 | N8: 1.1 | O8: 0 | P8: 14.6 | Q8: 2.5 | R8: 0.29 | S8: 0.3 | T8: 1.1 | U8: 0 | V8: 1.2 | W8: 0 | X8: 7 | Y8: 0 | Z8: 1.9 | AA8: 5.9 | AB8: 0.32 | AC8: 0.25 | AD8: 4.3 | AE8: 0.29 | AF8: 38 | AG8: 0 | AH8: 1.5 | AI8: 0 | AJ8: 0 | AK8: 33 | AL8: 374 | AM8: 2.7 | AN8: 10 | AO8: 3.7 | AP8: 121 | AQ8: 6 | AR8: 264 | AS8: 0 | AT8: 0.45 | AU8: 35.3 | AV8: =IFERROR(VLOOKUP(IFERROR(VLOOKUP(D8,Mapa_Similitud!$A$2:$B$2000,2,FALSE()),D8),Hoja1!$A$2:$K$1000,2,FALSE()),IFERROR(VLOOKUP(IFERROR(VLOOKUP(D8,Mapa_Similitud!$A$2:$B$2000,2,FALSE()),D8),Omega3_Referencia!$A$2:$E$100,3,FALSE()),0)) -> 0.06 | AW8: =IFERROR(VLOOKUP(IFERROR(VLOOKUP(D8,Mapa_Similitud!$A$2:$B$2000,2,FALSE()),D8),Hoja1!$A$2:$K$1000,3,FALSE()),IFERROR(VLOOKUP(IFERROR(VLOOKUP(D8,Mapa_Similitud!$A$2:$B$2000,2,FALSE()),D8),Omega3_Referencia!$A$2:$E$100,4,FALSE()),"N/A")) -> ALA | AX8: =IFERROR(VLOOKUP(IFERROR(VLOOKUP(D8,Mapa_Similitud!$A$2:$B$2000,2,FALSE()),D8),Hoja1!$A$2:$K$1000,5,FALSE()),0) -> 0 | AY8: =IFERROR(VLOOKUP(IFERROR(VLOOKUP(D8,Mapa_Similitud!$A$2:$B$2000,2,FALSE()),D8),Hoja1!$A$2:$K$1000,7,FALSE()),0) -> 65 | AZ8: =IFERROR(VLOOKUP(IFERROR(VLOOKUP(D8,Mapa_Similitud!$A$2:$B$2000,2,FALSE()),D8),Hoja1!$A$2:$K$1000,9,FALSE()),0) -> 0 | BA8: =IFERROR(K8/H8,0) -> 0.039784946 | BB8: =IFERROR(P8/H8,0) -> 0.039247312 | BC8: =IFERROR(AK8/H8,0) -> 0.088709677 | BD8: =IFERROR(AM8/H8,0) -> 0.0072580645 | BE8: =IFERROR(AQ8/H8,0) -> 0.016129032 | BF8: =IFERROR(T8/R8,0) -> 3.7931034 | BG8: =IFERROR(AK8/AL8,0) -> 0.088235294 | BH8: =IFERROR(R8/Q8,0) -> 0.116 | BI8: =IFERROR(AQ8/AR8,0) -> 0.022727273 | BJ8: =IFERROR(N8/L8,0) -> 0.016871166 | BK8: =IFERROR(P8/L8,0) -> 0.22392638 | BL8: =IFERROR((Q8*9)/H8,0) -> 0.060483871 | BM8: =IFERROR(AP8/H8,0) -> 0.32526882 | BN8: =IF(BA8>0.2,"Muy alta fuente de proteína",IF(BA8>0.15,"Alta fuente de proteína",IF(BA8>0.1,"Media fuente de proteína","Baja fuente de proteína"))) -> Baja fuente de proteína | BO8: =IF(BB8>0.03,"Alta",IF(BB8>0.015,"Media","Baja")) & " fuente de fibra" -> Alta fuente de fibra | BP8: =IF(BC8>1.5,"Alta fuente de calcio",IF(BC8>0.8,"Media fuente de calcio","Baja fuente de calcio")) -> Baja fuente de calcio | BQ8: =IF(BD8>0.015,"Alta fuente de hierro",IF(BD8>0.008,"Media fuente de hierro","Baja fuente de hierro")) -> Baja fuente de hierro | BR8: =IF(BE8>2,"Muy alto",IF(BE8>1,"Alto",IF(BE8>0.5,"Moderado","Bajo"))) & " en sodio" -> Bajo en sodio | BS8: =IF(BF8>2,"Altamente antiinflamatorio",IF(BF8>1,"Ligeramente antiinflamatorio",IF(BF8>0.5,"Neutro","Proinflamatorio"))) -> Altamente antiinflamatorio | BT8: =IF(BL8>0.4,"Muy alto en grasas",IF(BL8>0.3,"Alto en grasas",IF(BL8>0.2,"Moderado en grasas","Bajo en grasas"))) -> Bajo en grasas | BU8: =IF(BI8>1,"Alto riesgo de retención de líquidos",IF(BI8>0.5,"Riesgo moderado de retención","Equilibrio de líquidos ideal")) -> Equilibrio de líquidos ideal | BV8: =IF(BM8>0.5,"Alta",IF(BM8>0.2,"Media","Baja")) & " fuente de magnesio" -> Media fuente de magnesio | BW8: =IF(AV8>=0.5,"Alta fuente de Omega 3",IF(AV8>0.1,"Ligera fuente de Omega 3","Sin aporte de Omega 3")) -> Sin aporte de Omega 3 | BX8: =IF(AX8>0.5,"Alerta: Alto en grasas trans",IF(AX8>0,"Contiene grasas trans","Libre de grasas trans")) -> Libre de grasas trans | BY8: =IF(AY8>=50,"Alto",IF(AY8>=10,"Medio","Bajo")) & " poder antioxidante" -> Alto poder antioxidante | BZ8: =IF(AZ8>=1,"Probiótico activo","Sin probióticos") -> Sin probióticos | CA8: =IF(OR(AX8>0.5, O8>15, J8>0), "Altamente inflamatorio", IF(OR(AV8>=0.5, AY8>=50), "Antiinflamatorio", IF(OR(AX8>0, O8>5), "Moderadamente inflamatorio", "Poco inflamatorio"))) -> Antiinflamatorio | CB8: =IF(ISNUMBER(SEARCH("miel", D8)), "No irritante (Uso condicionado SII)", IF(OR(J8>0, ISNUMBER(SEARCH("cacao", D8)), ISNUMBER(SEARCH("chocolate puro", D8))), "Altamente irritante", IF(OR(AND(O8>15, BI8>1), ISNUMBER(SEARCH("chocolate", D8))), "Moderadamente irritante", "No irritante"))) -> No irritante | CC8: =IF(AV8=0,"Sin Omega 3 para evaluar",IFERROR(IF(((T8-AV8)/AV8)>4,"Exceso relativo de Omega 6","Balance de omegas favorable"),"Sin Omega 3 para evaluar")) -> Exceso relativo de Omega 6
A9: =1+A8 -> 8 | B9: CEREALES | C9: Granos y harinas | D9: Fécula de maíz | E9: Maicena | F9: 0.6 | G9: 1 | H9: 356 | I9: 10.9 | J9: 0 | K9: 0.41 | L9: 88 | M9: 88 | N9: 0 | O9: 0 | P9: 0.6 | Q9: 0.08 | R9: 0.011 | S9: 0.02 | T9: 0.03 | U9: 0 | V9: 0 | W9: 0 | X9: 0 | Y9: 0 | Z9: 0 | AA9: 1 | AB9: 0 | AC9: 0.008 | AD9: 0.03 | AE9: 0.005 | AF9: 1 | AG9: 0 | AH9: 0 | AI9: 0 | AJ9: 0 | AK9: 1 | AL9: 30 | AM9: 0.5 | AN9: 2.5 | AO9: 0.3 | AP9: 2 | AQ9: 3 | AR9: 7 | AS9: 1 | AT9: 0.05 | AU9: 2.8 | AV9: =IFERROR(VLOOKUP(IFERROR(VLOOKUP(D9,Mapa_Similitud!$A$2:$B$2000,2,FALSE()),D9),Hoja1!$A$2:$K$1000,2,FALSE()),IFERROR(VLOOKUP(IFERROR(VLOOKUP(D9,Mapa_Similitud!$A$2:$B$2000,2,FALSE()),D9),Omega3_Referencia!$A$2:$E$100,3,FALSE()),0)) -> 0 | AW9: =IFERROR(VLOOKUP(IFERROR(VLOOKUP(D9,Mapa_Similitud!$A$2:$B$2000,2,FALSE()),D9),Hoja1!$A$2:$K$1000,3,FALSE()),IFERROR(VLOOKUP(IFERROR(VLOOKUP(D9,Mapa_Similitud!$A$2:$B$2000,2,FALSE()),D9),Omega3_Referencia!$A$2:$E$100,4,FALSE()),"N/A")) -> N/A | AX9: =IFERROR(VLOOKUP(IFERROR(VLOOKUP(D9,Mapa_Similitud!$A$2:$B$2000,2,FALSE()),D9),Hoja1!$A$2:$K$1000,5,FALSE()),0) -> 0 | AY9: =IFERROR(VLOOKUP(IFERROR(VLOOKUP(D9,Mapa_Similitud!$A$2:$B$2000,2,FALSE()),D9),Hoja1!$A$2:$K$1000,7,FALSE()),0) -> 0 | AZ9: =IFERROR(VLOOKUP(IFERROR(VLOOKUP(D9,Mapa_Similitud!$A$2:$B$2000,2,FALSE()),D9),Hoja1!$A$2:$K$1000,9,FALSE()),0) -> 0 | BA9: =IFERROR(K9/H9,0) -> 0.0011516854 | BB9: =IFERROR(P9/H9,0) -> 0.0016853933 | BC9: =IFERROR(AK9/H9,0) -> 0.0028089888 | BD9: =IFERROR(AM9/H9,0) -> 0.0014044944 | BE9: =IFERROR(AQ9/H9,0) -> 0.0084269663 | BF9: =IFERROR(T9/R9,0) -> 2.7272727 | BG9: =IFERROR(AK9/AL9,0) -> 0.033333333 | BH9: =IFERROR(R9/Q9,0) -> 0.1375 | BI9: =IFERROR(AQ9/AR9,0) -> 0.42857143 | BJ9: =IFERROR(N9/L9,0) -> 0 | BK9: =IFERROR(P9/L9,0) -> 0.0068181818 | BL9: =IFERROR((Q9*9)/H9,0) -> 0.0020224719 | BM9: =IFERROR(AP9/H9,0) -> 0.0056179775 | BN9: =IF(BA9>0.2,"Muy alta fuente de proteína",IF(BA9>0.15,"Alta fuente de proteína",IF(BA9>0.1,"Media fuente de proteína","Baja fuente de proteína"))) -> Baja fuente de proteína | BO9: =IF(BB9>0.03,"Alta",IF(BB9>0.015,"Media","Baja")) & " fuente de fibra" -> Baja fuente de fibra | BP9: =IF(BC9>1.5,"Alta fuente de calcio",IF(BC9>0.8,"Media fuente de calcio","Baja fuente de calcio")) -> Baja fuente de calcio | BQ9: =IF(BD9>0.015,"Alta fuente de hierro",IF(BD9>0.008,"Media fuente de hierro","Baja fuente de hierro")) -> Baja fuente de hierro | BR9: =IF(BE9>2,"Muy alto",IF(BE9>1,"Alto",IF(BE9>0.5,"Moderado","Bajo"))) & " en sodio" -> Bajo en sodio | BS9: =IF(BF9>2,"Altamente antiinflamatorio",IF(BF9>1,"Ligeramente antiinflamatorio",IF(BF9>0.5,"Neutro","Proinflamatorio"))) -> Altamente antiinflamatorio | BT9: =IF(BL9>0.4,"Muy alto en grasas",IF(BL9>0.3,"Alto en grasas",IF(BL9>0.2,"Moderado en grasas","Bajo en grasas"))) -> Bajo en grasas | BU9: =IF(BI9>1,"Alto riesgo de retención de líquidos",IF(BI9>0.5,"Riesgo moderado de retención","Equilibrio de líquidos ideal")) -> Equilibrio de líquidos ideal | BV9: =IF(BM9>0.5,"Alta",IF(BM9>0.2,"Media","Baja")) & " fuente de magnesio" -> Baja fuente de magnesio | BW9: =IF(AV9>=0.5,"Alta fuente de Omega 3",IF(AV9>0.1,"Ligera fuente de Omega 3","Sin aporte de Omega 3")) -> Sin aporte de Omega 3 | BX9: =IF(AX9>0.5,"Alerta: Alto en grasas trans",IF(AX9>0,"Contiene grasas trans","Libre de grasas trans")) -> Libre de grasas trans | BY9: =IF(AY9>=50,"Alto",IF(AY9>=10,"Medio","Bajo")) & " poder antioxidante" -> Bajo poder antioxidante | BZ9: =IF(AZ9>=1,"Probiótico activo","Sin probióticos") -> Sin probióticos | CA9: =IF(OR(AX9>0.5, O9>15, J9>0), "Altamente inflamatorio", IF(OR(AV9>=0.5, AY9>=50), "Antiinflamatorio", IF(OR(AX9>0, O9>5), "Moderadamente inflamatorio", "Poco inflamatorio"))) -> Poco inflamatorio | CB9: =IF(ISNUMBER(SEARCH("miel", D9)), "No irritante (Uso condicionado SII)", IF(OR(J9>0, ISNUMBER(SEARCH("cacao", D9)), ISNUMBER(SEARCH("chocolate puro", D9))), "Altamente irritante", IF(OR(AND(O9>15, BI9>1), ISNUMBER(SEARCH("chocolate", D9))), "Moderadamente irritante", "No irritante"))) -> No irritante | CC9: =IF(AV9=0,"Sin Omega 3 para evaluar",IFERROR(IF(((T9-AV9)/AV9)>4,"Exceso relativo de Omega 6","Balance de omegas favorable"),"Sin Omega 3 para evaluar")) -> Sin Omega 3 para evaluar
A10: =1+A9 -> 9 | B10: CEREALES | C10: Granos y harinas | D10: Harina de arroz | F10: 1.2 | G10: 1 | H10: 349 | I10: 11.9 | J10: 0 | K10: 7.6 | L10: 78 | M10: 77.9 | N10: 0.12 | O10: 0 | P10: 0 | Q10: 0.7 | R10: 0.2 | S10: 0.22 | T10: 0.19 | U10: 0 | V10: 0 | W10: 0 | X10: 0 | Y10: 0 | Z10: 0.11 | AA10: 0 | AB10: 0.14 | AC10: 0.021 | AD10: 2.6 | AE10: 0.44 | AF10: 4 | AG10: 0 | AH10: 0 | AI10: 0 | AJ10: 0 | AK10: 10 | AL10: 98 | AM10: 0.35 | AN10: 0 | AO10: 0.8 | AP10: 35 | AQ10: 0 | AR10: 76 | AS10: 0 | AT10: 0 | AU10: 0 | AV10: =IFERROR(VLOOKUP(IFERROR(VLOOKUP(D10,Mapa_Similitud!$A$2:$B$2000,2,FALSE()),D10),Hoja1!$A$2:$K$1000,2,FALSE()),IFERROR(VLOOKUP(IFERROR(VLOOKUP(D10,Mapa_Similitud!$A$2:$B$2000,2,FALSE()),D10),Omega3_Referencia!$A$2:$E$100,3,FALSE()),0)) -> 0.01 | AW10: =IFERROR(VLOOKUP(IFERROR(VLOOKUP(D10,Mapa_Similitud!$A$2:$B$2000,2,FALSE()),D10),Hoja1!$A$2:$K$1000,3,FALSE()),IFERROR(VLOOKUP(IFERROR(VLOOKUP(D10,Mapa_Similitud!$A$2:$B$2000,2,FALSE()),D10),Omega3_Referencia!$A$2:$E$100,4,FALSE()),"N/A")) -> ALA | AX10: =IFERROR(VLOOKUP(IFERROR(VLOOKUP(D10,Mapa_Similitud!$A$2:$B$2000,2,FALSE()),D10),Hoja1!$A$2:$K$1000,5,FALSE()),0) -> 0 | AY10: =IFERROR(VLOOKUP(IFERROR(VLOOKUP(D10,Mapa_Similitud!$A$2:$B$2000,2,FALSE()),D10),Hoja1!$A$2:$K$1000,7,FALSE()),0) -> 1 | AZ10: =IFERROR(VLOOKUP(IFERROR(VLOOKUP(D10,Mapa_Similitud!$A$2:$B$2000,2,FALSE()),D10),Hoja1!$A$2:$K$1000,9,FALSE()),0) -> 0 | BA10: =IFERROR(K10/H10,0) -> 0.021776504 | BB10: =IFERROR(P10/H10,0) -> 0 | BC10: =IFERROR(AK10/H10,0) -> 0.028653295 | BD10: =IFERROR(AM10/H10,0) -> 0.0010028653 | BE10: =IFERROR(AQ10/H10,0) -> 0 | BF10: =IFERROR(T10/R10,0) -> 0.95 | BG10: =IFERROR(AK10/AL10,0) -> 0.10204082 | BH10: =IFERROR(R10/Q10,0) -> 0.28571429 | BI10: =IFERROR(AQ10/AR10,0) -> 0 | BJ10: =IFERROR(N10/L10,0) -> 0.0015384615 | BK10: =IFERROR(P10/L10,0) -> 0 | BL10: =IFERROR((Q10*9)/H10,0) -> 0.018051576 | BM10: =IFERROR(AP10/H10,0) -> 0.10028653 | BN10: =IF(BA10>0.2,"Muy alta fuente de proteína",IF(BA10>0.15,"Alta fuente de proteína",IF(BA10>0.1,"Media fuente de proteína","Baja fuente de proteína"))) -> Baja fuente de proteína | BO10: =IF(BB10>0.03,"Alta",IF(BB10>0.015,"Media","Baja")) & " fuente de fibra" -> Baja fuente de fibra | BP10: =IF(BC10>1.5,"Alta fuente de calcio",IF(BC10>0.8,"Media fuente de calcio","Baja fuente de calcio")) -> Baja fuente de calcio | BQ10: =IF(BD10>0.015,"Alta fuente de hierro",IF(BD10>0.008,"Media fuente de hierro","Baja fuente de hierro")) -> Baja fuente de hierro | BR10: =IF(BE10>2,"Muy alto",IF(BE10>1,"Alto",IF(BE10>0.5,"Moderado","Bajo"))) & " en sodio" -> Bajo en sodio | BS10: =IF(BF10>2,"Altamente antiinflamatorio",IF(BF10>1,"Ligeramente antiinflamatorio",IF(BF10>0.5,"Neutro","Proinflamatorio"))) -> Neutro | BT10: =IF(BL10>0.4,"Muy alto en grasas",IF(BL10>0.3,"Alto en grasas",IF(BL10>0.2,"Moderado en grasas","Bajo en grasas"))) -> Bajo en grasas | BU10: =IF(BI10>1,"Alto riesgo de retención de líquidos",IF(BI10>0.5,"Riesgo moderado de retención","Equilibrio de líquidos ideal")) -> Equilibrio de líquidos ideal | BV10: =IF(BM10>0.5,"Alta",IF(BM10>0.2,"Media","Baja")) & " fuente de magnesio" -> Baja fuente de magnesio | BW10: =IF(AV10>=0.5,"Alta fuente de Omega 3",IF(AV10>0.1,"Ligera fuente de Omega 3","Sin aporte de Omega 3")) -> Sin aporte de Omega 3 | BX10: =IF(AX10>0.5,"Alerta: Alto en grasas trans",IF(AX10>0,"Contiene grasas trans","Libre de grasas trans")) -> Libre de grasas trans | BY10: =IF(AY10>=50,"Alto",IF(AY10>=10,"Medio","Bajo")) & " poder antioxidante" -> Bajo poder antioxidante | BZ10: =IF(AZ10>=1,"Probiótico activo","Sin probióticos") -> Sin probióticos | CA10: =IF(OR(AX10>0.5, O10>15, J10>0), "Altamente inflamatorio", IF(OR(AV10>=0.5, AY10>=50), "Antiinflamatorio", IF(OR(AX10>0, O10>5), "Moderadamente inflamatorio", "Poco inflamatorio"))) -> Poco inflamatorio | CB10: =IF(ISNUMBER(SEARCH("miel", D10)), "No irritante (Uso condicionado SII)", IF(OR(J10>0, ISNUMBER(SEARCH("cacao", D10)), ISNUMBER(SEARCH("chocolate puro", D10))), "Altamente irritante", IF(OR(AND(O10>15, BI10>1), ISNUMBER(SEARCH("chocolate", D10))), "Moderadamente irritante", "No irritante"))) -> No irritante | CC10: =IF(AV10=0,"Sin Omega 3 para evaluar",IFERROR(IF(((T10-AV10)/AV10)>4,"Exceso relativo de Omega 6","Balance de omegas favorable"),"Sin Omega 3 para evaluar")) -> Exceso relativo de Omega 6
A11: =1+A10 -> 10 | B11: CEREALES | C11: Granos y harinas | D11: Harina de centeno | F11: 1.5 | G11: 1 | H11: 326 | I11: 13.4 | J11: 0 | K11: 10 | L11: 59.7 | M11: 59.7 | N11: 0 | O11: 0 | P11: 15 | Q11: 1.9 | R11: 0.24 | S11: 0.2 | T11: 0.85 | U11: 0 | V11: 0 | W11: 0 | X11: 0 | Y11: 0 | Z11: 1.5 | AA11: 0 | AB11: 0.3 | AC11: 0.2 | AD11: 1.6 | AE11: 0.3 | AF11: 70 | AG11: 0 | AH11: 0 | AI11: 0 | AJ11: 0 | AK11: 27 | AL11: 286 | AM11: 2.6 | AN11: 0 | AO11: 3 | AP11: 82 | AQ11: 2 | AR11: 390 | AS11: 0 | AT11: 0 | AU11: 14.4 | AV11: =IFERROR(VLOOKUP(IFERROR(VLOOKUP(D11,Mapa_Similitud!$A$2:$B$2000,2,FALSE()),D11),Hoja1!$A$2:$K$1000,2,FALSE()),IFERROR(VLOOKUP(IFERROR(VLOOKUP(D11,Mapa_Similitud!$A$2:$B$2000,2,FALSE()),D11),Omega3_Referencia!$A$2:$E$100,3,FALSE()),0)) -> 0.04 | AW11: =IFERROR(VLOOKUP(IFERROR(VLOOKUP(D11,Mapa_Similitud!$A$2:$B$2000,2,FALSE()),D11),Hoja1!$A$2:$K$1000,3,FALSE()),IFERROR(VLOOKUP(IFERROR(VLOOKUP(D11,Mapa_Similitud!$A$2:$B$2000,2,FALSE()),D11),Omega3_Referencia!$A$2:$E$100,4,FALSE()),"N/A")) -> ALA | AX11: =IFERROR(VLOOKUP(IFERROR(VLOOKUP(D11,Mapa_Similitud!$A$2:$B$2000,2,FALSE()),D11),Hoja1!$A$2:$K$1000,5,FALSE()),0) -> 0 | AY11: =IFERROR(VLOOKUP(IFERROR(VLOOKUP(D11,Mapa_Similitud!$A$2:$B$2000,2,FALSE()),D11),Hoja1!$A$2:$K$1000,7,FALSE()),0) -> 45 | AZ11: =IFERROR(VLOOKUP(IFERROR(VLOOKUP(D11,Mapa_Similitud!$A$2:$B$2000,2,FALSE()),D11),Hoja1!$A$2:$K$1000,9,FALSE()),0) -> 0 | BA11: =IFERROR(K11/H11,0) -> 0.030674847 | BB11: =IFERROR(P11/H11,0) -> 0.04601227 | BC11: =IFERROR(AK11/H11,0) -> 0.082822086 | BD11: =IFERROR(AM11/H11,0) -> 0.0079754601 | BE11: =IFERROR(AQ11/H11,0) -> 0.0061349693 | BF11: =IFERROR(T11/R11,0) -> 3.5416667 | BG11: =IFERROR(AK11/AL11,0) -> 0.094405594 | BH11: =IFERROR(R11/Q11,0) -> 0.12631579 | BI11: =IFERROR(AQ11/AR11,0) -> 0.0051282051 | BJ11: =IFERROR(N11/L11,0) -> 0 | BK11: =IFERROR(P11/L11,0) -> 0.25125628 | BL11: =IFERROR((Q11*9)/H11,0) -> 0.052453988 | BM11: =IFERROR(AP11/H11,0) -> 0.25153374 | BN11: =IF(BA11>0.2,"Muy alta fuente de proteína",IF(BA11>0.15,"Alta fuente de proteína",IF(BA11>0.1,"Media fuente de proteína","Baja fuente de proteína"))) -> Baja fuente de proteína | BO11: =IF(BB11>0.03,"Alta",IF(BB11>0.015,"Media","Baja")) & " fuente de fibra" -> Alta fuente de fibra | BP11: =IF(BC11>1.5,"Alta fuente de calcio",IF(BC11>0.8,"Media fuente de calcio","Baja fuente de calcio")) -> Baja fuente de calcio | BQ11: =IF(BD11>0.015,"Alta fuente de hierro",IF(BD11>0.008,"Media fuente de hierro","Baja fuente de hierro")) -> Baja fuente de hierro | BR11: =IF(BE11>2,"Muy alto",IF(BE11>1,"Alto",IF(BE11>0.5,"Moderado","Bajo"))) & " en sodio" -> Bajo en sodio | BS11: =IF(BF11>2,"Altamente antiinflamatorio",IF(BF11>1,"Ligeramente antiinflamatorio",IF(BF11>0.5,"Neutro","Proinflamatorio"))) -> Altamente antiinflamatorio | BT11: =IF(BL11>0.4,"Muy alto en grasas",IF(BL11>0.3,"Alto en grasas",IF(BL11>0.2,"Moderado en grasas","Bajo en grasas"))) -> Bajo en grasas | BU11: =IF(BI11>1,"Alto riesgo de retención de líquidos",IF(BI11>0.5,"Riesgo moderado de retención","Equilibrio de líquidos ideal")) -> Equilibrio de líquidos ideal | BV11: =IF(BM11>0.5,"Alta",IF(BM11>0.2,"Media","Baja")) & " fuente de magnesio" -> Media fuente de magnesio | BW11: =IF(AV11>=0.5,"Alta fuente de Omega 3",IF(AV11>0.1,"Ligera fuente de Omega 3","Sin aporte de Omega 3")) -> Sin aporte de Omega 3 | BX11: =IF(AX11>0.5,"Alerta: Alto en grasas trans",IF(AX11>0,"Contiene grasas trans","Libre de grasas trans")) -> Libre de grasas trans | BY11: =IF(AY11>=50,"Alto",IF(AY11>=10,"Medio","Bajo")) & " poder antioxidante" -> Medio poder antioxidante | BZ11: =IF(AZ11>=1,"Probiótico activo","Sin probióticos") -> Sin probióticos | CA11: =IF(OR(AX11>0.5, O11>15, J11>0), "Altamente inflamatorio", IF(OR(AV11>=0.5, AY11>=50), "Antiinflamatorio", IF(OR(AX11>0, O11>5), "Moderadamente inflamatorio", "Poco inflamatorio"))) -> Poco inflamatorio | CB11: =IF(ISNUMBER(SEARCH("miel", D11)), "No irritante (Uso condicionado SII)", IF(OR(J11>0, ISNUMBER(SEARCH("cacao", D11)), ISNUMBER(SEARCH("chocolate puro", D11))), "Altamente irritante", IF(OR(AND(O11>15, BI11>1), ISNUMBER(SEARCH("chocolate", D11))), "Moderadamente irritante", "No irritante"))) -> No irritante | CC11: =IF(AV11=0,"Sin Omega 3 para evaluar",IFERROR(IF(((T11-AV11)/AV11)>4,"Exceso relativo de Omega 6","Balance de omegas favorable"),"Sin Omega 3 para evaluar")) -> Exceso relativo de Omega 6
A12: =1+A11 -> 11 | B12: CEREALES | C12: Granos y harinas | D12: Harina de maíz | F12: 0.6 | G12: 1 | H12: 342 | I12: 13.2 | J12: 0 | K12: 8.3 | L12: 66.3 | M12: 66.3 | N12: 0 | O12: 0 | P12: 9.4 | Q12: 2.8 | R12: 0.35 | S12: 0.88 | T12: 1.4 | U12: 0 | V12: 50 | W12: 0 | X12: 300 | Y12: 0 | Z12: 0 | AA12: 1 | AB12: 0.44 | AC12: 0.13 | AD12: 0.82 | AE12: 0.06 | AF12: 10 | AG12: 0 | AH12: 0.55 | AI12: 6.6 | AJ12: 0 | AK12: 18 | AL12: 39 | AM12: 2.4 | AN12: 80 | AO12: 1.6 | AP12: 47 | AQ12: 0.7 | AR12: 120 | AS12: 0.46 | AT12: 0.13 | AU12: 15.4 | AV12: =IFERROR(VLOOKUP(IFERROR(VLOOKUP(D12,Mapa_Similitud!$A$2:$B$2000,2,FALSE()),D12),Hoja1!$A$2:$K$1000,2,FALSE()),IFERROR(VLOOKUP(IFERROR(VLOOKUP(D12,Mapa_Similitud!$A$2:$B$2000,2,FALSE()),D12),Omega3_Referencia!$A$2:$E$100,3,FALSE()),0)) -> 0.03 | AW12: =IFERROR(VLOOKUP(IFERROR(VLOOKUP(D12,Mapa_Similitud!$A$2:$B$2000,2,FALSE()),D12),Hoja1!$A$2:$K$1000,3,FALSE()),IFERROR(VLOOKUP(IFERROR(VLOOKUP(D12,Mapa_Similitud!$A$2:$B$2000,2,FALSE()),D12),Omega3_Referencia!$A$2:$E$100,4,FALSE()),"N/A")) -> ALA | AX12: =IFERROR(VLOOKUP(IFERROR(VLOOKUP(D12,Mapa_Similitud!$A$2:$B$2000,2,FALSE()),D12),Hoja1!$A$2:$K$1000,5,FALSE()),0) -> 0 | AY12: =IFERROR(VLOOKUP(IFERROR(VLOOKUP(D12,Mapa_Similitud!$A$2:$B$2000,2,FALSE()),D12),Hoja1!$A$2:$K$1000,7,FALSE()),0) -> 10 | AZ12: =IFERROR(VLOOKUP(IFERROR(VLOOKUP(D12,Mapa_Similitud!$A$2:$B$2000,2,FALSE()),D12),Hoja1!$A$2:$K$1000,9,FALSE()),0) -> 0 | BA12: =IFERROR(K12/H12,0) -> 0.024269006 | BB12: =IFERROR(P12/H12,0) -> 0.02748538 | BC12: =IFERROR(AK12/H12,0) -> 0.052631579 | BD12: =IFERROR(AM12/H12,0) -> 0.0070175439 | BE12: =IFERROR(AQ12/H12,0) -> 0.0020467836 | BF12: =IFERROR(T12/R12,0) -> 4 | BG12: =IFERROR(AK12/AL12,0) -> 0.46153846 | BH12: =IFERROR(R12/Q12,0) -> 0.125 | BI12: =IFERROR(AQ12/AR12,0) -> 0.0058333333 | BJ12: =IFERROR(N12/L12,0) -> 0 | BK12: =IFERROR(P12/L12,0) -> 0.14177979 | BL12: =IFERROR((Q12*9)/H12,0) -> 0.073684211 | BM12: =IFERROR(AP12/H12,0) -> 0.1374269 | BN12: =IF(BA12>0.2,"Muy alta fuente de proteína",IF(BA12>0.15,"Alta fuente de proteína",IF(BA12>0.1,"Media fuente de proteína","Baja fuente de proteína"))) -> Baja fuente de proteína | BO12: =IF(BB12>0.03,"Alta",IF(BB12>0.015,"Media","Baja")) & " fuente de fibra" -> Media fuente de fibra | BP12: =IF(BC12>1.5,"Alta fuente de calcio",IF(BC12>0.8,"Media fuente de calcio","Baja fuente de calcio")) -> Baja fuente de calcio | BQ12: =IF(BD12>0.015,"Alta fuente de hierro",IF(BD12>0.008,"Media fuente de hierro","Baja fuente de hierro")) -> Baja fuente de hierro | BR12: =IF(BE12>2,"Muy alto",IF(BE12>1,"Alto",IF(BE12>0.5,"Moderado","Bajo"))) & " en sodio" -> Bajo en sodio | BS12: =IF(BF12>2,"Altamente antiinflamatorio",IF(BF12>1,"Ligeramente antiinflamatorio",IF(BF12>0.5,"Neutro","Proinflamatorio"))) -> Altamente antiinflamatorio | BT12: =IF(BL12>0.4,"Muy alto en grasas",IF(BL12>0.3,"Alto en grasas",IF(BL12>0.2,"Moderado en grasas","Bajo en grasas"))) -> Bajo en grasas | BU12: =IF(BI12>1,"Alto riesgo de retención de líquidos",IF(BI12>0.5,"Riesgo moderado de retención","Equilibrio de líquidos ideal")) -> Equilibrio de líquidos ideal | BV12: =IF(BM12>0.5,"Alta",IF(BM12>0.2,"Media","Baja")) & " fuente de magnesio" -> Baja fuente de magnesio | BW12: =IF(AV12>=0.5,"Alta fuente de Omega 3",IF(AV12>0.1,"Ligera fuente de Omega 3","Sin aporte de Omega 3")) -> Sin aporte de Omega 3 | BX12: =IF(AX12>0.5,"Alerta: Alto en grasas trans",IF(AX12>0,"Contiene grasas trans","Libre de grasas trans")) -> Libre de grasas trans | BY12: =IF(AY12>=50,"Alto",IF(AY12>=10,"Medio","Bajo")) & " poder antioxidante" -> Medio poder antioxidante | BZ12: =IF(AZ12>=1,"Probiótico activo","Sin probióticos") -> Sin probióticos | CA12: =IF(OR(AX12>0.5, O12>15, J12>0), "Altamente inflamatorio", IF(OR(AV12>=0.5, AY12>=50), "Antiinflamatorio", IF(OR(AX12>0, O12>5), "Moderadamente inflamatorio", "Poco inflamatorio"))) -> Poco inflamatorio | CB12: =IF(ISNUMBER(SEARCH("miel", D12)), "No irritante (Uso condicionado SII)", IF(OR(J12>0, ISNUMBER(SEARCH("cacao", D12)), ISNUMBER(SEARCH("chocolate puro", D12))), "Altamente irritante", IF(OR(AND(O12>15, BI12>1), ISNUMBER(SEARCH("chocolate", D12))), "Moderadamente irritante", "No irritante"))) -> No irritante | CC12: =IF(AV12=0,"Sin Omega 3 para evaluar",IFERROR(IF(((T12-AV12)/AV12)>4,"Exceso relativo de Omega 6","Balance de omegas favorable"),"Sin Omega 3 para evaluar")) -> Exceso relativo de Omega 6
A13: =1+A12 -> 12 | B13: CEREALES | C13: Granos y harinas | D13: Harina de trigo | F13: 0.45 | G13: 1 | H13: 341 | I13: 14 | J13: 0 | K13: 9.9 | L13: 70.6 | M13: 69.9 | N13: 0.7 | O13: 0 | P13: 4.3 | Q13: 1.2 | R13: 0.16 | S13: 0.13 | T13: 0.51 | U13: 0 | V13: 0.17 | W13: 0 | X13: 1 | Y13: 0 | Z13: 0.34 | AA13: 32.7 | AB13: 0.11 | AC13: 0.03 | AD13: 2.3 | AE13: 0.1 | AF13: 16 | AG13: 0 | AH13: 0.4 | AI13: 1.1 | AJ13: 0 | AK13: 17 | AL13: 108 | AM13: 1 | AN13: 10 | AO13: 0.78 | AP13: 23 | AQ13: 2 | AR13: 146 | AS13: 0.69 | AT13: 0.14 | AU13: 4 | AV13: =IFERROR(VLOOKUP(IFERROR(VLOOKUP(D13,Mapa_Similitud!$A$2:$B$2000,2,FALSE()),D13),Hoja1!$A$2:$K$1000,2,FALSE()),IFERROR(VLOOKUP(IFERROR(VLOOKUP(D13,Mapa_Similitud!$A$2:$B$2000,2,FALSE()),D13),Omega3_Referencia!$A$2:$E$100,3,FALSE()),0)) -> 0.02 | AW13: =IFERROR(VLOOKUP(IFERROR(VLOOKUP(D13,Mapa_Similitud!$A$2:$B$2000,2,FALSE()),D13),Hoja1!$A$2:$K$1000,3,FALSE()),IFERROR(VLOOKUP(IFERROR(VLOOKUP(D13,Mapa_Similitud!$A$2:$B$2000,2,FALSE()),D13),Omega3_Referencia!$A$2:$E$100,4,FALSE()),"N/A")) -> ALA | AX13: =IFERROR(VLOOKUP(IFERROR(VLOOKUP(D13,Mapa_Similitud!$A$2:$B$2000,2,FALSE()),D13),Hoja1!$A$2:$K$1000,5,FALSE()),0) -> 0 | AY13: =IFERROR(VLOOKUP(IFERROR(VLOOKUP(D13,Mapa_Similitud!$A$2:$B$2000,2,FALSE()),D13),Hoja1!$A$2:$K$1000,7,FALSE()),0) -> 68.3 | AZ13: =IFERROR(VLOOKUP(IFERROR(VLOOKUP(D13,Mapa_Similitud!$A$2:$B$2000,2,FALSE()),D13),Hoja1!$A$2:$K$1000,9,FALSE()),0) -> 0 | BA13: =IFERROR(K13/H13,0) -> 0.029032258 | BB13: =IFERROR(P13/H13,0) -> 0.012609971 | BC13: =IFERROR(AK13/H13,0) -> 0.049853372 | BD13: =IFERROR(AM13/H13,0) -> 0.0029325513 | BE13: =IFERROR(AQ13/H13,0) -> 0.0058651026 | BF13: =IFERROR(T13/R13,0) -> 3.1875 | BG13: =IFERROR(AK13/AL13,0) -> 0.15740741 | BH13: =IFERROR(R13/Q13,0) -> 0.13333333 | BI13: =IFERROR(AQ13/AR13,0) -> 0.01369863 | BJ13: =IFERROR(N13/L13,0) -> 0.0099150142 | BK13: =IFERROR(P13/L13,0) -> 0.060906516 | BL13: =IFERROR((Q13*9)/H13,0) -> 0.031671554 | BM13: =IFERROR(AP13/H13,0) -> 0.06744868 | BN13: =IF(BA13>0.2,"Muy alta fuente de proteína",IF(BA13>0.15,"Alta fuente de proteína",IF(BA13>0.1,"Media fuente de proteína","Baja fuente de proteína"))) -> Baja fuente de proteína | BO13: =IF(BB13>0.03,"Alta",IF(BB13>0.015,"Media","Baja")) & " fuente de fibra" -> Baja fuente de fibra | BP13: =IF(BC13>1.5,"Alta fuente de calcio",IF(BC13>0.8,"Media fuente de calcio","Baja fuente de calcio")) -> Baja fuente de calcio | BQ13: =IF(BD13>0.015,"Alta fuente de hierro",IF(BD13>0.008,"Media fuente de hierro","Baja fuente de hierro")) -> Baja fuente de hierro | BR13: =IF(BE13>2,"Muy alto",IF(BE13>1,"Alto",IF(BE13>0.5,"Moderado","Bajo"))) & " en sodio" -> Bajo en sodio | BS13: =IF(BF13>2,"Altamente antiinflamatorio",IF(BF13>1,"Ligeramente antiinflamatorio",IF(BF13>0.5,"Neutro","Proinflamatorio"))) -> Altamente antiinflamatorio | BT13: =IF(BL13>0.4,"Muy alto en grasas",IF(BL13>0.3,"Alto en grasas",IF(BL13>0.2,"Moderado en grasas","Bajo en grasas"))) -> Bajo en grasas | BU13: =IF(BI13>1,"Alto riesgo de retención de líquidos",IF(BI13>0.5,"Riesgo moderado de retención","Equilibrio de líquidos ideal")) -> Equilibrio de líquidos ideal | BV13: =IF(BM13>0.5,"Alta",IF(BM13>0.2,"Media","Baja")) & " fuente de magnesio" -> Baja fuente de magnesio | BW13: =IF(AV13>=0.5,"Alta fuente de Omega 3",IF(AV13>0.1,"Ligera fuente de Omega 3","Sin aporte de Omega 3")) -> Sin aporte de Omega 3 | BX13: =IF(AX13>0.5,"Alerta: Alto en grasas trans",IF(AX13>0,"Contiene grasas trans","Libre de grasas trans")) -> Libre de grasas trans | BY13: =IF(AY13>=50,"Alto",IF(AY13>=10,"Medio","Bajo")) & " poder antioxidante" -> Alto poder antioxidante | BZ13: =IF(AZ13>=1,"Probiótico activo","Sin probióticos") -> Sin probióticos | CA13: =IF(OR(AX13>0.5, O13>15, J13>0), "Altamente inflamatorio", IF(OR(AV13>=0.5, AY13>=50), "Antiinflamatorio", IF(OR(AX13>0, O13>5), "Moderadamente inflamatorio", "Poco inflamatorio"))) -> Antiinflamatorio | CB13: =IF(ISNUMBER(SEARCH("miel", D13)), "No irritante (Uso condicionado SII)", IF(OR(J13>0, ISNUMBER(SEARCH("cacao", D13)), ISNUMBER(SEARCH("chocolate puro", D13))), "Altamente irritante", IF(OR(AND(O13>15, BI13>1), ISNUMBER(SEARCH("chocolate", D13))), "Moderadamente irritante", "No irritante"))) -> No irritante | CC13: =IF(AV13=0,"Sin Omega 3 para evaluar",IFERROR(IF(((T13-AV13)/AV13)>4,"Exceso relativo de Omega 6","Balance de omegas favorable"),"Sin Omega 3 para evaluar")) -> Exceso relativo de Omega 6
A14: =1+A13 -> 13 | B14: CEREALES | C14: Granos y harinas | D14: Harina integral de trigo | F14: 0.7 | G14: 1 | H14: 322 | I14: 17.8 | J14: 0 | K14: 12.7 | L14: 58.3 | M14: 56.2 | N14: 2.1 | O14: 0 | P14: 9 | Q14: 2.2 | R14: 0.28 | S14: 0.21 | T14: 0.89 | U14: 0 | V14: 0 | W14: 0 | X14: 0 | Y14: 0 | Z14: 1.4 | AA14: 65.5 | AB14: 0.47 | AC14: 0.09 | AD14: 8.2 | AE14: 0.5 | AF14: 57 | AG14: 0 | AH14: 0.8 | AI14: 7 | AJ14: 0 | AK14: 38 | AL14: 320 | AM14: 3.9 | AN14: 0 | AO14: 2.9 | AP14: 120 | AQ14: 3 | AR14: 340 | AS14: 3.1 | AT14: 0.45 | AU14: 53 | AV14: =IFERROR(VLOOKUP(IFERROR(VLOOKUP(D14,Mapa_Similitud!$A$2:$B$2000,2,FALSE()),D14),Hoja1!$A$2:$K$1000,2,FALSE()),IFERROR(VLOOKUP(IFERROR(VLOOKUP(D14,Mapa_Similitud!$A$2:$B$2000,2,FALSE()),D14),Omega3_Referencia!$A$2:$E$100,3,FALSE()),0)) -> 0.07 | AW14: =IFERROR(VLOOKUP(IFERROR(VLOOKUP(D14,Mapa_Similitud!$A$2:$B$2000,2,FALSE()),D14),Hoja1!$A$2:$K$1000,3,FALSE()),IFERROR(VLOOKUP(IFERROR(VLOOKUP(D14,Mapa_Similitud!$A$2:$B$2000,2,FALSE()),D14),Omega3_Referencia!$A$2:$E$100,4,FALSE()),"N/A")) -> ALA | AX14: =IFERROR(VLOOKUP(IFERROR(VLOOKUP(D14,Mapa_Similitud!$A$2:$B$2000,2,FALSE()),D14),Hoja1!$A$2:$K$1000,5,FALSE()),0) -> 0 | AY14: =IFERROR(VLOOKUP(IFERROR(VLOOKUP(D14,Mapa_Similitud!$A$2:$B$2000,2,FALSE()),D14),Hoja1!$A$2:$K$1000,7,FALSE()),0) -> 90.5 | AZ14: =IFERROR(VLOOKUP(IFERROR(VLOOKUP(D14,Mapa_Similitud!$A$2:$B$2000,2,FALSE()),D14),Hoja1!$A$2:$K$1000,9,FALSE()),0) -> 0 | BA14: =IFERROR(K14/H14,0) -> 0.039440994 | BB14: =IFERROR(P14/H14,0) -> 0.027950311 | BC14: =IFERROR(AK14/H14,0) -> 0.11801242 | BD14: =IFERROR(AM14/H14,0) -> 0.012111801 | BE14: =IFERROR(AQ14/H14,0) -> 0.0093167702 | BF14: =IFERROR(T14/R14,0) -> 3.1785714 | BG14: =IFERROR(AK14/AL14,0) -> 0.11875 | BH14: =IFERROR(R14/Q14,0) -> 0.12727273 | BI14: =IFERROR(AQ14/AR14,0) -> 0.0088235294 | BJ14: =IFERROR(N14/L14,0) -> 0.036020583 | BK14: =IFERROR(P14/L14,0) -> 0.15437393 | BL14: =IFERROR((Q14*9)/H14,0) -> 0.061490683 | BM14: =IFERROR(AP14/H14,0) -> 0.37267081 | BN14: =IF(BA14>0.2,"Muy alta fuente de proteína",IF(BA14>0.15,"Alta fuente de proteína",IF(BA14>0.1,"Media fuente de proteína","Baja fuente de proteína"))) -> Baja fuente de proteína | BO14: =IF(BB14>0.03,"Alta",IF(BB14>0.015,"Media","Baja")) & " fuente de fibra" -> Media fuente de fibra | BP14: =IF(BC14>1.5,"Alta fuente de calcio",IF(BC14>0.8,"Media fuente de calcio","Baja fuente de calcio")) -> Baja fuente de calcio | BQ14: =IF(BD14>0.015,"Alta fuente de hierro",IF(BD14>0.008,"Media fuente de hierro","Baja fuente de hierro")) -> Media fuente de hierro | BR14: =IF(BE14>2,"Muy alto",IF(BE14>1,"Alto",IF(BE14>0.5,"Moderado","Bajo"))) & " en sodio" -> Bajo en sodio | BS14: =IF(BF14>2,"Altamente antiinflamatorio",IF(BF14>1,"Ligeramente antiinflamatorio",IF(BF14>0.5,"Neutro","Proinflamatorio"))) -> Altamente antiinflamatorio | BT14: =IF(BL14>0.4,"Muy alto en grasas",IF(BL14>0.3,"Alto en grasas",IF(BL14>0.2,"Moderado en grasas","Bajo en grasas"))) -> Bajo en grasas | BU14: =IF(BI14>1,"Alto riesgo de retención de líquidos",IF(BI14>0.5,"Riesgo moderado de retención","Equilibrio de líquidos ideal")) -> Equilibrio de líquidos ideal | BV14: =IF(BM14>0.5,"Alta",IF(BM14>0.2,"Media","Baja")) & " fuente de magnesio" -> Media fuente de magnesio | BW14: =IF(AV14>=0.5,"Alta fuente de Omega 3",IF(AV14>0.1,"Ligera fuente de Omega 3","Sin aporte de Omega 3")) -> Sin aporte de Omega 3 | BX14: =IF(AX14>0.5,"Alerta: Alto en grasas trans",IF(AX14>0,"Contiene grasas trans","Libre de grasas trans")) -> Libre de grasas trans | BY14: =IF(AY14>=50,"Alto",IF(AY14>=10,"Medio","Bajo")) & " poder antioxidante" -> Alto poder antioxidante | BZ14: =IF(AZ14>=1,"Probiótico activo","Sin probióticos") -> Sin probióticos | CA14: =IF(OR(AX14>0.5, O14>15, J14>0), "Altamente inflamatorio", IF(OR(AV14>=0.5, AY14>=50), "Antiinflamatorio", IF(OR(AX14>0, O14>5), "Moderadamente inflamatorio", "Poco inflamatorio"))) -> Antiinflamatorio | CB14: =IF(ISNUMBER(SEARCH("miel", D14)), "No irritante (Uso condicionado SII)", IF(OR(J14>0, ISNUMBER(SEARCH("cacao", D14)), ISNUMBER(SEARCH("chocolate puro", D14))), "Altamente irritante", IF(OR(AND(O14>15, BI14>1), ISNUMBER(SEARCH("chocolate", D14))), "Moderadamente irritante", "No irritante"))) -> No irritante | CC14: =IF(AV14=0,"Sin Omega 3 para evaluar",IFERROR(IF(((T14-AV14)/AV14)>4,"Exceso relativo de Omega 6","Balance de omegas favorable"),"Sin Omega 3 para evaluar")) -> Exceso relativo de Omega 6
A15: =1+A14 -> 14 | B15: CEREALES | C15: Granos y harinas | D15: Máchica | E15: Tostado; Gofio canario | F15: 0.8 | G15: 1 | H15: 356 | I15: 6.1 | J15: 0 | K15: 10.1 | L15: 64.8 | M15: 63.4 | N15: 1.4 | O15: 0 | P15: 16.2 | Q15: 2.7 | R15: 0.31 | S15: 0.36 | T15: 1.2 | U15: 0 | V15: 0 | W15: 0 | X15: 0 | Y15: 0 | Z15: 0.4 | AA15: 0 | AB15: 0.21 | AC15: 0.04 | AD15: 4.6 | AE15: 0.3 | AF15: 25 | AG15: 0 | AH15: 0 | AI15: 0 | AJ15: 0 | AK15: 16.8 | AL15: 314 | AM15: 6.8 | AN15: 0 | AO15: 0.7 | AP15: 103 | AQ15: 214 | AR15: 136 | AS15: 0 | AT15: 0 | AU15: 0 | AV15: =IFERROR(VLOOKUP(IFERROR(VLOOKUP(D15,Mapa_Similitud!$A$2:$B$2000,2,FALSE()),D15),Hoja1!$A$2:$K$1000,2,FALSE()),IFERROR(VLOOKUP(IFERROR(VLOOKUP(D15,Mapa_Similitud!$A$2:$B$2000,2,FALSE()),D15),Omega3_Referencia!$A$2:$E$100,3,FALSE()),0)) -> 0.05 | AW15: =IFERROR(VLOOKUP(IFERROR(VLOOKUP(D15,Mapa_Similitud!$A$2:$B$2000,2,FALSE()),D15),Hoja1!$A$2:$K$1000,3,FALSE()),IFERROR(VLOOKUP(IFERROR(VLOOKUP(D15,Mapa_Similitud!$A$2:$B$2000,2,FALSE()),D15),Omega3_Referencia!$A$2:$E$100,4,FALSE()),"N/A")) -> ALA | AX15: =IFERROR(VLOOKUP(IFERROR(VLOOKUP(D15,Mapa_Similitud!$A$2:$B$2000,2,FALSE()),D15),Hoja1!$A$2:$K$1000,5,FALSE()),0) -> 0 | AY15: =IFERROR(VLOOKUP(IFERROR(VLOOKUP(D15,Mapa_Similitud!$A$2:$B$2000,2,FALSE()),D15),Hoja1!$A$2:$K$1000,7,FALSE()),0) -> 50 | AZ15: =IFERROR(VLOOKUP(IFERROR(VLOOKUP(D15,Mapa_Similitud!$A$2:$B$2000,2,FALSE()),D15),Hoja1!$A$2:$K$1000,9,FALSE()),0) -> 0 | BA15: =IFERROR(K15/H15,0) -> 0.028370787 | BB15: =IFERROR(P15/H15,0) -> 0.045505618 | BC15: =IFERROR(AK15/H15,0) -> 0.047191011 | BD15: =IFERROR(AM15/H15,0) -> 0.019101124 | BE15: =IFERROR(AQ15/H15,0) -> 0.6011236 | BF15: =IFERROR(T15/R15,0) -> 3.8709677 | BG15: =IFERROR(AK15/AL15,0) -> 0.053503185 | BH15: =IFERROR(R15/Q15,0) -> 0.11481481 | BI15: =IFERROR(AQ15/AR15,0) -> 1.5735294 | BJ15: =IFERROR(N15/L15,0) -> 0.021604938 | BK15: =IFERROR(P15/L15,0) -> 0.25 | BL15: =IFERROR((Q15*9)/H15,0) -> 0.068258427 | BM15: =IFERROR(AP15/H15,0) -> 0.28932584 | BN15: =IF(BA15>0.2,"Muy alta fuente de proteína",IF(BA15>0.15,"Alta fuente de proteína",IF(BA15>0.1,"Media fuente de proteína","Baja fuente de proteína"))) -> Baja fuente de proteína | BO15: =IF(BB15>0.03,"Alta",IF(BB15>0.015,"Media","Baja")) & " fuente de fibra" -> Alta fuente de fibra | BP15: =IF(BC15>1.5,"Alta fuente de calcio",IF(BC15>0.8,"Media fuente de calcio","Baja fuente de calcio")) -> Baja fuente de calcio | BQ15: =IF(BD15>0.015,"Alta fuente de hierro",IF(BD15>0.008,"Media fuente de hierro","Baja fuente de hierro")) -> Alta fuente de hierro | BR15: =IF(BE15>2,"Muy alto",IF(BE15>1,"Alto",IF(BE15>0.5,"Moderado","Bajo"))) & " en sodio" -> Moderado en sodio | BS15: =IF(BF15>2,"Altamente antiinflamatorio",IF(BF15>1,"Ligeramente antiinflamatorio",IF(BF15>0.5,"Neutro","Proinflamatorio"))) -> Altamente antiinflamatorio | BT15: =IF(BL15>0.4,"Muy alto en grasas",IF(BL15>0.3,"Alto en grasas",IF(BL15>0.2,"Moderado en grasas","Bajo en grasas"))) -> Bajo en grasas | BU15: =IF(BI15>1,"Alto riesgo de retención de líquidos",IF(BI15>0.5,"Riesgo moderado de retención","Equilibrio de líquidos ideal")) -> Alto riesgo de retención de líquidos | BV15: =IF(BM15>0.5,"Alta",IF(BM15>0.2,"Media","Baja")) & " fuente de magnesio" -> Media fuente de magnesio | BW15: =IF(AV15>=0.5,"Alta fuente de Omega 3",IF(AV15>0.1,"Ligera fuente de Omega 3","Sin aporte de Omega 3")) -> Sin aporte de Omega 3 | BX15: =IF(AX15>0.5,"Alerta: Alto en grasas trans",IF(AX15>0,"Contiene grasas trans","Libre de grasas trans")) -> Libre de grasas trans | BY15: =IF(AY15>=50,"Alto",IF(AY15>=10,"Medio","Bajo")) & " poder antioxidante" -> Alto poder antioxidante | BZ15: =IF(AZ15>=1,"Probiótico activo","Sin probióticos") -> Sin probióticos | CA15: =IF(OR(AX15>0.5, O15>15, J15>0), "Altamente inflamatorio", IF(OR(AV15>=0.5, AY15>=50), "Antiinflamatorio", IF(OR(AX15>0, O15>5), "Moderadamente inflamatorio", "Poco inflamatorio"))) -> Antiinflamatorio | CB15: =IF(ISNUMBER(SEARCH("miel", D15)), "No irritante (Uso condicionado SII)", IF(OR(J15>0, ISNUMBER(SEARCH("cacao", D15)), ISNUMBER(SEARCH("chocolate puro", D15))), "Altamente irritante", IF(OR(AND(O15>15, BI15>1), ISNUMBER(SEARCH("chocolate", D15))), "Moderadamente irritante", "No irritante"))) -> No irritante | CC15: =IF(AV15=0,"Sin Omega 3 para evaluar",IFERROR(IF(((T15-AV15)/AV15)>4,"Exceso relativo de Omega 6","Balance de omegas favorable"),"Sin Omega 3 para evaluar")) -> Exceso relativo de Omega 6
A16: =1+A15 -> 15 | B16: CEREALES | C16: Granos y harinas | D16: Maíz en grano hervido en lata | F16: 1.8 | G16: 1 | H16: 102 | I16: 74.9 | J16: 0 | K16: 3.3 | L16: 18.2 | M16: 13.7 | N16: 4.5 | O16: 0 | P16: 2.3 | Q16: 1.3 | R16: 0.2 | S16: 0.37 | T16: 0.6 | U16: 0 | V16: 13 | W16: 0 | X16: 0 | Y16: 0 | Z16: 0.45 | AA16: 1 | AB16: 0.04 | AC16: 0.08 | AD16: 1.8 | AE16: 0.09 | AF16: 33 | AG16: 0 | AH16: 0.88 | AI16: 0 | AJ16: 1 | AK16: 3 | AL16: 69 | AM16: 0.6 | AN16: 1 | AO16: 0.3 | AP16: 22 | AQ16: 288 | AR16: 200 | AS16: 0.19 | AT16: 0.053 | AU16: 0.8 | AV16: =IFERROR(VLOOKUP(IFERROR(VLOOKUP(D16,Mapa_Similitud!$A$2:$B$2000,2,FALSE()),D16),Hoja1!$A$2:$K$1000,2,FALSE()),IFERROR(VLOOKUP(IFERROR(VLOOKUP(D16,Mapa_Similitud!$A$2:$B$2000,2,FALSE()),D16),Omega3_Referencia!$A$2:$E$100,3,FALSE()),0)) -> 0.02 | AW16: =IFERROR(VLOOKUP(IFERROR(VLOOKUP(D16,Mapa_Similitud!$A$2:$B$2000,2,FALSE()),D16),Hoja1!$A$2:$K$1000,3,FALSE()),IFERROR(VLOOKUP(IFERROR(VLOOKUP(D16,Mapa_Similitud!$A$2:$B$2000,2,FALSE()),D16),Omega3_Referencia!$A$2:$E$100,4,FALSE()),"N/A")) -> ALA | AX16: =IFERROR(VLOOKUP(IFERROR(VLOOKUP(D16,Mapa_Similitud!$A$2:$B$2000,2,FALSE()),D16),Hoja1!$A$2:$K$1000,5,FALSE()),0) -> 0 | AY16: =IFERROR(VLOOKUP(IFERROR(VLOOKUP(D16,Mapa_Similitud!$A$2:$B$2000,2,FALSE()),D16),Hoja1!$A$2:$K$1000,7,FALSE()),0) -> 15 | AZ16: =IFERROR(VLOOKUP(IFERROR(VLOOKUP(D16,Mapa_Similitud!$A$2:$B$2000,2,FALSE()),D16),Hoja1!$A$2:$K$1000,9,FALSE()),0) -> 0 | BA16: =IFERROR(K16/H16,0) -> 0.032352941 | BB16: =IFERROR(P16/H16,0) -> 0.02254902 | BC16: =IFERROR(AK16/H16,0) -> 0.029411765 | BD16: =IFERROR(AM16/H16,0) -> 0.0058823529 | BE16: =IFERROR(AQ16/H16,0) -> 2.8235294 | BF16: =IFERROR(T16/R16,0) -> 3 | BG16: =IFERROR(AK16/AL16,0) -> 0.043478261 | BH16: =IFERROR(R16/Q16,0) -> 0.15384615 | BI16: =IFERROR(AQ16/AR16,0) -> 1.44 | BJ16: =IFERROR(N16/L16,0) -> 0.24725275 | BK16: =IFERROR(P16/L16,0) -> 0.12637363 | BL16: =IFERROR((Q16*9)/H16,0) -> 0.11470588 | BM16: =IFERROR(AP16/H16,0) -> 0.21568627 | BN16: =IF(BA16>0.2,"Muy alta fuente de proteína",IF(BA16>0.15,"Alta fuente de proteína",IF(BA16>0.1,"Media fuente de proteína","Baja fuente de proteína"))) -> Baja fuente de proteína | BO16: =IF(BB16>0.03,"Alta",IF(BB16>0.015,"Media","Baja")) & " fuente de fibra" -> Media fuente de fibra | BP16: =IF(BC16>1.5,"Alta fuente de calcio",IF(BC16>0.8,"Media fuente de calcio","Baja fuente de calcio")) -> Baja fuente de calcio | BQ16: =IF(BD16>0.015,"Alta fuente de hierro",IF(BD16>0.008,"Media fuente de hierro","Baja fuente de hierro")) -> Baja fuente de hierro | BR16: =IF(BE16>2,"Muy alto",IF(BE16>1,"Alto",IF(BE16>0.5,"Moderado","Bajo"))) & " en sodio" -> Muy alto en sodio | BS16: =IF(BF16>2,"Altamente antiinflamatorio",IF(BF16>1,"Ligeramente antiinflamatorio",IF(BF16>0.5,"Neutro","Proinflamatorio"))) -> Altamente antiinflamatorio | BT16: =IF(BL16>0.4,"Muy alto en grasas",IF(BL16>0.3,"Alto en grasas",IF(BL16>0.2,"Moderado en grasas","Bajo en grasas"))) -> Bajo en grasas | BU16: =IF(BI16>1,"Alto riesgo de retención de líquidos",IF(BI16>0.5,"Riesgo moderado de retención","Equilibrio de líquidos ideal")) -> Alto riesgo de retención de líquidos | BV16: =IF(BM16>0.5,"Alta",IF(BM16>0.2,"Media","Baja")) & " fuente de magnesio" -> Media fuente de magnesio | BW16: =IF(AV16>=0.5,"Alta fuente de Omega 3",IF(AV16>0.1,"Ligera fuente de Omega 3","Sin aporte de Omega 3")) -> Sin aporte de Omega 3 | BX16: =IF(AX16>0.5,"Alerta: Alto en grasas trans",IF(AX16>0,"Contiene grasas trans","Libre de grasas trans")) -> Libre de grasas trans | BY16: =IF(AY16>=50,"Alto",IF(AY16>=10,"Medio","Bajo")) & " poder antioxidante" -> Medio poder antioxidante | BZ16: =IF(AZ16>=1,"Probiótico activo","Sin probióticos") -> Sin probióticos | CA16: =IF(OR(AX16>0.5, O16>15, J16>0), "Altamente inflamatorio", IF(OR(AV16>=0.5, AY16>=50), "Antiinflamatorio", IF(OR(AX16>0, O16>5), "Moderadamente inflamatorio", "Poco inflamatorio"))) -> Poco inflamatorio | CB16: =IF(ISNUMBER(SEARCH("miel", D16)), "No irritante (Uso condicionado SII)", IF(OR(J16>0, ISNUMBER(SEARCH("cacao", D16)), ISNUMBER(SEARCH("chocolate puro", D16))), "Altamente irritante", IF(OR(AND(O16>15, BI16>1), ISNUMBER(SEARCH("chocolate", D16))), "Moderadamente irritante", "No irritante"))) -> No irritante | CC16: =IF(AV16=0,"Sin Omega 3 para evaluar",IFERROR(IF(((T16-AV16)/AV16)>4,"Exceso relativo de Omega 6","Balance de omegas favorable"),"Sin Omega 3 para evaluar")) -> Exceso relativo de Omega 6
A17: =1+A16 -> 16 | B17: CEREALES | C17: Granos y harinas | D17: Maíz en mazorca crudo | F17: 0.5 | G17: 0.59 | H17: 346 | I17: 13.7 | J17: 0 | K17: 8.6 | L17: 64.7 | M17: 58.5 | N17: 6.2 | O17: 0 | P17: 9.2 | Q17: 3.8 | R17: 0.57 | S17: 1 | T17: 1.5 | U17: 0 | V17: 21.4 | W17: 0 | X17: 129 | Y17: 0 | Z17: 1.1 | AA17: 1 | AB17: 0.36 | AC17: 0.2 | AD17: 1.5 | AE17: 0.4 | AF17: 26 | AG17: 0 | AH17: 0.65 | AI17: 0 | AJ17: 0 | AK17: 7 | AL17: 256 | AM17: 2.4 | AN17: 2 | AO17: 1.7 | AP17: 93 | AQ17: 6 | AR17: 330 | AS17: 0.46 | AT17: 0.23 | AU17: 15.4 | AV17: =IFERROR(VLOOKUP(IFERROR(VLOOKUP(D17,Mapa_Similitud!$A$2:$B$2000,2,FALSE()),D17),Hoja1!$A$2:$K$1000,2,FALSE()),IFERROR(VLOOKUP(IFERROR(VLOOKUP(D17,Mapa_Similitud!$A$2:$B$2000,2,FALSE()),D17),Omega3_Referencia!$A$2:$E$100,3,FALSE()),0)) -> 0.02 | AW17: =IFERROR(VLOOKUP(IFERROR(VLOOKUP(D17,Mapa_Similitud!$A$2:$B$2000,2,FALSE()),D17),Hoja1!$A$2:$K$1000,3,FALSE()),IFERROR(VLOOKUP(IFERROR(VLOOKUP(D17,Mapa_Similitud!$A$2:$B$2000,2,FALSE()),D17),Omega3_Referencia!$A$2:$E$100,4,FALSE()),"N/A")) -> ALA | AX17: =IFERROR(VLOOKUP(IFERROR(VLOOKUP(D17,Mapa_Similitud!$A$2:$B$2000,2,FALSE()),D17),Hoja1!$A$2:$K$1000,5,FALSE()),0) -> 0 | AY17: =IFERROR(VLOOKUP(IFERROR(VLOOKUP(D17,Mapa_Similitud!$A$2:$B$2000,2,FALSE()),D17),Hoja1!$A$2:$K$1000,7,FALSE()),0) -> 20 | AZ17: =IFERROR(VLOOKUP(IFERROR(VLOOKUP(D17,Mapa_Similitud!$A$2:$B$2000,2,FALSE()),D17),Hoja1!$A$2:$K$1000,9,FALSE()),0) -> 0 | BA17: =IFERROR(K17/H17,0) -> 0.024855491 | BB17: =IFERROR(P17/H17,0) -> 0.026589595 | BC17: =IFERROR(AK17/H17,0) -> 0.020231214 | BD17: =IFERROR(AM17/H17,0) -> 0.0069364162 | BE17: =IFERROR(AQ17/H17,0) -> 0.01734104 | BF17: =IFERROR(T17/R17,0) -> 2.6315789 | BG17: =IFERROR(AK17/AL17,0) -> 0.02734375 | BH17: =IFERROR(R17/Q17,0) -> 0.15 | BI17: =IFERROR(AQ17/AR17,0) -> 0.018181818 | BJ17: =IFERROR(N17/L17,0) -> 0.095826893 | BK17: =IFERROR(P17/L17,0) -> 0.14219474 | BL17: =IFERROR((Q17*9)/H17,0) -> 0.098843931 | BM17: =IFERROR(AP17/H17,0) -> 0.26878613 | BN17: =IF(BA17>0.2,"Muy alta fuente de proteína",IF(BA17>0.15,"Alta fuente de proteína",IF(BA17>0.1,"Media fuente de proteína","Baja fuente de proteína"))) -> Baja fuente de proteína | BO17: =IF(BB17>0.03,"Alta",IF(BB17>0.015,"Media","Baja")) & " fuente de fibra" -> Media fuente de fibra | BP17: =IF(BC17>1.5,"Alta fuente de calcio",IF(BC17>0.8,"Media fuente de calcio","Baja fuente de calcio")) -> Baja fuente de calcio | BQ17: =IF(BD17>0.015,"Alta fuente de hierro",IF(BD17>0.008,"Media fuente de hierro","Baja fuente de hierro")) -> Baja fuente de hierro | BR17: =IF(BE17>2,"Muy alto",IF(BE17>1,"Alto",IF(BE17>0.5,"Moderado","Bajo"))) & " en sodio" -> Bajo en sodio | BS17: =IF(BF17>2,"Altamente antiinflamatorio",IF(BF17>1,"Ligeramente antiinflamatorio",IF(BF17>0.5,"Neutro","Proinflamatorio"))) -> Altamente antiinflamatorio | BT17: =IF(BL17>0.4,"Muy alto en grasas",IF(BL17>0.3,"Alto en grasas",IF(BL17>0.2,"Moderado en grasas","Bajo en grasas"))) -> Bajo en grasas | BU17: =IF(BI17>1,"Alto riesgo de retención de líquidos",IF(BI17>0.5,"Riesgo moderado de retención","Equilibrio de líquidos ideal")) -> Equilibrio de líquidos ideal | BV17: =IF(BM17>0.5,"Alta",IF(BM17>0.2,"Media","Baja")) & " fuente de magnesio" -> Media fuente de magnesio | BW17: =IF(AV17>=0.5,"Alta fuente de Omega 3",IF(AV17>0.1,"Ligera fuente de Omega 3","Sin aporte de Omega 3")) -> Sin aporte de Omega 3 | BX17: =IF(AX17>0.5,"Alerta: Alto en grasas trans",IF(AX17>0,"Contiene grasas trans","Libre de grasas trans")) -> Libre de grasas trans | BY17: =IF(AY17>=50,"Alto",IF(AY17>=10,"Medio","Bajo")) & " poder antioxidante" -> Medio poder antioxidante | BZ17: =IF(AZ17>=1,"Probiótico activo","Sin probióticos") -> Sin probióticos | CA17: =IF(OR(AX17>0.5, O17>15, J17>0), "Altamente inflamatorio", IF(OR(AV17>=0.5, AY17>=50), "Antiinflamatorio", IF(OR(AX17>0, O17>5), "Moderadamente inflamatorio", "Poco inflamatorio"))) -> Poco inflamatorio | CB17: =IF(ISNUMBER(SEARCH("miel", D17)), "No irritante (Uso condicionado SII)", IF(OR(J17>0, ISNUMBER(SEARCH("cacao", D17)), ISNUMBER(SEARCH("chocolate puro", D17))), "Altamente irritante", IF(OR(AND(O17>15, BI17>1), ISNUMBER(SEARCH("chocolate", D17))), "Moderadamente irritante", "No irritante"))) -> No irritante | CC17: =IF(AV17=0,"Sin Omega 3 para evaluar",IFERROR(IF(((T17-AV17)/AV17)>4,"Exceso relativo de Omega 6","Balance de omegas favorable"),"Sin Omega 3 para evaluar")) -> Exceso relativo de Omega 6
A18: =1+A17 -> 17 | B18: CEREALES | C18: Granos y harinas | D18: Maíz en mazorca hervido | F18: 0.8 | G18: 0.59 | H18: 110 | I18: 72.3 | J18: 0 | K18: 3.4 | L18: 18.6 | M18: 14 | N18: 4.5 | O18: 0 | P18: 4.2 | Q18: 1.5 | R18: 0.2 | S18: 0.4 | T18: 0.6 | U18: 0 | V18: 26.3 | W18: 0 | X18: 158 | Y18: 0 | Z18: 0.7 | AA18: 1 | AB18: 0.22 | AC18: 0.07 | AD18: 2 | AE18: 0.1 | AF18: 31 | AG18: 0 | AH18: 0.37 | AI18: 0 | AJ18: 7 | AK18: 3 | AL18: 103 | AM18: 0.6 | AN18: 1 | AO18: 0.3 | AP18: 33 | AQ18: 17 | AR18: 251 | AS18: 0.14 | AT18: 0.046 | AU18: 0.7 | AV18: =IFERROR(VLOOKUP(IFERROR(VLOOKUP(D18,Mapa_Similitud!$A$2:$B$2000,2,FALSE()),D18),Hoja1!$A$2:$K$1000,2,FALSE()),IFERROR(VLOOKUP(IFERROR(VLOOKUP(D18,Mapa_Similitud!$A$2:$B$2000,2,FALSE()),D18),Omega3_Referencia!$A$2:$E$100,3,FALSE()),0)) -> 0.02 | AW18: =IFERROR(VLOOKUP(IFERROR(VLOOKUP(D18,Mapa_Similitud!$A$2:$B$2000,2,FALSE()),D18),Hoja1!$A$2:$K$1000,3,FALSE()),IFERROR(VLOOKUP(IFERROR(VLOOKUP(D18,Mapa_Similitud!$A$2:$B$2000,2,FALSE()),D18),Omega3_Referencia!$A$2:$E$100,4,FALSE()),"N/A")) -> ALA | AX18: =IFERROR(VLOOKUP(IFERROR(VLOOKUP(D18,Mapa_Similitud!$A$2:$B$2000,2,FALSE()),D18),Hoja1!$A$2:$K$1000,5,FALSE()),0) -> 0 | AY18: =IFERROR(VLOOKUP(IFERROR(VLOOKUP(D18,Mapa_Similitud!$A$2:$B$2000,2,FALSE()),D18),Hoja1!$A$2:$K$1000,7,FALSE()),0) -> 18 | AZ18: =IFERROR(VLOOKUP(IFERROR(VLOOKUP(D18,Mapa_Similitud!$A$2:$B$2000,2,FALSE()),D18),Hoja1!$A$2:$K$1000,9,FALSE()),0) -> 0 | BA18: =IFERROR(K18/H18,0) -> 0.030909091 | BB18: =IFERROR(P18/H18,0) -> 0.038181818 | BC18: =IFERROR(AK18/H18,0) -> 0.027272727 | BD18: =IFERROR(AM18/H18,0) -> 0.0054545455 | BE18: =IFERROR(AQ18/H18,0) -> 0.15454545 | BF18: =IFERROR(T18/R18,0) -> 3 | BG18: =IFERROR(AK18/AL18,0) -> 0.029126214 | BH18: =IFERROR(R18/Q18,0) -> 0.13333333 | BI18: =IFERROR(AQ18/AR18,0) -> 0.067729084 | BJ18: =IFERROR(N18/L18,0) -> 0.24193548 | BK18: =IFERROR(P18/L18,0) -> 0.22580645 | BL18: =IFERROR((Q18*9)/H18,0) -> 0.12272727 | BM18: =IFERROR(AP18/H18,0) -> 0.3 | BN18: =IF(BA18>0.2,"Muy alta fuente de proteína",IF(BA18>0.15,"Alta fuente de proteína",IF(BA18>0.1,"Media fuente de proteína","Baja fuente de proteína"))) -> Baja fuente de proteína | BO18: =IF(BB18>0.03,"Alta",IF(BB18>0.015,"Media","Baja")) & " fuente de fibra" -> Alta fuente de fibra | BP18: =IF(BC18>1.5,"Alta fuente de calcio",IF(BC18>0.8,"Media fuente de calcio","Baja fuente de calcio")) -> Baja fuente de calcio | BQ18: =IF(BD18>0.015,"Alta fuente de hierro",IF(BD18>0.008,"Media fuente de hierro","Baja fuente de hierro")) -> Baja fuente de hierro | BR18: =IF(BE18>2,"Muy alto",IF(BE18>1,"Alto",IF(BE18>0.5,"Moderado","Bajo"))) & " en sodio" -> Bajo en sodio | BS18: =IF(BF18>2,"Altamente antiinflamatorio",IF(BF18>1,"Ligeramente antiinflamatorio",IF(BF18>0.5,"Neutro","Proinflamatorio"))) -> Altamente antiinflamatorio | BT18: =IF(BL18>0.4,"Muy alto en grasas",IF(BL18>0.3,"Alto en grasas",IF(BL18>0.2,"Moderado en grasas","Bajo en grasas"))) -> Bajo en grasas | BU18: =IF(BI18>1,"Alto riesgo de retención de líquidos",IF(BI18>0.5,"Riesgo moderado de retención","Equilibrio de líquidos ideal")) -> Equilibrio de líquidos ideal | BV18: =IF(BM18>0.5,"Alta",IF(BM18>0.2,"Media","Baja")) & " fuente de magnesio" -> Media fuente de magnesio | BW18: =IF(AV18>=0.5,"Alta fuente de Omega 3",IF(AV18>0.1,"Ligera fuente de Omega 3","Sin aporte de Omega 3")) -> Sin aporte de Omega 3 | BX18: =IF(AX18>0.5,"Alerta: Alto en grasas trans",IF(AX18>0,"Contiene grasas trans","Libre de grasas trans")) -> Libre de grasas trans | BY18: =IF(AY18>=50,"Alto",IF(AY18>=10,"Medio","Bajo")) & " poder antioxidante" -> Medio poder antioxidante | BZ18: =IF(AZ18>=1,"Probiótico activo","Sin probióticos") -> Sin probióticos | CA18: =IF(OR(AX18>0.5, O18>15, J18>0), "Altamente inflamatorio", IF(OR(AV18>=0.5, AY18>=50), "Antiinflamatorio", IF(OR(AX18>0, O18>5), "Moderadamente inflamatorio", "Poco inflamatorio"))) -> Poco inflamatorio | CB18: =IF(ISNUMBER(SEARCH("miel", D18)), "No irritante (Uso condicionado SII)", IF(OR(J18>0, ISNUMBER(SEARCH("cacao", D18)), ISNUMBER(SEARCH("chocolate puro", D18))), "Altamente irritante", IF(OR(AND(O18>15, BI18>1), ISNUMBER(SEARCH("chocolate", D18))), "Moderadamente irritante", "No irritante"))) -> No irritante | CC18: =IF(AV18=0,"Sin Omega 3 para evaluar",IFERROR(IF(((T18-AV18)/AV18)>4,"Exceso relativo de Omega 6","Balance de omegas favorable"),"Sin Omega 3 para evaluar")) -> Exceso relativo de Omega 6
A19: =1+A18 -> 18 | B19: CEREALES | C19: Granos y harinas | D19: Quinoa | F19: 1.5 | G19: 1 | H19: 354 | I19: 13.3 | J19: 0 | K19: 14.1 | L19: 57.2 | M19: 52.2 | N19: 5 | O19: 0 | P19: 7 | Q19: 6.1 | R19: 0.71 | S19: 1.6 | T19: 3.3 | U19: 0 | V19: 1.4 | W19: 0 | X19: 8.5 | Y19: 0 | Z19: 2.9 | AA19: 0 | AB19: 0.36 | AC19: 0.32 | AD19: 1.5 | AE19: 0.49 | AF19: 184 | AG19: 0 | AH19: 0 | AI19: 0 | AJ19: 0 | AK19: 0.33 | AL19: 457 | AM19: 4.6 | AN19: 0 | AO19: 3.1 | AP19: 197 | AQ19: 5 | AR19: 563 | AS19: 2 | AT19: 0.59 | AU19: 8.5 | AV19: =IFERROR(VLOOKUP(IFERROR(VLOOKUP(D19,Mapa_Similitud!$A$2:$B$2000,2,FALSE()),D19),Hoja1!$A$2:$K$1000,2,FALSE()),IFERROR(VLOOKUP(IFERROR(VLOOKUP(D19,Mapa_Similitud!$A$2:$B$2000,2,FALSE()),D19),Omega3_Referencia!$A$2:$E$100,3,FALSE()),0)) -> 0.26 | AW19: =IFERROR(VLOOKUP(IFERROR(VLOOKUP(D19,Mapa_Similitud!$A$2:$B$2000,2,FALSE()),D19),Hoja1!$A$2:$K$1000,3,FALSE()),IFERROR(VLOOKUP(IFERROR(VLOOKUP(D19,Mapa_Similitud!$A$2:$B$2000,2,FALSE()),D19),Omega3_Referencia!$A$2:$E$100,4,FALSE()),"N/A")) -> ALA | AX19: =IFERROR(VLOOKUP(IFERROR(VLOOKUP(D19,Mapa_Similitud!$A$2:$B$2000,2,FALSE()),D19),Hoja1!$A$2:$K$1000,5,FALSE()),0) -> 0 | AY19: =IFERROR(VLOOKUP(IFERROR(VLOOKUP(D19,Mapa_Similitud!$A$2:$B$2000,2,FALSE()),D19),Hoja1!$A$2:$K$1000,7,FALSE()),0) -> 45 | AZ19: =IFERROR(VLOOKUP(IFERROR(VLOOKUP(D19,Mapa_Similitud!$A$2:$B$2000,2,FALSE()),D19),Hoja1!$A$2:$K$1000,9,FALSE()),0) -> 0 | BA19: =IFERROR(K19/H19,0) -> 0.039830508 | BB19: =IFERROR(P19/H19,0) -> 0.019774011 | BC19: =IFERROR(AK19/H19,0) -> 0.00093220339 | BD19: =IFERROR(AM19/H19,0) -> 0.01299435 | BE19: =IFERROR(AQ19/H19,0) -> 0.014124294 | BF19: =IFERROR(T19/R19,0) -> 4.6478873 | BG19: =IFERROR(AK19/AL19,0) -> 0.00072210066 | BH19: =IFERROR(R19/Q19,0) -> 0.11639344 | BI19: =IFERROR(AQ19/AR19,0) -> 0.0088809947 | BJ19: =IFERROR(N19/L19,0) -> 0.087412587 | BK19: =IFERROR(P19/L19,0) -> 0.12237762 | BL19: =IFERROR((Q19*9)/H19,0) -> 0.15508475 | BM19: =IFERROR(AP19/H19,0) -> 0.55649718 | BN19: =IF(BA19>0.2,"Muy alta fuente de proteína",IF(BA19>0.15,"Alta fuente de proteína",IF(BA19>0.1,"Media fuente de proteína","Baja fuente de proteína"))) -> Baja fuente de proteína | BO19: =IF(BB19>0.03,"Alta",IF(BB19>0.015,"Media","Baja")) & " fuente de fibra" -> Media fuente de fibra | BP19: =IF(BC19>1.5,"Alta fuente de calcio",IF(BC19>0.8,"Media fuente de calcio","Baja fuente de calcio")) -> Baja fuente de calcio | BQ19: =IF(BD19>0.015,"Alta fuente de hierro",IF(BD19>0.008,"Media fuente de hierro","Baja fuente de hierro")) -> Media fuente de hierro | BR19: =IF(BE19>2,"Muy alto",IF(BE19>1,"Alto",IF(BE19>0.5,"Moderado","Bajo"))) & " en sodio" -> Bajo en sodio | BS19: =IF(BF19>2,"Altamente antiinflamatorio",IF(BF19>1,"Ligeramente antiinflamatorio",IF(BF19>0.5,"Neutro","Proinflamatorio"))) -> Altamente antiinflamatorio | BT19: =IF(BL19>0.4,"Muy alto en grasas",IF(BL19>0.3,"Alto en grasas",IF(BL19>0.2,"Moderado en grasas","Bajo en grasas"))) -> Bajo en grasas | BU19: =IF(BI19>1,"Alto riesgo de retención de líquidos",IF(BI19>0.5,"Riesgo moderado de retención","Equilibrio de líquidos ideal")) -> Equilibrio de líquidos ideal | BV19: =IF(BM19>0.5,"Alta",IF(BM19>0.2,"Media","Baja")) & " fuente de magnesio" -> Alta fuente de magnesio | BW19: =IF(AV19>=0.5,"Alta fuente de Omega 3",IF(AV19>0.1,"Ligera fuente de Omega 3","Sin aporte de Omega 3")) -> Ligera fuente de Omega 3 | BX19: =IF(AX19>0.5,"Alerta: Alto en grasas trans",IF(AX19>0,"Contiene grasas trans","Libre de grasas trans")) -> Libre de grasas trans | BY19: =IF(AY19>=50,"Alto",IF(AY19>=10,"Medio","Bajo")) & " poder antioxidante" -> Medio poder antioxidante | BZ19: =IF(AZ19>=1,"Probiótico activo","Sin probióticos") -> Sin probióticos | CA19: =IF(OR(AX19>0.5, O19>15, J19>0), "Altamente inflamatorio", IF(OR(AV19>=0.5, AY19>=50), "Antiinflamatorio", IF(OR(AX19>0, O19>5), "Moderadamente inflamatorio", "Poco inflamatorio"))) -> Poco inflamatorio | CB19: =IF(ISNUMBER(SEARCH("miel", D19)), "No irritante (Uso condicionado SII)", IF(OR(J19>0, ISNUMBER(SEARCH("cacao", D19)), ISNUMBER(SEARCH("chocolate puro", D19))), "Altamente irritante", IF(OR(AND(O19>15, BI19>1), ISNUMBER(SEARCH("chocolate", D19))), "Moderadamente irritante", "No irritante"))) -> No irritante | CC19: =IF(AV19=0,"Sin Omega 3 para evaluar",IFERROR(IF(((T19-AV19)/AV19)>4,"Exceso relativo de Omega 6","Balance de omegas favorable"),"Sin Omega 3 para evaluar")) -> Exceso relativo de Omega 6
A20: =1+A19 -> 19 | B20: CEREALES | C20: Granos y harinas | D20: Sémola de trigo | F20: 1.1 | G20: 1 | H20: 351 | I20: 10.1 | J20: 0 | K20: 12.7 | L20: 69 | M20: 68.7 | N20: 0.32 | O20: 0 | P20: 7.2 | Q20: 1.1 | R20: 0.15 | S20: 0.12 | T20: 0.43 | U20: 0 | V20: 0 | W20: 0 | X20: 0 | Y20: 0 | Z20: 0.26 | AA20: 98.2 | AB20: 0.28 | AC20: 0.08 | AD20: 6 | AE20: 0.1 | AF20: 72 | AG20: 0 | AH20: 0.58 | AI20: 0 | AJ20: 0 | AK20: 17 | AL20: 136 | AM20: 1.2 | AN20: 5.1 | AO20: 1.1 | AP20: 47 | AQ20: 1 | AR20: 186 | AS20: 0.62 | AT20: 0.19 | AU20: 2.5 | AV20: =IFERROR(VLOOKUP(IFERROR(VLOOKUP(D20,Mapa_Similitud!$A$2:$B$2000,2,FALSE()),D20),Hoja1!$A$2:$K$1000,2,FALSE()),IFERROR(VLOOKUP(IFERROR(VLOOKUP(D20,Mapa_Similitud!$A$2:$B$2000,2,FALSE()),D20),Omega3_Referencia!$A$2:$E$100,3,FALSE()),0)) -> 0.02 | AW20: =IFERROR(VLOOKUP(IFERROR(VLOOKUP(D20,Mapa_Similitud!$A$2:$B$2000,2,FALSE()),D20),Hoja1!$A$2:$K$1000,3,FALSE()),IFERROR(VLOOKUP(IFERROR(VLOOKUP(D20,Mapa_Similitud!$A$2:$B$2000,2,FALSE()),D20),Omega3_Referencia!$A$2:$E$100,4,FALSE()),"N/A")) -> ALA | AX20: =IFERROR(VLOOKUP(IFERROR(VLOOKUP(D20,Mapa_Similitud!$A$2:$B$2000,2,FALSE()),D20),Hoja1!$A$2:$K$1000,5,FALSE()),0) -> 0 | AY20: =IFERROR(VLOOKUP(IFERROR(VLOOKUP(D20,Mapa_Similitud!$A$2:$B$2000,2,FALSE()),D20),Hoja1!$A$2:$K$1000,7,FALSE()),0) -> 12 | AZ20: =IFERROR(VLOOKUP(IFERROR(VLOOKUP(D20,Mapa_Similitud!$A$2:$B$2000,2,FALSE()),D20),Hoja1!$A$2:$K$1000,9,FALSE()),0) -> 0 | BA20: =IFERROR(K20/H20,0) -> 0.036182336 | BB20: =IFERROR(P20/H20,0) -> 0.020512821 | BC20: =IFERROR(AK20/H20,0) -> 0.048433048 | BD20: =IFERROR(AM20/H20,0) -> 0.0034188034 | BE20: =IFERROR(AQ20/H20,0) -> 0.0028490028 | BF20: =IFERROR(T20/R20,0) -> 2.8666667 | BG20: =IFERROR(AK20/AL20,0) -> 0.125 | BH20: =IFERROR(R20/Q20,0) -> 0.13636364 | BI20: =IFERROR(AQ20/AR20,0) -> 0.0053763441 | BJ20: =IFERROR(N20/L20,0) -> 0.0046376812 | BK20: =IFERROR(P20/L20,0) -> 0.10434783 | BL20: =IFERROR((Q20*9)/H20,0) -> 0.028205128 | BM20: =IFERROR(AP20/H20,0) -> 0.13390313 | BN20: =IF(BA20>0.2,"Muy alta fuente de proteína",IF(BA20>0.15,"Alta fuente de proteína",IF(BA20>0.1,"Media fuente de proteína","Baja fuente de proteína"))) -> Baja fuente de proteína | BO20: =IF(BB20>0.03,"Alta",IF(BB20>0.015,"Media","Baja")) & " fuente de fibra" -> Media fuente de fibra | BP20: =IF(BC20>1.5,"Alta fuente de calcio",IF(BC20>0.8,"Media fuente de calcio","Baja fuente de calcio")) -> Baja fuente de calcio | BQ20: =IF(BD20>0.015,"Alta fuente de hierro",IF(BD20>0.008,"Media fuente de hierro","Baja fuente de hierro")) -> Baja fuente de hierro | BR20: =IF(BE20>2,"Muy alto",IF(BE20>1,"Alto",IF(BE20>0.5,"Moderado","Bajo"))) & " en sodio" -> Bajo en sodio | BS20: =IF(BF20>2,"Altamente antiinflamatorio",IF(BF20>1,"Ligeramente antiinflamatorio",IF(BF20>0.5,"Neutro","Proinflamatorio"))) -> Altamente antiinflamatorio | BT20: =IF(BL20>0.4,"Muy alto en grasas",IF(BL20>0.3,"Alto en grasas",IF(BL20>0.2,"Moderado en grasas","Bajo en grasas"))) -> Bajo en grasas | BU20: =IF(BI20>1,"Alto riesgo de retención de líquidos",IF(BI20>0.5,"Riesgo moderado de retención","Equilibrio de líquidos ideal")) -> Equilibrio de líquidos ideal | BV20: =IF(BM20>0.5,"Alta",IF(BM20>0.2,"Media","Baja")) & " fuente de magnesio" -> Baja fuente de magnesio | BW20: =IF(AV20>=0.5,"Alta fuente de Omega 3",IF(AV20>0.1,"Ligera fuente de Omega 3","Sin aporte de Omega 3")) -> Sin aporte de Omega 3 | BX20: =IF(AX20>0.5,"Alerta: Alto en grasas trans",IF(AX20>0,"Contiene grasas trans","Libre de grasas trans")) -> Libre de grasas trans | BY20: =IF(AY20>=50,"Alto",IF(AY20>=10,"Medio","Bajo")) & " poder antioxidante" -> Medio poder antioxidante | BZ20: =IF(AZ20>=1,"Probiótico activo","Sin probióticos") -> Sin probióticos | CA20: =IF(OR(AX20>0.5, O20>15, J20>0), "Altamente inflamatorio", IF(OR(AV20>=0.5, AY20>=50), "Antiinflamatorio", IF(OR(AX20>0, O20>5), "Moderadamente inflamatorio", "Poco inflamatorio"))) -> Poco inflamatorio | CB20: =IF(ISNUMBER(SEARCH("miel", D20)), "No irritante (Uso condicionado SII)", IF(OR(J20>0, ISNUMBER(SEARCH("cacao", D20)), ISNUMBER(SEARCH("chocolate puro", D20))), "Altamente irritante", IF(OR(AND(O20>15, BI20>1), ISNUMBER(SEARCH("chocolate", D20))), "Moderadamente irritante", "No irritante"))) -> No irritante | CC20: =IF(AV20=0,"Sin Omega 3 para evaluar",IFERROR(IF(((T20-AV20)/AV20)>4,"Exceso relativo de Omega 6","Balance de omegas favorable"),"Sin Omega 3 para evaluar")) -> Exceso relativo de Omega 6
A21: =1+A20 -> 20 | B21: CEREALES | C21: Panes | D21: Masa de hojaldre congelada | F21: 2.5 | G21: 1 | H21: 544 | I21: 8.4 | J21: 0 | K21: 7.4 | L21: 41.3 | M21: 39.4 | N21: 1.9 | O21: 0 | P21: 1.5 | Q21: 38.5 | R21: 5.5 | S21: 8.3 | T21: 22.2 | U21: 1 | V21: 0 | W21: 0 | X21: 0 | Y21: 1 | Z21: 2.4 | AA21: 14.4 | AB21: 0.32 | AC21: 0.25 | AD21: 5.2 | AE21: 0.019 | AF21: 47 | AG21: 0 | AH21: 0 | AI21: 0 | AJ21: 0 | AK21: 10 | AL21: 60 | AM21: 2.6 | AN21: 17.2 | AO21: 0.54 | AP21: 16 | AQ21: 253 | AR21: 62 | AS21: 0.49 | AT21: 0.11 | AU21: 24.5 | AV21: =IFERROR(VLOOKUP(IFERROR(VLOOKUP(D21,Mapa_Similitud!$A$2:$B$2000,2,FALSE()),D21),Hoja1!$A$2:$K$1000,2,FALSE()),IFERROR(VLOOKUP(IFERROR(VLOOKUP(D21,Mapa_Similitud!$A$2:$B$2000,2,FALSE()),D21),Omega3_Referencia!$A$2:$E$100,3,FALSE()),0)) -> 0.05 | AW21: =IFERROR(VLOOKUP(IFERROR(VLOOKUP(D21,Mapa_Similitud!$A$2:$B$2000,2,FALSE()),D21),Hoja1!$A$2:$K$1000,3,FALSE()),IFERROR(VLOOKUP(IFERROR(VLOOKUP(D21,Mapa_Similitud!$A$2:$B$2000,2,FALSE()),D21),Omega3_Referencia!$A$2:$E$100,4,FALSE()),"N/A")) -> ALA | AX21: =IFERROR(VLOOKUP(IFERROR(VLOOKUP(D21,Mapa_Similitud!$A$2:$B$2000,2,FALSE()),D21),Hoja1!$A$2:$K$1000,5,FALSE()),0) -> 2.8 | AY21: =IFERROR(VLOOKUP(IFERROR(VLOOKUP(D21,Mapa_Similitud!$A$2:$B$2000,2,FALSE()),D21),Hoja1!$A$2:$K$1000,7,FALSE()),0) -> 5 | AZ21: =IFERROR(VLOOKUP(IFERROR(VLOOKUP(D21,Mapa_Similitud!$A$2:$B$2000,2,FALSE()),D21),Hoja1!$A$2:$K$1000,9,FALSE()),0) -> 0 | BA21: =IFERROR(K21/H21,0) -> 0.013602941 | BB21: =IFERROR(P21/H21,0) -> 0.0027573529 | BC21: =IFERROR(AK21/H21,0) -> 0.018382353 | BD21: =IFERROR(AM21/H21,0) -> 0.0047794118 | BE21: =IFERROR(AQ21/H21,0) -> 0.46507353 | BF21: =IFERROR(T21/R21,0) -> 4.0363636 | BG21: =IFERROR(AK21/AL21,0) -> 0.16666667 | BH21: =IFERROR(R21/Q21,0) -> 0.14285714 | BI21: =IFERROR(AQ21/AR21,0) -> 4.0806452 | BJ21: =IFERROR(N21/L21,0) -> 0.046004843 | BK21: =IFERROR(P21/L21,0) -> 0.036319613 | BL21: =IFERROR((Q21*9)/H21,0) -> 0.63694853 | BM21: =IFERROR(AP21/H21,0) -> 0.029411765 | BN21: =IF(BA21>0.2,"Muy alta fuente de proteína",IF(BA21>0.15,"Alta fuente de proteína",IF(BA21>0.1,"Media fuente de proteína","Baja fuente de proteína"))) -> Baja fuente de proteína | BO21: =IF(BB21>0.03,"Alta",IF(BB21>0.015,"Media","Baja")) & " fuente de fibra" -> Baja fuente de fibra | BP21: =IF(BC21>1.5,"Alta fuente de calcio",IF(BC21>0.8,"Media fuente de calcio","Baja fuente de calcio")) -> Baja fuente de calcio | BQ21: =IF(BD21>0.015,"Alta fuente de hierro",IF(BD21>0.008,"Media fuente de hierro","Baja fuente de hierro")) -> Baja fuente de hierro | BR21: =IF(BE21>2,"Muy alto",IF(BE21>1,"Alto",IF(BE21>0.5,"Moderado","Bajo"))) & " en sodio" -> Bajo en sodio | BS21: =IF(BF21>2,"Altamente antiinflamatorio",IF(BF21>1,"Ligeramente antiinflamatorio",IF(BF21>0.5,"Neutro","Proinflamatorio"))) -> Altamente antiinflamatorio | BT21: =IF(BL21>0.4,"Muy alto en grasas",IF(BL21>0.3,"Alto en grasas",IF(BL21>0.2,"Moderado en grasas","Bajo en grasas"))) -> Muy alto en grasas | BU21: =IF(BI21>1,"Alto riesgo de retención de líquidos",IF(BI21>0.5,"Riesgo moderado de retención","Equilibrio de líquidos ideal")) -> Alto riesgo de retención de líquidos | BV21: =IF(BM21>0.5,"Alta",IF(BM21>0.2,"Media","Baja")) & " fuente de magnesio" -> Baja fuente de magnesio | BW21: =IF(AV21>=0.5,"Alta fuente de Omega 3",IF(AV21>0.1,"Ligera fuente de Omega 3","Sin aporte de Omega 3")) -> Sin aporte de Omega 3 | BX21: =IF(AX21>0.5,"Alerta: Alto en grasas trans",IF(AX21>0,"Contiene grasas trans","Libre de grasas trans")) -> Alerta: Alto en grasas trans | BY21: =IF(AY21>=50,"Alto",IF(AY21>=10,"Medio","Bajo")) & " poder antioxidante" -> Bajo poder antioxidante | BZ21: =IF(AZ21>=1,"Probiótico activo","Sin probióticos") -> Sin probióticos | CA21: =IF(OR(AX21>0.5, O21>15, J21>0), "Altamente inflamatorio", IF(OR(AV21>=0.5, AY21>=50), "Antiinflamatorio", IF(OR(AX21>0, O21>5), "Moderadamente inflamatorio", "Poco inflamatorio"))) -> Altamente inflamatorio | CB21: =IF(ISNUMBER(SEARCH("miel", D21)), "No irritante (Uso condicionado SII)", IF(OR(J21>0, ISNUMBER(SEARCH("cacao", D21)), ISNUMBER(SEARCH("chocolate puro", D21))), "Altamente irritante", IF(OR(AND(O21>15, BI21>1), ISNUMBER(SEARCH("chocolate", D21))), "Moderadamente irritante", "No irritante"))) -> No irritante | CC21: =IF(AV21=0,"Sin Omega 3 para evaluar",IFERROR(IF(((T21-AV21)/AV21)>4,"Exceso relativo de Omega 6","Balance de omegas favorable"),"Sin Omega 3 para evaluar")) -> Exceso relativo de Omega 6
A22: =1+A21 -> 21 | B22: CEREALES | C22: Panes | D22: Masa quebrada | F22: 2.5 | G22: 1 | H22: 372 | I22: 32.8 | J22: 0 | K22: 6.1 | L22: 39.3 | M22: 37.8 | N22: 1.5 | O22: 1.5 | P22: 0.9 | Q22: 20.9 | R22: 8.8 | S22: 0 | T22: 0 | U22: 114 | V22: 35.8 | W22: 35.5 | X22: 1.6 | Y22: 0.52 | Z22: 1 | AA22: 17.9 | AB22: 0.07 | AC22: 0.079 | AD22: 1.6 | AE22: 0.064 | AF22: 16.1 | AG22: 0.36 | AH22: 0.49 | AI22: 4.5 | AJ22: 0 | AK22: 22.4 | AL22: 89 | AM22: 0.85 | AN22: 7.2 | AO22: 0.7 | AP22: 14.6 | AQ22: 460 | AR22: 95.7 | AS22: 0.33 | AT22: 0.088 | AU22: 3.9 | AV22: =IFERROR(VLOOKUP(IFERROR(VLOOKUP(D22,Mapa_Similitud!$A$2:$B$2000,2,FALSE()),D22),Hoja1!$A$2:$K$1000,2,FALSE()),IFERROR(VLOOKUP(IFERROR(VLOOKUP(D22,Mapa_Similitud!$A$2:$B$2000,2,FALSE()),D22),Omega3_Referencia!$A$2:$E$100,3,FALSE()),0)) -> 0.05 | AW22: =IFERROR(VLOOKUP(IFERROR(VLOOKUP(D22,Mapa_Similitud!$A$2:$B$2000,2,FALSE()),D22),Hoja1!$A$2:$K$1000,3,FALSE()),IFERROR(VLOOKUP(IFERROR(VLOOKUP(D22,Mapa_Similitud!$A$2:$B$2000,2,FALSE()),D22),Omega3_Referencia!$A$2:$E$100,4,FALSE()),"N/A")) -> ALA | AX22: =IFERROR(VLOOKUP(IFERROR(VLOOKUP(D22,Mapa_Similitud!$A$2:$B$2000,2,FALSE()),D22),Hoja1!$A$2:$K$1000,5,FALSE()),0) -> 1.9 | AY22: =IFERROR(VLOOKUP(IFERROR(VLOOKUP(D22,Mapa_Similitud!$A$2:$B$2000,2,FALSE()),D22),Hoja1!$A$2:$K$1000,7,FALSE()),0) -> 4 | AZ22: =IFERROR(VLOOKUP(IFERROR(VLOOKUP(D22,Mapa_Similitud!$A$2:$B$2000,2,FALSE()),D22),Hoja1!$A$2:$K$1000,9,FALSE()),0) -> 0 | BA22: =IFERROR(K22/H22,0) -> 0.016397849 | BB22: =IFERROR(P22/H22,0) -> 0.0024193548 | BC22: =IFERROR(AK22/H22,0) -> 0.060215054 | BD22: =IFERROR(AM22/H22,0) -> 0.0022849462 | BE22: =IFERROR(AQ22/H22,0) -> 1.2365591 | BF22: =IFERROR(T22/R22,0) -> 0 | BG22: =IFERROR(AK22/AL22,0) -> 0.25168539 | BH22: =IFERROR(R22/Q22,0) -> 0.42105263 | BI22: =IFERROR(AQ22/AR22,0) -> 4.8066876 | BJ22: =IFERROR(N22/L22,0) -> 0.038167939 | BK22: =IFERROR(P22/L22,0) -> 0.022900763 | BL22: =IFERROR((Q22*9)/H22,0) -> 0.50564516 | BM22: =IFERROR(AP22/H22,0) -> 0.039247312 | BN22: =IF(BA22>0.2,"Muy alta fuente de proteína",IF(BA22>0.15,"Alta fuente de proteína",IF(BA22>0.1,"Media fuente de proteína","Baja fuente de proteína"))) -> Baja fuente de proteína | BO22: =IF(BB22>0.03,"Alta",IF(BB22>0.015,"Media","Baja")) & " fuente de fibra" -> Baja fuente de fibra | BP22: =IF(BC22>1.5,"Alta fuente de calcio",IF(BC22>0.8,"Media fuente de calcio","Baja fuente de calcio")) -> Baja fuente de calcio | BQ22: =IF(BD22>0.015,"Alta fuente de hierro",IF(BD22>0.008,"Media fuente de hierro","Baja fuente de hierro")) -> Baja fuente de hierro | BR22: =IF(BE22>2,"Muy alto",IF(BE22>1,"Alto",IF(BE22>0.5,"Moderado","Bajo"))) & " en sodio" -> Alto en sodio | BS22: =IF(BF22>2,"Altamente antiinflamatorio",IF(BF22>1,"Ligeramente antiinflamatorio",IF(BF22>0.5,"Neutro","Proinflamatorio"))) -> Proinflamatorio | BT22: =IF(BL22>0.4,"Muy alto en grasas",IF(BL22>0.3,"Alto en grasas",IF(BL22>0.2,"Moderado en grasas","Bajo en grasas"))) -> Muy alto en grasas | BU22: =IF(BI22>1,"Alto riesgo de retención de líquidos",IF(BI22>0.5,"Riesgo moderado de retención","Equilibrio de líquidos ideal")) -> Alto riesgo de retención de líquidos | BV22: =IF(BM22>0.5,"Alta",IF(BM22>0.2,"Media","Baja")) & " fuente de magnesio" -> Baja fuente de magnesio | BW22: =IF(AV22>=0.5,"Alta fuente de Omega 3",IF(AV22>0.1,"Ligera fuente de Omega 3","Sin aporte de Omega 3")) -> Sin aporte de Omega 3 | BX22: =IF(AX22>0.5,"Alerta: Alto en grasas trans",IF(AX22>0,"Contiene grasas trans","Libre de grasas trans")) -> Alerta: Alto en grasas trans | BY22: =IF(AY22>=50,"Alto",IF(AY22>=10,"Medio","Bajo")) & " poder antioxidante" -> Bajo poder antioxidante | BZ22: =IF(AZ22>=1,"Probiótico activo","Sin probióticos") -> Sin probióticos | CA22: =IF(OR(AX22>0.5, O22>15, J22>0), "Altamente inflamatorio", IF(OR(AV22>=0.5, AY22>=50), "Antiinflamatorio", IF(OR(AX22>0, O22>5), "Moderadamente inflamatorio", "Poco inflamatorio"))) -> Altamente inflamatorio | CB22: =IF(ISNUMBER(SEARCH("miel", D22)), "No irritante (Uso condicionado SII)", IF(OR(J22>0, ISNUMBER(SEARCH("cacao", D22)), ISNUMBER(SEARCH("chocolate puro", D22))), "Altamente irritante", IF(OR(AND(O22>15, BI22>1), ISNUMBER(SEARCH("chocolate", D22))), "Moderadamente irritante", "No irritante"))) -> No irritante | CC22: =IF(AV22=0,"Sin Omega 3 para evaluar",IFERROR(IF(((T22-AV22)/AV22)>4,"Exceso relativo de Omega 6","Balance de omegas favorable"),"Sin Omega 3 para evaluar")) -> Balance de omegas favorable
A23: =1+A22 -> 22 | B23: CEREALES | C23: Panes | D23: Pan blanco | F23: 0.8 | G23: 1 | H23: 243 | I23: 39.6 | J23: 0 | K23: 8.3 | L23: 47 | M23: 42.2 | N23: 4.8 | O23: 0 | P23: 3.5 | Q23: 1.6 | R23: 0.39 | S23: 0.28 | T23: 0.34 | U23: 0 | V23: 0.33 | W23: 0 | X23: 2 | Y23: 0 | Z23: 0 | AA23: 1.9 | AB23: 0.086 | AC23: 0.06 | AD23: 3 | AE23: 0.06 | AF23: 23 | AG23: 0 | AH23: 0.3 | AI23: 1 | AJ23: 0 | AK23: 56 | AL23: 91 | AM23: 1.6 | AN23: 4.7 | AO23: 0.61 | AP23: 25.1 | AQ23: 424 | AR23: 110 | AS23: 0.5 | AT23: 0.19 | AU23: 28 | AV23: =IFERROR(VLOOKUP(IFERROR(VLOOKUP(D23,Mapa_Similitud!$A$2:$B$2000,2,FALSE()),D23),Hoja1!$A$2:$K$1000,2,FALSE()),IFERROR(VLOOKUP(IFERROR(VLOOKUP(D23,Mapa_Similitud!$A$2:$B$2000,2,FALSE()),D23),Omega3_Referencia!$A$2:$E$100,3,FALSE()),0)) -> 0.04 | AW23: =IFERROR(VLOOKUP(IFERROR(VLOOKUP(D23,Mapa_Similitud!$A$2:$B$2000,2,FALSE()),D23),Hoja1!$A$2:$K$1000,3,FALSE()),IFERROR(VLOOKUP(IFERROR(VLOOKUP(D23,Mapa_Similitud!$A$2:$B$2000,2,FALSE()),D23),Omega3_Referencia!$A$2:$E$100,4,FALSE()),"N/A")) -> ALA | AX23: =IFERROR(VLOOKUP(IFERROR(VLOOKUP(D23,Mapa_Similitud!$A$2:$B$2000,2,FALSE()),D23),Hoja1!$A$2:$K$1000,5,FALSE()),0) -> 0.1 | AY23: =IFERROR(VLOOKUP(IFERROR(VLOOKUP(D23,Mapa_Similitud!$A$2:$B$2000,2,FALSE()),D23),Hoja1!$A$2:$K$1000,7,FALSE()),0) -> 20 | AZ23: =IFERROR(VLOOKUP(IFERROR(VLOOKUP(D23,Mapa_Similitud!$A$2:$B$2000,2,FALSE()),D23),Hoja1!$A$2:$K$1000,9,FALSE()),0) -> 0 | BA23: =IFERROR(K23/H23,0) -> 0.034156379 | BB23: =IFERROR(P23/H23,0) -> 0.014403292 | BC23: =IFERROR(AK23/H23,0) -> 0.23045267 | BD23: =IFERROR(AM23/H23,0) -> 0.0065843621 | BE23: =IFERROR(AQ23/H23,0) -> 1.744856 | BF23: =IFERROR(T23/R23,0) -> 0.87179487 | BG23: =IFERROR(AK23/AL23,0) -> 0.61538462 | BH23: =IFERROR(R23/Q23,0) -> 0.24375 | BI23: =IFERROR(AQ23/AR23,0) -> 3.8545455 | BJ23: =IFERROR(N23/L23,0) -> 0.10212766 | BK23: =IFERROR(P23/L23,0) -> 0.074468085 | BL23: =IFERROR((Q23*9)/H23,0) -> 0.059259259 | BM23: =IFERROR(AP23/H23,0) -> 0.10329218 | BN23: =IF(BA23>0.2,"Muy alta fuente de proteína",IF(BA23>0.15,"Alta fuente de proteína",IF(BA23>0.1,"Media fuente de proteína","Baja fuente de proteína"))) -> Baja fuente de proteína | BO23: =IF(BB23>0.03,"Alta",IF(BB23>0.015,"Media","Baja")) & " fuente de fibra" -> Baja fuente de fibra | BP23: =IF(BC23>1.5,"Alta fuente de calcio",IF(BC23>0.8,"Media fuente de calcio","Baja fuente de calcio")) -> Baja fuente de calcio | BQ23: =IF(BD23>0.015,"Alta fuente de hierro",IF(BD23>0.008,"Media fuente de hierro","Baja fuente de hierro")) -> Baja fuente de hierro | BR23: =IF(BE23>2,"Muy alto",IF(BE23>1,"Alto",IF(BE23>0.5,"Moderado","Bajo"))) & " en sodio" -> Alto en sodio | BS23: =IF(BF23>2,"Altamente antiinflamatorio",IF(BF23>1,"Ligeramente antiinflamatorio",IF(BF23>0.5,"Neutro","Proinflamatorio"))) -> Neutro | BT23: =IF(BL23>0.4,"Muy alto en grasas",IF(BL23>0.3,"Alto en grasas",IF(BL23>0.2,"Moderado en grasas","Bajo en grasas"))) -> Bajo en grasas | BU23: =IF(BI23>1,"Alto riesgo de retención de líquidos",IF(BI23>0.5,"Riesgo moderado de retención","Equilibrio de líquidos ideal")) -> Alto riesgo de retención de líquidos | BV23: =IF(BM23>0.5,"Alta",IF(BM23>0.2,"Media","Baja")) & " fuente de magnesio" -> Baja fuente de magnesio | BW23: =IF(AV23>=0.5,"Alta fuente de Omega 3",IF(AV23>0.1,"Ligera fuente de Omega 3","Sin aporte de Omega 3")) -> Sin aporte de Omega 3 | BX23: =IF(AX23>0.5,"Alerta: Alto en grasas trans",IF(AX23>0,"Contiene grasas trans","Libre de grasas trans")) -> Contiene grasas trans | BY23: =IF(AY23>=50,"Alto",IF(AY23>=10,"Medio","Bajo")) & " poder antioxidante" -> Medio poder antioxidante | BZ23: =IF(AZ23>=1,"Probiótico activo","Sin probióticos") -> Sin probióticos | CA23: =IF(OR(AX23>0.5, O23>15, J23>0), "Altamente inflamatorio", IF(OR(AV23>=0.5, AY23>=50), "Antiinflamatorio", IF(OR(AX23>0, O23>5), "Moderadamente inflamatorio", "Poco inflamatorio"))) -> Moderadamente inflamatorio | CB23: =IF(ISNUMBER(SEARCH("miel", D23)), "No irritante (Uso condicionado SII)", IF(OR(J23>0, ISNUMBER(SEARCH("cacao", D23)), ISNUMBER(SEARCH("chocolate puro", D23))), "Altamente irritante", IF(OR(AND(O23>15, BI23>1), ISNUMBER(SEARCH("chocolate", D23))), "Moderadamente irritante", "No irritante"))) -> No irritante | CC23: =IF(AV23=0,"Sin Omega 3 para evaluar",IFERROR(IF(((T23-AV23)/AV23)>4,"Exceso relativo de Omega 6","Balance de omegas favorable"),"Sin Omega 3 para evaluar")) -> Exceso relativo de Omega 6
A24: =1+A23 -> 23 | B24: CEREALES | C24: Panes | D24: Pan blanco sin sal | F24: 1 | G24: 1 | H24: 265 | I24: 33.5 | J24: 0 | K24: 8 | L24: 53.9 | M24: 52 | N24: 1.9 | O24: 0 | P24: 3.5 | Q24: 1.1 | R24: 0.2 | S24: 0.1 | T24: 0.4 | U24: 0 | V24: 0 | W24: 0 | X24: 0 | Y24: 0 | Z24: 0.18 | AA24: 1.9 | AB24: 0.09 | AC24: 0.05 | AD24: 2.6 | AE24: 0.12 | AF24: 23 | AG24: 0 | AH24: 0.3 | AI24: 0 | AJ24: 0 | AK24: 20 | AL24: 90 | AM24: 1.7 | AN24: 5 | AO24: 0.6 | AP24: 26 | AQ24: 2 | AR24: 100 | AS24: 0.38 | AT24: 0.13 | AU24: 22.6 | AV24: =IFERROR(VLOOKUP(IFERROR(VLOOKUP(D24,Mapa_Similitud!$A$2:$B$2000,2,FALSE()),D24),Hoja1!$A$2:$K$1000,2,FALSE()),IFERROR(VLOOKUP(IFERROR(VLOOKUP(D24,Mapa_Similitud!$A$2:$B$2000,2,FALSE()),D24),Omega3_Referencia!$A$2:$E$100,3,FALSE()),0)) -> 0.04 | AW24: =IFERROR(VLOOKUP(IFERROR(VLOOKUP(D24,Mapa_Similitud!$A$2:$B$2000,2,FALSE()),D24),Hoja1!$A$2:$K$1000,3,FALSE()),IFERROR(VLOOKUP(IFERROR(VLOOKUP(D24,Mapa_Similitud!$A$2:$B$2000,2,FALSE()),D24),Omega3_Referencia!$A$2:$E$100,4,FALSE()),"N/A")) -> ALA | AX24: =IFERROR(VLOOKUP(IFERROR(VLOOKUP(D24,Mapa_Similitud!$A$2:$B$2000,2,FALSE()),D24),Hoja1!$A$2:$K$1000,5,FALSE()),0) -> 0.1 | AY24: =IFERROR(VLOOKUP(IFERROR(VLOOKUP(D24,Mapa_Similitud!$A$2:$B$2000,2,FALSE()),D24),Hoja1!$A$2:$K$1000,7,FALSE()),0) -> 20 | AZ24: =IFERROR(VLOOKUP(IFERROR(VLOOKUP(D24,Mapa_Similitud!$A$2:$B$2000,2,FALSE()),D24),Hoja1!$A$2:$K$1000,9,FALSE()),0) -> 0 | BA24: =IFERROR(K24/H24,0) -> 0.030188679 | BB24: =IFERROR(P24/H24,0) -> 0.013207547 | BC24: =IFERROR(AK24/H24,0) -> 0.075471698 | BD24: =IFERROR(AM24/H24,0) -> 0.0064150943 | BE24: =IFERROR(AQ24/H24,0) -> 0.0075471698 | BF24: =IFERROR(T24/R24,0) -> 2 | BG24: =IFERROR(AK24/AL24,0) -> 0.22222222 | BH24: =IFERROR(R24/Q24,0) -> 0.18181818 | BI24: =IFERROR(AQ24/AR24,0) -> 0.02 | BJ24: =IFERROR(N24/L24,0) -> 0.035250464 | BK24: =IFERROR(P24/L24,0) -> 0.064935065 | BL24: =IFERROR((Q24*9)/H24,0) -> 0.037358491 | BM24: =IFERROR(AP24/H24,0) -> 0.098113208 | BN24: =IF(BA24>0.2,"Muy alta fuente de proteína",IF(BA24>0.15,"Alta fuente de proteína",IF(BA24>0.1,"Media fuente de proteína","Baja fuente de proteína"))) -> Baja fuente de proteína | BO24: =IF(BB24>0.03,"Alta",IF(BB24>0.015,"Media","Baja")) & " fuente de fibra" -> Baja fuente de fibra | BP24: =IF(BC24>1.5,"Alta fuente de calcio",IF(BC24>0.8,"Media fuente de calcio","Baja fuente de calcio")) -> Baja fuente de calcio | BQ24: =IF(BD24>0.015,"Alta fuente de hierro",IF(BD24>0.008,"Media fuente de hierro","Baja fuente de hierro")) -> Baja fuente de hierro | BR24: =IF(BE24>2,"Muy alto",IF(BE24>1,"Alto",IF(BE24>0.5,"Moderado","Bajo"))) & " en sodio" -> Bajo en sodio | BS24: =IF(BF24>2,"Altamente antiinflamatorio",IF(BF24>1,"Ligeramente antiinflamatorio",IF(BF24>0.5,"Neutro","Proinflamatorio"))) -> Ligeramente antiinflamatorio | BT24: =IF(BL24>0.4,"Muy alto en grasas",IF(BL24>0.3,"Alto en grasas",IF(BL24>0.2,"Moderado en grasas","Bajo en grasas"))) -> Bajo en grasas | BU24: =IF(BI24>1,"Alto riesgo de retención de líquidos",IF(BI24>0.5,"Riesgo moderado de retención","Equilibrio de líquidos ideal")) -> Equilibrio de líquidos ideal | BV24: =IF(BM24>0.5,"Alta",IF(BM24>0.2,"Media","Baja")) & " fuente de magnesio" -> Baja fuente de magnesio | BW24: =IF(AV24>=0.5,"Alta fuente de Omega 3",IF(AV24>0.1,"Ligera fuente de Omega 3","Sin aporte de Omega 3")) -> Sin aporte de Omega 3 | BX24: =IF(AX24>0.5,"Alerta: Alto en grasas trans",IF(AX24>0,"Contiene grasas trans","Libre de grasas trans")) -> Contiene grasas trans | BY24: =IF(AY24>=50,"Alto",IF(AY24>=10,"Medio","Bajo")) & " poder antioxidante" -> Medio poder antioxidante | BZ24: =IF(AZ24>=1,"Probiótico activo","Sin probióticos") -> Sin probióticos | CA24: =IF(OR(AX24>0.5, O24>15, J24>0), "Altamente inflamatorio", IF(OR(AV24>=0.5, AY24>=50), "Antiinflamatorio", IF(OR(AX24>0, O24>5), "Moderadamente inflamatorio", "Poco inflamatorio"))) -> Moderadamente inflamatorio | CB24: =IF(ISNUMBER(SEARCH("miel", D24)), "No irritante (Uso condicionado SII)", IF(OR(J24>0, ISNUMBER(SEARCH("cacao", D24)), ISNUMBER(SEARCH("chocolate puro", D24))), "Altamente irritante", IF(OR(AND(O24>15, BI24>1), ISNUMBER(SEARCH("chocolate", D24))), "Moderadamente irritante", "No irritante"))) -> No irritante | CC24: =IF(AV24=0,"Sin Omega 3 para evaluar",IFERROR(IF(((T24-AV24)/AV24)>4,"Exceso relativo de Omega 6","Balance de omegas favorable"),"Sin Omega 3 para evaluar")) -> Exceso relativo de Omega 6
A25: =1+A24 -> 24 | B25: CEREALES | C25: Panes | D25: Pan blanco tipo baguette | F25: 1.2 | G25: 1 | H25: 273 | I25: 31.5 | J25: 0 | K25: 8 | L25: 55.9 | M25: 53.6 | N25: 2.3 | O25: 0 | P25: 3.5 | Q25: 1.2 | R25: 0.2 | S25: 0.1 | T25: 0.4 | U25: 0 | V25: 0 | W25: 0 | X25: 0 | Y25: 0 | Z25: 0.18 | AA25: 1.9 | AB25: 0.09 | AC25: 0.05 | AD25: 3.3 | AE25: 0.08 | AF25: 24 | AG25: 0 | AH25: 0.39 | AI25: 1 | AJ25: 0 | AK25: 23 | AL25: 110 | AM25: 1.5 | AN25: 6 | AO25: 0.7 | AP25: 28 | AQ25: 424 | AR25: 130 | AS25: 0.5 | AT25: 0.16 | AU25: 28 | AV25: =IFERROR(VLOOKUP(IFERROR(VLOOKUP(D25,Mapa_Similitud!$A$2:$B$2000,2,FALSE()),D25),Hoja1!$A$2:$K$1000,2,FALSE()),IFERROR(VLOOKUP(IFERROR(VLOOKUP(D25,Mapa_Similitud!$A$2:$B$2000,2,FALSE()),D25),Omega3_Referencia!$A$2:$E$100,3,FALSE()),0)) -> 0.04 | AW25: =IFERROR(VLOOKUP(IFERROR(VLOOKUP(D25,Mapa_Similitud!$A$2:$B$2000,2,FALSE()),D25),Hoja1!$A$2:$K$1000,3,FALSE()),IFERROR(VLOOKUP(IFERROR(VLOOKUP(D25,Mapa_Similitud!$A$2:$B$2000,2,FALSE()),D25),Omega3_Referencia!$A$2:$E$100,4,FALSE()),"N/A")) -> ALA | AX25: =IFERROR(VLOOKUP(IFERROR(VLOOKUP(D25,Mapa_Similitud!$A$2:$B$2000,2,FALSE()),D25),Hoja1!$A$2:$K$1000,5,FALSE()),0) -> 0.1 | AY25: =IFERROR(VLOOKUP(IFERROR(VLOOKUP(D25,Mapa_Similitud!$A$2:$B$2000,2,FALSE()),D25),Hoja1!$A$2:$K$1000,7,FALSE()),0) -> 20 | AZ25: =IFERROR(VLOOKUP(IFERROR(VLOOKUP(D25,Mapa_Similitud!$A$2:$B$2000,2,FALSE()),D25),Hoja1!$A$2:$K$1000,9,FALSE()),0) -> 0 | BA25: =IFERROR(K25/H25,0) -> 0.029304029 | BB25: =IFERROR(P25/H25,0) -> 0.012820513 | BC25: =IFERROR(AK25/H25,0) -> 0.084249084 | BD25: =IFERROR(AM25/H25,0) -> 0.0054945055 | BE25: =IFERROR(AQ25/H25,0) -> 1.5531136 | BF25: =IFERROR(T25/R25,0) -> 2 | BG25: =IFERROR(AK25/AL25,0) -> 0.20909091 | BH25: =IFERROR(R25/Q25,0) -> 0.16666667 | BI25: =IFERROR(AQ25/AR25,0) -> 3.2615385 | BJ25: =IFERROR(N25/L25,0) -> 0.041144902 | BK25: =IFERROR(P25/L25,0) -> 0.062611807 | BL25: =IFERROR((Q25*9)/H25,0) -> 0.03956044 | BM25: =IFERROR(AP25/H25,0) -> 0.1025641 | BN25: =IF(BA25>0.2,"Muy alta fuente de proteína",IF(BA25>0.15,"Alta fuente de proteína",IF(BA25>0.1,"Media fuente de proteína","Baja fuente de proteína"))) -> Baja fuente de proteína | BO25: =IF(BB25>0.03,"Alta",IF(BB25>0.015,"Media","Baja")) & " fuente de fibra" -> Baja fuente de fibra | BP25: =IF(BC25>1.5,"Alta fuente de calcio",IF(BC25>0.8,"Media fuente de calcio","Baja fuente de calcio")) -> Baja fuente de calcio | BQ25: =IF(BD25>0.015,"Alta fuente de hierro",IF(BD25>0.008,"Media fuente de hierro","Baja fuente de hierro")) -> Baja fuente de hierro | BR25: =IF(BE25>2,"Muy alto",IF(BE25>1,"Alto",IF(BE25>0.5,"Moderado","Bajo"))) & " en sodio" -> Alto en sodio | BS25: =IF(BF25>2,"Altamente antiinflamatorio",IF(BF25>1,"Ligeramente antiinflamatorio",IF(BF25>0.5,"Neutro","Proinflamatorio"))) -> Ligeramente antiinflamatorio | BT25: =IF(BL25>0.4,"Muy alto en grasas",IF(BL25>0.3,"Alto en grasas",IF(BL25>0.2,"Moderado en grasas","Bajo en grasas"))) -> Bajo en grasas | BU25: =IF(BI25>1,"Alto riesgo de retención de líquidos",IF(BI25>0.5,"Riesgo moderado de retención","Equilibrio de líquidos ideal")) -> Alto riesgo de retención de líquidos | BV25: =IF(BM25>0.5,"Alta",IF(BM25>0.2,"Media","Baja")) & " fuente de magnesio" -> Baja fuente de magnesio | BW25: =IF(AV25>=0.5,"Alta fuente de Omega 3",IF(AV25>0.1,"Ligera fuente de Omega 3","Sin aporte de Omega 3")) -> Sin aporte de Omega 3 | BX25: =IF(AX25>0.5,"Alerta: Alto en grasas trans",IF(AX25>0,"Contiene grasas trans","Libre de grasas trans")) -> Contiene grasas trans | BY25: =IF(AY25>=50,"Alto",IF(AY25>=10,"Medio","Bajo")) & " poder antioxidante" -> Medio poder antioxidante | BZ25: =IF(AZ25>=1,"Probiótico activo","Sin probióticos") -> Sin probióticos | CA25: =IF(OR(AX25>0.5, O25>15, J25>0), "Altamente inflamatorio", IF(OR(AV25>=0.5, AY25>=50), "Antiinflamatorio", IF(OR(AX25>0, O25>5), "Moderadamente inflamatorio", "Poco inflamatorio"))) -> Moderadamente inflamatorio | CB25: =IF(ISNUMBER(SEARCH("miel", D25)), "No irritante (Uso condicionado SII)", IF(OR(J25>0, ISNUMBER(SEARCH("cacao", D25)), ISNUMBER(SEARCH("chocolate puro", D25))), "Altamente irritante", IF(OR(AND(O25>15, BI25>1), ISNUMBER(SEARCH("chocolate", D25))), "Moderadamente irritante", "No irritante"))) -> No irritante | CC25: =IF(AV25=0,"Sin Omega 3 para evaluar",IFERROR(IF(((T25-AV25)/AV25)>4,"Exceso relativo de Omega 6","Balance de omegas favorable"),"Sin Omega 3 para evaluar")) -> Exceso relativo de Omega 6
A26: =1+A25 -> 25 | B26: CEREALES | C26: Panes | D26: Pan blanco tostado | F26: 1.8 | G26: 1 | H26: 389 | I26: 6.6 | J26: 0 | K26: 11.5 | L26: 73.4 | M26: 68.2 | N26: 5.2 | O26: 0 | P26: 3.9 | Q26: 4.6 | R26: 0.5 | S26: 1.9 | T26: 0.98 | U26: 0 | V26: 0 | W26: 0 | X26: 0 | Y26: 0 | Z26: 0.01 | AA26: 3 | AB26: 0.36 | AC26: 0.27 | AD26: 6.2 | AE26: 0.09 | AF26: 21 | AG26: 0 | AH26: 0.3 | AI26: 1 | AJ26: 0 | AK26: 114 | AL26: 92 | AM26: 1 | AN26: 7 | AO26: 0.78 | AP26: 25 | AQ26: 702 | AR26: 160 | AS26: 0.55 | AT26: 0.17 | AU26: 33.6 | AV26: =IFERROR(VLOOKUP(IFERROR(VLOOKUP(D26,Mapa_Similitud!$A$2:$B$2000,2,FALSE()),D26),Hoja1!$A$2:$K$1000,2,FALSE()),IFERROR(VLOOKUP(IFERROR(VLOOKUP(D26,Mapa_Similitud!$A$2:$B$2000,2,FALSE()),D26),Omega3_Referencia!$A$2:$E$100,3,FALSE()),0)) -> 0.04 | AW26: =IFERROR(VLOOKUP(IFERROR(VLOOKUP(D26,Mapa_Similitud!$A$2:$B$2000,2,FALSE()),D26),Hoja1!$A$2:$K$1000,3,FALSE()),IFERROR(VLOOKUP(IFERROR(VLOOKUP(D26,Mapa_Similitud!$A$2:$B$2000,2,FALSE()),D26),Omega3_Referencia!$A$2:$E$100,4,FALSE()),"N/A")) -> ALA | AX26: =IFERROR(VLOOKUP(IFERROR(VLOOKUP(D26,Mapa_Similitud!$A$2:$B$2000,2,FALSE()),D26),Hoja1!$A$2:$K$1000,5,FALSE()),0) -> 0.1 | AY26: =IFERROR(VLOOKUP(IFERROR(VLOOKUP(D26,Mapa_Similitud!$A$2:$B$2000,2,FALSE()),D26),Hoja1!$A$2:$K$1000,7,FALSE()),0) -> 18 | AZ26: =IFERROR(VLOOKUP(IFERROR(VLOOKUP(D26,Mapa_Similitud!$A$2:$B$2000,2,FALSE()),D26),Hoja1!$A$2:$K$1000,9,FALSE()),0) -> 0 | BA26: =IFERROR(K26/H26,0) -> 0.029562982 | BB26: =IFERROR(P26/H26,0) -> 0.010025707 | BC26: =IFERROR(AK26/H26,0) -> 0.29305913 | BD26: =IFERROR(AM26/H26,0) -> 0.0025706941 | BE26: =IFERROR(AQ26/H26,0) -> 1.8046272 | BF26: =IFERROR(T26/R26,0) -> 1.96 | BG26: =IFERROR(AK26/AL26,0) -> 1.2391304 | BH26: =IFERROR(R26/Q26,0) -> 0.10869565 | BI26: =IFERROR(AQ26/AR26,0) -> 4.3875 | BJ26: =IFERROR(N26/L26,0) -> 0.070844687 | BK26: =IFERROR(P26/L26,0) -> 0.053133515 | BL26: =IFERROR((Q26*9)/H26,0) -> 0.10642674 | BM26: =IFERROR(AP26/H26,0) -> 0.064267352 | BN26: =IF(BA26>0.2,"Muy alta fuente de proteína",IF(BA26>0.15,"Alta fuente de proteína",IF(BA26>0.1,"Media fuente de proteína","Baja fuente de proteína"))) -> Baja fuente de proteína | BO26: =IF(BB26>0.03,"Alta",IF(BB26>0.015,"Media","Baja")) & " fuente de fibra" -> Baja fuente de fibra | BP26: =IF(BC26>1.5,"Alta fuente de calcio",IF(BC26>0.8,"Media fuente de calcio","Baja fuente de calcio")) -> Baja fuente de calcio | BQ26: =IF(BD26>0.015,"Alta fuente de hierro",IF(BD26>0.008,"Media fuente de hierro","Baja fuente de hierro")) -> Baja fuente de hierro | BR26: =IF(BE26>2,"Muy alto",IF(BE26>1,"Alto",IF(BE26>0.5,"Moderado","Bajo"))) & " en sodio" -> Alto en sodio | BS26: =IF(BF26>2,"Altamente antiinflamatorio",IF(BF26>1,"Ligeramente antiinflamatorio",IF(BF26>0.5,"Neutro","Proinflamatorio"))) -> Ligeramente antiinflamatorio | BT26: =IF(BL26>0.4,"Muy alto en grasas",IF(BL26>0.3,"Alto en grasas",IF(BL26>0.2,"Moderado en grasas","Bajo en grasas"))) -> Bajo en grasas | BU26: =IF(BI26>1,"Alto riesgo de retención de líquidos",IF(BI26>0.5,"Riesgo moderado de retención","Equilibrio de líquidos ideal")) -> Alto riesgo de retención de líquidos | BV26: =IF(BM26>0.5,"Alta",IF(BM26>0.2,"Media","Baja")) & " fuente de magnesio" -> Baja fuente de magnesio | BW26: =IF(AV26>=0.5,"Alta fuente de Omega 3",IF(AV26>0.1,"Ligera fuente de Omega 3","Sin aporte de Omega 3")) -> Sin aporte de Omega 3 | BX26: =IF(AX26>0.5,"Alerta: Alto en grasas trans",IF(AX26>0,"Contiene grasas trans","Libre de grasas trans")) -> Contiene grasas trans | BY26: =IF(AY26>=50,"Alto",IF(AY26>=10,"Medio","Bajo")) & " poder antioxidante" -> Medio poder antioxidante | BZ26: =IF(AZ26>=1,"Probiótico activo","Sin probióticos") -> Sin probióticos | CA26: =IF(OR(AX26>0.5, O26>15, J26>0), "Altamente inflamatorio", IF(OR(AV26>=0.5, AY26>=50), "Antiinflamatorio", IF(OR(AX26>0, O26>5), "Moderadamente inflamatorio", "Poco inflamatorio"))) -> Moderadamente inflamatorio | CB26: =IF(ISNUMBER(SEARCH("miel", D26)), "No irritante (Uso condicionado SII)", IF(OR(J26>0, ISNUMBER(SEARCH("cacao", D26)), ISNUMBER(SEARCH("chocolate puro", D26))), "Altamente irritante", IF(OR(AND(O26>15, BI26>1), ISNUMBER(SEARCH("chocolate", D26))), "Moderadamente irritante", "No irritante"))) -> No irritante | CC26: =IF(AV26=0,"Sin Omega 3 para evaluar",IFERROR(IF(((T26-AV26)/AV26)>4,"Exceso relativo de Omega 6","Balance de omegas favorable"),"Sin Omega 3 para evaluar")) -> Exceso relativo de Omega 6
A27: =1+A26 -> 26 | B27: CEREALES | C27: Panes | D27: Pan blanco tostado sin sal | F27: 2 | G27: 1 | H27: 389 | I27: 6.6 | J27: 0 | K27: 11.5 | L27: 73.4 | M27: 68.2 | N27: 5.2 | O27: 0 | P27: 5.2 | Q27: 3.9 | R27: 0.5 | S27: 1.8 | T27: 0.82 | U27: 1 | V27: 0 | W27: 0 | X27: 0 | Y27: 0 | Z27: 0.01 | AA27: 3 | AB27: 0.42 | AC27: 0.34 | AD27: 5.7 | AE27: 0.063 | AF27: 26 | AG27: 0.02 | AH27: 0.28 | AI27: 0 | AJ27: 0 | AK27: 119 | AL27: 103 | AM27: 3.3 | AN27: 7 | AO27: 0.68 | AP27: 26 | AQ27: 192 | AR27: 131 | AS27: 0.42 | AT27: 0.14 | AU27: 33.6 | AV27: =IFERROR(VLOOKUP(IFERROR(VLOOKUP(D27,Mapa_Similitud!$A$2:$B$2000,2,FALSE()),D27),Hoja1!$A$2:$K$1000,2,FALSE()),IFERROR(VLOOKUP(IFERROR(VLOOKUP(D27,Mapa_Similitud!$A$2:$B$2000,2,FALSE()),D27),Omega3_Referencia!$A$2:$E$100,3,FALSE()),0)) -> 0.04 | AW27: =IFERROR(VLOOKUP(IFERROR(VLOOKUP(D27,Mapa_Similitud!$A$2:$B$2000,2,FALSE()),D27),Hoja1!$A$2:$K$1000,3,FALSE()),IFERROR(VLOOKUP(IFERROR(VLOOKUP(D27,Mapa_Similitud!$A$2:$B$2000,2,FALSE()),D27),Omega3_Referencia!$A$2:$E$100,4,FALSE()),"N/A")) -> ALA | AX27: =IFERROR(VLOOKUP(IFERROR(VLOOKUP(D27,Mapa_Similitud!$A$2:$B$2000,2,FALSE()),D27),Hoja1!$A$2:$K$1000,5,FALSE()),0) -> 0.1 | AY27: =IFERROR(VLOOKUP(IFERROR(VLOOKUP(D27,Mapa_Similitud!$A$2:$B$2000,2,FALSE()),D27),Hoja1!$A$2:$K$1000,7,FALSE()),0) -> 18 | AZ27: =IFERROR(VLOOKUP(IFERROR(VLOOKUP(D27,Mapa_Similitud!$A$2:$B$2000,2,FALSE()),D27),Hoja1!$A$2:$K$1000,9,FALSE()),0) -> 0 | BA27: =IFERROR(K27/H27,0) -> 0.029562982 | BB27: =IFERROR(P27/H27,0) -> 0.013367609 | BC27: =IFERROR(AK27/H27,0) -> 0.3059126 | BD27: =IFERROR(AM27/H27,0) -> 0.0084832905 | BE27: =IFERROR(AQ27/H27,0) -> 0.49357326 | BF27: =IFERROR(T27/R27,0) -> 1.64 | BG27: =IFERROR(AK27/AL27,0) -> 1.1553398 | BH27: =IFERROR(R27/Q27,0) -> 0.12820513 | BI27: =IFERROR(AQ27/AR27,0) -> 1.4656489 | BJ27: =IFERROR(N27/L27,0) -> 0.070844687 | BK27: =IFERROR(P27/L27,0) -> 0.070844687 | BL27: =IFERROR((Q27*9)/H27,0) -> 0.090231362 | BM27: =IFERROR(AP27/H27,0) -> 0.066838046 | BN27: =IF(BA27>0.2,"Muy alta fuente de proteína",IF(BA27>0.15,"Alta fuente de proteína",IF(BA27>0.1,"Media fuente de proteína","Baja fuente de proteína"))) -> Baja fuente de proteína | BO27: =IF(BB27>0.03,"Alta",IF(BB27>0.015,"Media","Baja")) & " fuente de fibra" -> Baja fuente de fibra | BP27: =IF(BC27>1.5,"Alta fuente de calcio",IF(BC27>0.8,"Media fuente de calcio","Baja fuente de calcio")) -> Baja fuente de calcio | BQ27: =IF(BD27>0.015,"Alta fuente de hierro",IF(BD27>0.008,"Media fuente de hierro","Baja fuente de hierro")) -> Media fuente de hierro | BR27: =IF(BE27>2,"Muy alto",IF(BE27>1,"Alto",IF(BE27>0.5,"Moderado","Bajo"))) & " en sodio" -> Bajo en sodio | BS27: =IF(BF27>2,"Altamente antiinflamatorio",IF(BF27>1,"Ligeramente antiinflamatorio",IF(BF27>0.5,"Neutro","Proinflamatorio"))) -> Ligeramente antiinflamatorio | BT27: =IF(BL27>0.4,"Muy alto en grasas",IF(BL27>0.3,"Alto en grasas",IF(BL27>0.2,"Moderado en grasas","Bajo en grasas"))) -> Bajo en grasas | BU27: =IF(BI27>1,"Alto riesgo de retención de líquidos",IF(BI27>0.5,"Riesgo moderado de retención","Equilibrio de líquidos ideal")) -> Alto riesgo de retención de líquidos | BV27: =IF(BM27>0.5,"Alta",IF(BM27>0.2,"Media","Baja")) & " fuente de magnesio" -> Baja fuente de magnesio | BW27: =IF(AV27>=0.5,"Alta fuente de Omega 3",IF(AV27>0.1,"Ligera fuente de Omega 3","Sin aporte de Omega 3")) -> Sin aporte de Omega 3 | BX27: =IF(AX27>0.5,"Alerta: Alto en grasas trans",IF(AX27>0,"Contiene grasas trans","Libre de grasas trans")) -> Contiene grasas trans | BY27: =IF(AY27>=50,"Alto",IF(AY27>=10,"Medio","Bajo")) & " poder antioxidante" -> Medio poder antioxidante | BZ27: =IF(AZ27>=1,"Probiótico activo","Sin probióticos") -> Sin probióticos | CA27: =IF(OR(AX27>0.5, O27>15, J27>0), "Altamente inflamatorio", IF(OR(AV27>=0.5, AY27>=50), "Antiinflamatorio", IF(OR(AX27>0, O27>5), "Moderadamente inflamatorio", "Poco inflamatorio"))) -> Moderadamente inflamatorio | CB27: =IF(ISNUMBER(SEARCH("miel", D27)), "No irritante (Uso condicionado SII)", IF(OR(J27>0, ISNUMBER(SEARCH("cacao", D27)), ISNUMBER(SEARCH("chocolate puro", D27))), "Altamente irritante", IF(OR(AND(O27>15, BI27>1), ISNUMBER(SEARCH("chocolate", D27))), "Moderadamente irritante", "No irritante"))) -> No irritante | CC27: =IF(AV27=0,"Sin Omega 3 para evaluar",IFERROR(IF(((T27-AV27)/AV27)>4,"Exceso relativo de Omega 6","Balance de omegas favorable"),"Sin Omega 3 para evaluar")) -> Exceso relativo de Omega 6
... A54: =1+A53 -> 53 | B54: LEGUMBRES | C54: Derivados de legumbres | D54: Lecitina de soja | F54: 8 | G54: 1 | H54: 501 | I54: 41.1 | J54: 0 | K54: 0 | L54: 5.9 | M54: 3 | N54: 2.9 | O54: 0 | P54: 0 | Q54: 53 | R54: 13 | S54: 5 | T54: 35 | U54: 0 | V54: 0 | W54: 0 | X54: 0 | Y54: 0 | Z54: 0 | AA54: 0 | AB54: 0 | AC54: 0 | AD54: 0 | AE54: 0 | AF54: 0 | AG54: 0 | AH54: 0 | AI54: 0 | AJ54: 0 | AK54: 0 | AL54: 3.1 | AM54: 0 | AN54: 0 | AO54: 0 | AP54: 0 | AQ54: 0 | AR54: 1.2 | AS54: 0 | AT54: 0 | AU54: 0 | AV54: =IFERROR(VLOOKUP(IFERROR(VLOOKUP(D54,Mapa_Similitud!$A$2:$B$2000,2,FALSE()),D54),Hoja1!$A$2:$K$1000,2,FALSE()),IFERROR(VLOOKUP(IFERROR(VLOOKUP(D54,Mapa_Similitud!$A$2:$B$2000,2,FALSE()),D54),Omega3_Referencia!$A$2:$E$100,3,FALSE()),0)) -> 0 | AW54: =IFERROR(VLOOKUP(IFERROR(VLOOKUP(D54,Mapa_Similitud!$A$2:$B$2000,2,FALSE()),D54),Hoja1!$A$2:$K$1000,3,FALSE()),IFERROR(VLOOKUP(IFERROR(VLOOKUP(D54,Mapa_Similitud!$A$2:$B$2000,2,FALSE()),D54),Omega3_Referencia!$A$2:$E$100,4,FALSE()),"N/A")) -> N/A | AX54: =IFERROR(VLOOKUP(IFERROR(VLOOKUP(D54,Mapa_Similitud!$A$2:$B$2000,2,FALSE()),D54),Hoja1!$A$2:$K$1000,5,FALSE()),0) -> 0 | AY54: =IFERROR(VLOOKUP(IFERROR(VLOOKUP(D54,Mapa_Similitud!$A$2:$B$2000,2,FALSE()),D54),Hoja1!$A$2:$K$1000,7,FALSE()),0) -> 0 | AZ54: =IFERROR(VLOOKUP(IFERROR(VLOOKUP(D54,Mapa_Similitud!$A$2:$B$2000,2,FALSE()),D54),Hoja1!$A$2:$K$1000,9,FALSE()),0) -> 0 | BA54: =IFERROR(K54/H54,0) -> 0 | BB54: =IFERROR(P54/H54,0) -> 0 | BC54: =IFERROR(AK54/H54,0) -> 0 | BD54: =IFERROR(AM54/H54,0) -> 0 | BE54: =IFERROR(AQ54/H54,0) -> 0 | BF54: =IFERROR(T54/R54,0) -> 2.6923077 | BG54: =IFERROR(AK54/AL54,0) -> 0 | BH54: =IFERROR(R54/Q54,0) -> 0.24528302 | BI54: =IFERROR(AQ54/AR54,0) -> 0 | BJ54: =IFERROR(N54/L54,0) -> 0.49152542 | BK54: =IFERROR(P54/L54,0) -> 0 | BL54: =IFERROR((Q54*9)/H54,0) -> 0.95209581 | BM54: =IFERROR(AP54/H54,0) -> 0 | BN54: =IF(BA54>0.2,"Muy alta fuente de proteína",IF(BA54>0.15,"Alta fuente de proteína",IF(BA54>0.1,"Media fuente de proteína","Baja fuente de proteína"))) -> Baja fuente de proteína | BO54: =IF(BB54>0.03,"Alta",IF(BB54>0.015,"Media","Baja")) & " fuente de fibra" -> Baja fuente de fibra | BP54: =IF(BC54>1.5,"Alta fuente de calcio",IF(BC54>0.8,"Media fuente de calcio","Baja fuente de calcio")) -> Baja fuente de calcio | BQ54: =IF(BD54>0.015,"Alta fuente de hierro",IF(BD54>0.008,"Media fuente de hierro","Baja fuente de hierro")) -> Baja fuente de hierro | BR54: =IF(BE54>2,"Muy alto",IF(BE54>1,"Alto",IF(BE54>0.5,"Moderado","Bajo"))) & " en sodio" -> Bajo en sodio | BS54: =IF(BF54>2,"Altamente antiinflamatorio",IF(BF54>1,"Ligeramente antiinflamatorio",IF(BF54>0.5,"Neutro","Proinflamatorio"))) -> Altamente antiinflamatorio | BT54: =IF(BL54>0.4,"Muy alto en grasas",IF(BL54>0.3,"Alto en grasas",IF(BL54>0.2,"Moderado en grasas","Bajo en grasas"))) -> Muy alto en grasas | BU54: =IF(BI54>1,"Alto riesgo de retención de líquidos",IF(BI54>0.5,"Riesgo moderado de retención","Equilibrio de líquidos ideal")) -> Equilibrio de líquidos ideal | BV54: =IF(BM54>0.5,"Alta",IF(BM54>0.2,"Media","Baja")) & " fuente de magnesio" -> Baja fuente de magnesio | BW54: =IF(AV54>=0.5,"Alta fuente de Omega 3",IF(AV54>0.1,"Ligera fuente de Omega 3","Sin aporte de Omega 3")) -> Sin aporte de Omega 3 | BX54: =IF(AX54>0.5,"Alerta: Alto en grasas trans",IF(AX54>0,"Contiene grasas trans","Libre de grasas trans")) -> Libre de grasas trans | BY54: =IF(AY54>=50,"Alto",IF(AY54>=10,"Medio","Bajo")) & " poder antioxidante" -> Bajo poder antioxidante | BZ54: =IF(AZ54>=1,"Probiótico activo","Sin probióticos") -> Sin probióticos | CA54: =IF(OR(AX54>0.5, O54>15, J54>0), "Altamente inflamatorio", IF(OR(AV54>=0.5, AY54>=50), "Antiinflamatorio", IF(OR(AX54>0, O54>5), "Moderadamente inflamatorio", "Poco inflamatorio"))) -> Poco inflamatorio | CB54: =IF(ISNUMBER(SEARCH("miel", D54)), "No irritante (Uso condicionado SII)", IF(OR(J54>0, ISNUMBER(SEARCH("cacao", D54)), ISNUMBER(SEARCH("chocolate puro", D54))), "Altamente irritante", IF(OR(AND(O54>15, BI54>1), ISNUMBER(SEARCH("chocolate", D54))), "Moderadamente irritante", "No irritante"))) -> No irritante | CC54: =IF(AV54=0,"Sin Omega 3 para evaluar",IFERROR(IF(((T54-AV54)/AV54)>4,"Exceso relativo de Omega 6","Balance de omegas favorable"),"Sin Omega 3 para evaluar")) -> Sin Omega 3 para evaluar
A55: =1+A54 -> 54 | B55: LEGUMBRES | C55: Derivados de legumbres | D55: Lentejas | E55: brotes | F55: 0.8 | G55: 1 | H55: 129 | I55: 67.7 | J55: 0 | K55: 9 | L55: 22.1 | M55: 0 | N55: 0 | O55: 0 | P55: 0 | Q55: 0.55 | R55: 0.057 | S55: 0.1 | T55: 0.22 | U55: 0 | V55: 2 | W55: 0 | X55: 0 | Y55: 0 | Z55: 0 | AA55: 0 | AB55: 0.23 | AC55: 0.13 | AD55: 1.1 | AE55: 0.19 | AF55: 100 | AG55: 0 | AH55: 0 | AI55: 0 | AJ55: 16.5 | AK55: 25 | AL55: 173 | AM55: 3.2 | AN55: 0 | AO55: 1.5 | AP55: 37 | AQ55: 11 | AR55: 322 | AS55: 0 | AT55: 0 | AU55: 0.6 | AV55: =IFERROR(VLOOKUP(IFERROR(VLOOKUP(D55,Mapa_Similitud!$A$2:$B$2000,2,FALSE()),D55),Hoja1!$A$2:$K$1000,2,FALSE()),IFERROR(VLOOKUP(IFERROR(VLOOKUP(D55,Mapa_Similitud!$A$2:$B$2000,2,FALSE()),D55),Omega3_Referencia!$A$2:$E$100,3,FALSE()),0)) -> 0.11 | AW55: =IFERROR(VLOOKUP(IFERROR(VLOOKUP(D55,Mapa_Similitud!$A$2:$B$2000,2,FALSE()),D55),Hoja1!$A$2:$K$1000,3,FALSE()),IFERROR(VLOOKUP(IFERROR(VLOOKUP(D55,Mapa_Similitud!$A$2:$B$2000,2,FALSE()),D55),Omega3_Referencia!$A$2:$E$100,4,FALSE()),"N/A")) -> ALA | AX55: =IFERROR(VLOOKUP(IFERROR(VLOOKUP(D55,Mapa_Similitud!$A$2:$B$2000,2,FALSE()),D55),Hoja1!$A$2:$K$1000,5,FALSE()),0) -> 0 | AY55: =IFERROR(VLOOKUP(IFERROR(VLOOKUP(D55,Mapa_Similitud!$A$2:$B$2000,2,FALSE()),D55),Hoja1!$A$2:$K$1000,7,FALSE()),0) -> 120 | AZ55: =IFERROR(VLOOKUP(IFERROR(VLOOKUP(D55,Mapa_Similitud!$A$2:$B$2000,2,FALSE()),D55),Hoja1!$A$2:$K$1000,9,FALSE()),0) -> 0 | BA55: =IFERROR(K55/H55,0) -> 0.069767442 | BB55: =IFERROR(P55/H55,0) -> 0 | BC55: =IFERROR(AK55/H55,0) -> 0.19379845 | BD55: =IFERROR(AM55/H55,0) -> 0.024806202 | BE55: =IFERROR(AQ55/H55,0) -> 0.085271318 | BF55: =IFERROR(T55/R55,0) -> 3.8596491 | BG55: =IFERROR(AK55/AL55,0) -> 0.14450867 | BH55: =IFERROR(R55/Q55,0) -> 0.10363636 | BI55: =IFERROR(AQ55/AR55,0) -> 0.034161491 | BJ55: =IFERROR(N55/L55,0) -> 0 | BK55: =IFERROR(P55/L55,0) -> 0 | BL55: =IFERROR((Q55*9)/H55,0) -> 0.038372093 | BM55: =IFERROR(AP55/H55,0) -> 0.28682171 | BN55: =IF(BA55>0.2,"Muy alta fuente de proteína",IF(BA55>0.15,"Alta fuente de proteína",IF(BA55>0.1,"Media fuente de proteína","Baja fuente de proteína"))) -> Baja fuente de proteína | BO55: =IF(BB55>0.03,"Alta",IF(BB55>0.015,"Media","Baja")) & " fuente de fibra" -> Baja fuente de fibra | BP55: =IF(BC55>1.5,"Alta fuente de calcio",IF(BC55>0.8,"Media fuente de calcio","Baja fuente de calcio")) -> Baja fuente de calcio | BQ55: =IF(BD55>0.015,"Alta fuente de hierro",IF(BD55>0.008,"Media fuente de hierro","Baja fuente de hierro")) -> Alta fuente de hierro | BR55: =IF(BE55>2,"Muy alto",IF(BE55>1,"Alto",IF(BE55>0.5,"Moderado","Bajo"))) & " en sodio" -> Bajo en sodio | BS55: =IF(BF55>2,"Altamente antiinflamatorio",IF(BF55>1,"Ligeramente antiinflamatorio",IF(BF55>0.5,"Neutro","Proinflamatorio"))) -> Altamente antiinflamatorio | BT55: =IF(BL55>0.4,"Muy alto en grasas",IF(BL55>0.3,"Alto en grasas",IF(BL55>0.2,"Moderado en grasas","Bajo en grasas"))) -> Bajo en grasas | BU55: =IF(BI55>1,"Alto riesgo de retención de líquidos",IF(BI55>0.5,"Riesgo moderado de retención","Equilibrio de líquidos ideal")) -> Equilibrio de líquidos ideal | BV55: =IF(BM55>0.5,"Alta",IF(BM55>0.2,"Media","Baja")) & " fuente de magnesio" -> Media fuente de magnesio | BW55: =IF(AV55>=0.5,"Alta fuente de Omega 3",IF(AV55>0.1,"Ligera fuente de Omega 3","Sin aporte de Omega 3")) -> Ligera fuente de Omega 3 | BX55: =IF(AX55>0.5,"Alerta: Alto en grasas trans",IF(AX55>0,"Contiene grasas trans","Libre de grasas trans")) -> Libre de grasas trans | BY55: =IF(AY55>=50,"Alto",IF(AY55>=10,"Medio","Bajo")) & " poder antioxidante" -> Alto poder antioxidante | BZ55: =IF(AZ55>=1,"Probiótico activo","Sin probióticos") -> Sin probióticos | CA55: =IF(OR(AX55>0.5, O55>15, J55>0), "Altamente inflamatorio", IF(OR(AV55>=0.5, AY55>=50), "Antiinflamatorio", IF(OR(AX55>0, O55>5), "Moderadamente inflamatorio", "Poco inflamatorio"))) -> Antiinflamatorio | CB55: =IF(ISNUMBER(SEARCH("miel", D55)), "No irritante (Uso condicionado SII)", IF(OR(J55>0, ISNUMBER(SEARCH("cacao", D55)), ISNUMBER(SEARCH("chocolate puro", D55))), "Altamente irritante", IF(OR(AND(O55>15, BI55>1), ISNUMBER(SEARCH("chocolate", D55))), "Moderadamente irritante", "No irritante"))) -> No irritante | CC55: =IF(AV55=0,"Sin Omega 3 para evaluar",IFERROR(IF(((T55-AV55)/AV55)>4,"Exceso relativo de Omega 6","Balance de omegas favorable"),"Sin Omega 3 para evaluar")) -> Balance de omegas favorable
A56: =1+A55 -> 55 | B56: LEGUMBRES | C56: Derivados de legumbres | D56: Salchicha vegetal | F56: 4.5 | G56: 1 | H56: 283 | I56: 50.4 | J56: 0 | K56: 18.5 | L56: 9.8 | M56: 9.8 | N56: 0 | O56: 0 | P56: 2.8 | Q56: 18.2 | R56: 2.9 | S56: 4.5 | T56: 9.3 | U56: 0 | V56: 0 | W56: 0 | X56: 0 | Y56: 0 | Z56: 2.1 | AA56: 0 | AB56: 2.3 | AC56: 11.2 | AD56: 0.83 | AE56: 0 | AF56: 0 | AG56: 26 | AH56: 0 | AI56: 0 | AJ56: 0 | AK56: 63 | AL56: 225 | AM56: 372 | AN56: 0 | AO56: 1.5 | AP56: 36 | AQ56: 888 | AR56: 231 | AS56: 0 | AT56: 0 | AU56: 144 | AV56: =IFERROR(VLOOKUP(IFERROR(VLOOKUP(D56,Mapa_Similitud!$A$2:$B$2000,2,FALSE()),D56),Hoja1!$A$2:$K$1000,2,FALSE()),IFERROR(VLOOKUP(IFERROR(VLOOKUP(D56,Mapa_Similitud!$A$2:$B$2000,2,FALSE()),D56),Omega3_Referencia!$A$2:$E$100,3,FALSE()),0)) -> 0.05 | AW56: =IFERROR(VLOOKUP(IFERROR(VLOOKUP(D56,Mapa_Similitud!$A$2:$B$2000,2,FALSE()),D56),Hoja1!$A$2:$K$1000,3,FALSE()),IFERROR(VLOOKUP(IFERROR(VLOOKUP(D56,Mapa_Similitud!$A$2:$B$2000,2,FALSE()),D56),Omega3_Referencia!$A$2:$E$100,4,FALSE()),"N/A")) -> ALA | AX56: =IFERROR(VLOOKUP(IFERROR(VLOOKUP(D56,Mapa_Similitud!$A$2:$B$2000,2,FALSE()),D56),Hoja1!$A$2:$K$1000,5,FALSE()),0) -> 0.3 | AY56: =IFERROR(VLOOKUP(IFERROR(VLOOKUP(D56,Mapa_Similitud!$A$2:$B$2000,2,FALSE()),D56),Hoja1!$A$2:$K$1000,7,FALSE()),0) -> 20 | AZ56: =IFERROR(VLOOKUP(IFERROR(VLOOKUP(D56,Mapa_Similitud!$A$2:$B$2000,2,FALSE()),D56),Hoja1!$A$2:$K$1000,9,FALSE()),0) -> 0 | BA56: =IFERROR(K56/H56,0) -> 0.065371025 | BB56: =IFERROR(P56/H56,0) -> 0.0098939929 | BC56: =IFERROR(AK56/H56,0) -> 0.22261484 | BD56: =IFERROR(AM56/H56,0) -> 1.3144876 | BE56: =IFERROR(AQ56/H56,0) -> 3.1378092 | BF56: =IFERROR(T56/R56,0) -> 3.2068966 | BG56: =IFERROR(AK56/AL56,0) -> 0.28 | BH56: =IFERROR(R56/Q56,0) -> 0.15934066 | BI56: =IFERROR(AQ56/AR56,0) -> 3.8441558 | BJ56: =IFERROR(N56/L56,0) -> 0 | BK56: =IFERROR(P56/L56,0) -> 0.28571429 | BL56: =IFERROR((Q56*9)/H56,0) -> 0.57879859 | BM56: =IFERROR(AP56/H56,0) -> 0.12720848 | BN56: =IF(BA56>0.2,"Muy alta fuente de proteína",IF(BA56>0.15,"Alta fuente de proteína",IF(BA56>0.1,"Media fuente de proteína","Baja fuente de proteína"))) -> Baja fuente de proteína | BO56: =IF(BB56>0.03,"Alta",IF(BB56>0.015,"Media","Baja")) & " fuente de fibra" -> Baja fuente de fibra | BP56: =IF(BC56>1.5,"Alta fuente de calcio",IF(BC56>0.8,"Media fuente de calcio","Baja fuente de calcio")) -> Baja fuente de calcio | BQ56: =IF(BD56>0.015,"Alta fuente de hierro",IF(BD56>0.008,"Media fuente de hierro","Baja fuente de hierro")) -> Alta fuente de hierro | BR56: =IF(BE56>2,"Muy alto",IF(BE56>1,"Alto",IF(BE56>0.5,"Moderado","Bajo"))) & " en sodio" -> Muy alto en sodio | BS56: =IF(BF56>2,"Altamente antiinflamatorio",IF(BF56>1,"Ligeramente antiinflamatorio",IF(BF56>0.5,"Neutro","Proinflamatorio"))) -> Altamente antiinflamatorio | BT56: =IF(BL56>0.4,"Muy alto en grasas",IF(BL56>0.3,"Alto en grasas",IF(BL56>0.2,"Moderado en grasas","Bajo en grasas"))) -> Muy alto en grasas | BU56: =IF(BI56>1,"Alto riesgo de retención de líquidos",IF(BI56>0.5,"Riesgo moderado de retención","Equilibrio de líquidos ideal")) -> Alto riesgo de retención de líquidos | BV56: =IF(BM56>0.5,"Alta",IF(BM56>0.2,"Media","Baja")) & " fuente de magnesio" -> Baja fuente de magnesio | BW56: =IF(AV56>=0.5,"Alta fuente de Omega 3",IF(AV56>0.1,"Ligera fuente de Omega 3","Sin aporte de Omega 3")) -> Sin aporte de Omega 3 | BX56: =IF(AX56>0.5,"Alerta: Alto en grasas trans",IF(AX56>0,"Contiene grasas trans","Libre de grasas trans")) -> Contiene grasas trans | BY56: =IF(AY56>=50,"Alto",IF(AY56>=10,"Medio","Bajo")) & " poder antioxidante" -> Medio poder antioxidante | BZ56: =IF(AZ56>=1,"Probiótico activo","Sin probióticos") -> Sin probióticos | CA56: =IF(OR(AX56>0.5, O56>15, J56>0), "Altamente inflamatorio", IF(OR(AV56>=0.5, AY56>=50), "Antiinflamatorio", IF(OR(AX56>0, O56>5), "Moderadamente inflamatorio", "Poco inflamatorio"))) -> Moderadamente inflamatorio | CB56: =IF(ISNUMBER(SEARCH("miel", D56)), "No irritante (Uso condicionado SII)", IF(OR(J56>0, ISNUMBER(SEARCH("cacao", D56)), ISNUMBER(SEARCH("chocolate puro", D56))), "Altamente irritante", IF(OR(AND(O56>15, BI56>1), ISNUMBER(SEARCH("chocolate", D56))), "Moderadamente irritante", "No irritante"))) -> No irritante | CC56: =IF(AV56=0,"Sin Omega 3 para evaluar",IFERROR(IF(((T56-AV56)/AV56)>4,"Exceso relativo de Omega 6","Balance de omegas favorable"),"Sin Omega 3 para evaluar")) -> Exceso relativo de Omega 6
A57: =1+A56 -> 56 | B57: LEGUMBRES | C57: Derivados de legumbres | D57: Tempeh | F57: 4.6 | G57: 1 | H57: 104 | I57: 76 | J57: 0 | K57: 18 | L57: 3.5 | M57: 3 | N57: 0.5 | O57: 0 | P57: 0 | Q57: 1.5 | R57: 0 | S57: 0 | T57: 0 | U57: 0 | V57: 0 | W57: 0 | X57: 0 | Y57: 0 | Z57: 0 | AA57: 0 | AB57: 0.078 | AC57: 0.36 | AD57: 2.6 | AE57: 0.22 | AF57: 24 | AG57: 0.08 | AH57: 0 | AI57: 0 | AJ57: 0 | AK57: 111 | AL57: 266 | AM57: 2.7 | AN57: 0 | AO57: 1.1 | AP57: 81 | AQ57: 9 | AR57: 412 | AS57: 0 | AT57: 0 | AU57: 0 | AV57: =IFERROR(VLOOKUP(IFERROR(VLOOKUP(D57,Mapa_Similitud!$A$2:$B$2000,2,FALSE()),D57),Hoja1!$A$2:$K$1000,2,FALSE()),IFERROR(VLOOKUP(IFERROR(VLOOKUP(D57,Mapa_Similitud!$A$2:$B$2000,2,FALSE()),D57),Omega3_Referencia!$A$2:$E$100,3,FALSE()),0)) -> 0.35 | AW57: =IFERROR(VLOOKUP(IFERROR(VLOOKUP(D57,Mapa_Similitud!$A$2:$B$2000,2,FALSE()),D57),Hoja1!$A$2:$K$1000,3,FALSE()),IFERROR(VLOOKUP(IFERROR(VLOOKUP(D57,Mapa_Similitud!$A$2:$B$2000,2,FALSE()),D57),Omega3_Referencia!$A$2:$E$100,4,FALSE()),"N/A")) -> ALA | AX57: =IFERROR(VLOOKUP(IFERROR(VLOOKUP(D57,Mapa_Similitud!$A$2:$B$2000,2,FALSE()),D57),Hoja1!$A$2:$K$1000,5,FALSE()),0) -> 0 | AY57: =IFERROR(VLOOKUP(IFERROR(VLOOKUP(D57,Mapa_Similitud!$A$2:$B$2000,2,FALSE()),D57),Hoja1!$A$2:$K$1000,7,FALSE()),0) -> 110 | AZ57: =IFERROR(VLOOKUP(IFERROR(VLOOKUP(D57,Mapa_Similitud!$A$2:$B$2000,2,FALSE()),D57),Hoja1!$A$2:$K$1000,9,FALSE()),0) -> 1 | BA57: =IFERROR(K57/H57,0) -> 0.17307692 | BB57: =IFERROR(P57/H57,0) -> 0 | BC57: =IFERROR(AK57/H57,0) -> 1.0673077 | BD57: =IFERROR(AM57/H57,0) -> 0.025961538 | BE57: =IFERROR(AQ57/H57,0) -> 0.086538462 | BF57: =IFERROR(T57/R57,0) -> 0 | BG57: =IFERROR(AK57/AL57,0) -> 0.41729323 | BH57: =IFERROR(R57/Q57,0) -> 0 | BI57: =IFERROR(AQ57/AR57,0) -> 0.02184466 | BJ57: =IFERROR(N57/L57,0) -> 0.14285714 | BK57: =IFERROR(P57/L57,0) -> 0 | BL57: =IFERROR((Q57*9)/H57,0) -> 0.12980769 | BM57: =IFERROR(AP57/H57,0) -> 0.77884615 | BN57: =IF(BA57>0.2,"Muy alta fuente de proteína",IF(BA57>0.15,"Alta fuente de proteína",IF(BA57>0.1,"Media fuente de proteína","Baja fuente de proteína"))) -> Alta fuente de proteína | BO57: =IF(BB57>0.03,"Alta",IF(BB57>0.015,"Media","Baja")) & " fuente de fibra" -> Baja fuente de fibra | BP57: =IF(BC57>1.5,"Alta fuente de calcio",IF(BC57>0.8,"Media fuente de calcio","Baja fuente de calcio")) -> Media fuente de calcio | BQ57: =IF(BD57>0.015,"Alta fuente de hierro",IF(BD57>0.008,"Media fuente de hierro","Baja fuente de hierro")) -> Alta fuente de hierro | BR57: =IF(BE57>2,"Muy alto",IF(BE57>1,"Alto",IF(BE57>0.5,"Moderado","Bajo"))) & " en sodio" -> Bajo en sodio | BS57: =IF(BF57>2,"Altamente antiinflamatorio",IF(BF57>1,"Ligeramente antiinflamatorio",IF(BF57>0.5,"Neutro","Proinflamatorio"))) -> Proinflamatorio | BT57: =IF(BL57>0.4,"Muy alto en grasas",IF(BL57>0.3,"Alto en grasas",IF(BL57>0.2,"Moderado en grasas","Bajo en grasas"))) -> Bajo en grasas | BU57: =IF(BI57>1,"Alto riesgo de retención de líquidos",IF(BI57>0.5,"Riesgo moderado de retención","Equilibrio de líquidos ideal")) -> Equilibrio de líquidos ideal | BV57: =IF(BM57>0.5,"Alta",IF(BM57>0.2,"Media","Baja")) & " fuente de magnesio" -> Alta fuente de magnesio | BW57: =IF(AV57>=0.5,"Alta fuente de Omega 3",IF(AV57>0.1,"Ligera fuente de Omega 3","Sin aporte de Omega 3")) -> Ligera fuente de Omega 3 | BX57: =IF(AX57>0.5,"Alerta: Alto en grasas trans",IF(AX57>0,"Contiene grasas trans","Libre de grasas trans")) -> Libre de grasas trans | BY57: =IF(AY57>=50,"Alto",IF(AY57>=10,"Medio","Bajo")) & " poder antioxidante" -> Alto poder antioxidante | BZ57: =IF(AZ57>=1,"Probiótico activo","Sin probióticos") -> Probiótico activo | CA57: =IF(OR(AX57>0.5, O57>15, J57>0), "Altamente inflamatorio", IF(OR(AV57>=0.5, AY57>=50), "Antiinflamatorio", IF(OR(AX57>0, O57>5), "Moderadamente inflamatorio", "Poco inflamatorio"))) -> Antiinflamatorio | CB57: =IF(ISNUMBER(SEARCH("miel", D57)), "No irritante (Uso condicionado SII)", IF(OR(J57>0, ISNUMBER(SEARCH("cacao", D57)), ISNUMBER(SEARCH("chocolate puro", D57))), "Altamente irritante", IF(OR(AND(O57>15, BI57>1), ISNUMBER(SEARCH("chocolate", D57))), "Moderadamente irritante", "No irritante"))) -> No irritante | CC57: =IF(AV57=0,"Sin Omega 3 para evaluar",IFERROR(IF(((T57-AV57)/AV57)>4,"Exceso relativo de Omega 6","Balance de omegas favorable"),"Sin Omega 3 para evaluar")) -> Balance de omegas favorable
A58: =1+A57 -> 57 | B58: LEGUMBRES | C58: Legumbres en conserva | D58: Garbanzo en conserva | F58: 1.8 | G58: 1 | H58: 120 | I58: 71.7 | J58: 0 | K58: 7.2 | L58: 14.1 | M58: 13.7 | N58: 0.4 | O58: 0 | P58: 4.1 | Q58: 2.9 | R58: 0.31 | S58: 0.72 | T58: 1.3 | U58: 0 | V58: 3.5 | W58: 0 | X58: 21 | Y58: 0 | Z58: 1.6 | AA58: 132 | AB58: 0.13 | AC58: 0.06 | AD58: 1.2 | AE58: 0.04 | AF58: 67 | AG58: 0 | AH58: 0.29 | AI58: 0 | AJ58: 0 | AK58: 43 | AL58: 335 | AM58: 2.8 | AN58: 1 | AO58: 1.2 | AP58: 24 | AQ58: 220 | AR58: 110 | AS58: 0.6 | AT58: 0.17 | AU58: 1 | AV58: =IFERROR(VLOOKUP(IFERROR(VLOOKUP(D58,Mapa_Similitud!$A$2:$B$2000,2,FALSE()),D58),Hoja1!$A$2:$K$1000,2,FALSE()),IFERROR(VLOOKUP(IFERROR(VLOOKUP(D58,Mapa_Similitud!$A$2:$B$2000,2,FALSE()),D58),Omega3_Referencia!$A$2:$E$100,3,FALSE()),0)) -> 0.03 | AW58: =IFERROR(VLOOKUP(IFERROR(VLOOKUP(D58,Mapa_Similitud!$A$2:$B$2000,2,FALSE()),D58),Hoja1!$A$2:$K$1000,3,FALSE()),IFERROR(VLOOKUP(IFERROR(VLOOKUP(D58,Mapa_Similitud!$A$2:$B$2000,2,FALSE()),D58),Omega3_Referencia!$A$2:$E$100,4,FALSE()),"N/A")) -> ALA | AX58: =IFERROR(VLOOKUP(IFERROR(VLOOKUP(D58,Mapa_Similitud!$A$2:$B$2000,2,FALSE()),D58),Hoja1!$A$2:$K$1000,5,FALSE()),0) -> 0 | AY58: =IFERROR(VLOOKUP(IFERROR(VLOOKUP(D58,Mapa_Similitud!$A$2:$B$2000,2,FALSE()),D58),Hoja1!$A$2:$K$1000,7,FALSE()),0) -> 40 | AZ58: =IFERROR(VLOOKUP(IFERROR(VLOOKUP(D58,Mapa_Similitud!$A$2:$B$2000,2,FALSE()),D58),Hoja1!$A$2:$K$1000,9,FALSE()),0) -> 0 | BA58: =IFERROR(K58/H58,0) -> 0.06 | BB58: =IFERROR(P58/H58,0) -> 0.034166667 | BC58: =IFERROR(AK58/H58,0) -> 0.35833333 | BD58: =IFERROR(AM58/H58,0) -> 0.023333333 | BE58: =IFERROR(AQ58/H58,0) -> 1.8333333 | BF58: =IFERROR(T58/R58,0) -> 4.1935484 | BG58: =IFERROR(AK58/AL58,0) -> 0.12835821 | BH58: =IFERROR(R58/Q58,0) -> 0.10689655 | BI58: =IFERROR(AQ58/AR58,0) -> 2 | BJ58: =IFERROR(N58/L58,0) -> 0.028368794 | BK58: =IFERROR(P58/L58,0) -> 0.29078014 | BL58: =IFERROR((Q58*9)/H58,0) -> 0.2175 | BM58: =IFERROR(AP58/H58,0) -> 0.2 | BN58: =IF(BA58>0.2,"Muy alta fuente de proteína",IF(BA58>0.15,"Alta fuente de proteína",IF(BA58>0.1,"Media fuente de proteína","Baja fuente de proteína"))) -> Baja fuente de proteína | BO58: =IF(BB58>0.03,"Alta",IF(BB58>0.015,"Media","Baja")) & " fuente de fibra" -> Alta fuente de fibra | BP58: =IF(BC58>1.5,"Alta fuente de calcio",IF(BC58>0.8,"Media fuente de calcio","Baja fuente de calcio")) -> Baja fuente de calcio | BQ58: =IF(BD58>0.015,"Alta fuente de hierro",IF(BD58>0.008,"Media fuente de hierro","Baja fuente de hierro")) -> Alta fuente de hierro | BR58: =IF(BE58>2,"Muy alto",IF(BE58>1,"Alto",IF(BE58>0.5,"Moderado","Bajo"))) & " en sodio" -> Alto en sodio | BS58: =IF(BF58>2,"Altamente antiinflamatorio",IF(BF58>1,"Ligeramente antiinflamatorio",IF(BF58>0.5,"Neutro","Proinflamatorio"))) -> Altamente antiinflamatorio | BT58: =IF(BL58>0.4,"Muy alto en grasas",IF(BL58>0.3,"Alto en grasas",IF(BL58>0.2,"Moderado en grasas","Bajo en grasas"))) -> Moderado en grasas | BU58: =IF(BI58>1,"Alto riesgo de retención de líquidos",IF(BI58>0.5,"Riesgo moderado de retención","Equilibrio de líquidos ideal")) -> Alto riesgo de retención de líquidos | BV58: =IF(BM58>0.5,"Alta",IF(BM58>0.2,"Media","Baja")) & " fuente de magnesio" -> Baja fuente de magnesio | BW58: =IF(AV58>=0.5,"Alta fuente de Omega 3",IF(AV58>0.1,"Ligera fuente de Omega 3","Sin aporte de Omega 3")) -> Sin aporte de Omega 3 | BX58: =IF(AX58>0.5,"Alerta: Alto en grasas trans",IF(AX58>0,"Contiene grasas trans","Libre de grasas trans")) -> Libre de grasas trans | BY58: =IF(AY58>=50,"Alto",IF(AY58>=10,"Medio","Bajo")) & " poder antioxidante" -> Medio poder antioxidante | BZ58: =IF(AZ58>=1,"Probiótico activo","Sin probióticos") -> Sin probióticos | CA58: =IF(OR(AX58>0.5, O58>15, J58>0), "Altamente inflamatorio", IF(OR(AV58>=0.5, AY58>=50), "Antiinflamatorio", IF(OR(AX58>0, O58>5), "Moderadamente inflamatorio", "Poco inflamatorio"))) -> Poco inflamatorio | CB58: =IF(ISNUMBER(SEARCH("miel", D58)), "No irritante (Uso condicionado SII)", IF(OR(J58>0, ISNUMBER(SEARCH("cacao", D58)), ISNUMBER(SEARCH("chocolate puro", D58))), "Altamente irritante", IF(OR(AND(O58>15, BI58>1), ISNUMBER(SEARCH("chocolate", D58))), "Moderadamente irritante", "No irritante"))) -> No irritante | CC58: =IF(AV58=0,"Sin Omega 3 para evaluar",IFERROR(IF(((T58-AV58)/AV58)>4,"Exceso relativo de Omega 6","Balance de omegas favorable"),"Sin Omega 3 para evaluar")) -> Exceso relativo de Omega 6
A59: =1+A58 -> 58 | B59: LEGUMBRES | C59: Legumbres en conserva | D59: Judía blanca en conserva | F59: 1.8 | G59: 1 | H59: 101 | I59: 72.9 | J59: 0 | K59: 6.7 | L59: 15.7 | M59: 14.7 | N59: 1 | O59: 0 | P59: 4.4 | Q59: 0.3 | R59: 0.07 | S59: 0.01 | T59: 0.12 | U59: 0 | V59: 0 | W59: 0 | X59: 0 | Y59: 0 | Z59: 0.2 | AA59: 9.5 | AB59: 0.1 | AC59: 0.04 | AD59: 1.3 | AE59: 0.07 | AF59: 60 | AG59: 0 | AH59: 0.17 | AI59: 0 | AJ59: 0 | AK59: 71 | AL59: 84 | AM59: 2.8 | AN59: 1 | AO59: 2.3 | AP59: 23 | AQ59: 243 | AR59: 362 | AS59: 0.22 | AT59: 0.47 | AU59: 0.6 | AV59: =IFERROR(VLOOKUP(IFERROR(VLOOKUP(D59,Mapa_Similitud!$A$2:$B$2000,2,FALSE()),D59),Hoja1!$A$2:$K$1000,2,FALSE()),IFERROR(VLOOKUP(IFERROR(VLOOKUP(D59,Mapa_Similitud!$A$2:$B$2000,2,FALSE()),D59),Omega3_Referencia!$A$2:$E$100,3,FALSE()),0)) -> 0.1 | AW59: =IFERROR(VLOOKUP(IFERROR(VLOOKUP(D59,Mapa_Similitud!$A$2:$B$2000,2,FALSE()),D59),Hoja1!$A$2:$K$1000,3,FALSE()),IFERROR(VLOOKUP(IFERROR(VLOOKUP(D59,Mapa_Similitud!$A$2:$B$2000,2,FALSE()),D59),Omega3_Referencia!$A$2:$E$100,4,FALSE()),"N/A")) -> ALA | AX59: =IFERROR(VLOOKUP(IFERROR(VLOOKUP(D59,Mapa_Similitud!$A$2:$B$2000,2,FALSE()),D59),Hoja1!$A$2:$K$1000,5,FALSE()),0) -> 0 | AY59: =IFERROR(VLOOKUP(IFERROR(VLOOKUP(D59,Mapa_Similitud!$A$2:$B$2000,2,FALSE()),D59),Hoja1!$A$2:$K$1000,7,FALSE()),0) -> 65 | AZ59: =IFERROR(VLOOKUP(IFERROR(VLOOKUP(D59,Mapa_Similitud!$A$2:$B$2000,2,FALSE()),D59),Hoja1!$A$2:$K$1000,9,FALSE()),0) -> 0 | BA59: =IFERROR(K59/H59,0) -> 0.066336634 | BB59: =IFERROR(P59/H59,0) -> 0.043564356 | BC59: =IFERROR(AK59/H59,0) -> 0.7029703 | BD59: =IFERROR(AM59/H59,0) -> 0.027722772 | BE59: =IFERROR(AQ59/H59,0) -> 2.4059406 | BF59: =IFERROR(T59/R59,0) -> 1.7142857 | BG59: =IFERROR(AK59/AL59,0) -> 0.8452381 | BH59: =IFERROR(R59/Q59,0) -> 0.23333333 | BI59: =IFERROR(AQ59/AR59,0) -> 0.67127072 | BJ59: =IFERROR(N59/L59,0) -> 0.063694268 | BK59: =IFERROR(P59/L59,0) -> 0.28025478 | BL59: =IFERROR((Q59*9)/H59,0) -> 0.026732673 | BM59: =IFERROR(AP59/H59,0) -> 0.22772277 | BN59: =IF(BA59>0.2,"Muy alta fuente de proteína",IF(BA59>0.15,"Alta fuente de proteína",IF(BA59>0.1,"Media fuente de proteína","Baja fuente de proteína"))) -> Baja fuente de proteína | BO59: =IF(BB59>0.03,"Alta",IF(BB59>0.015,"Media","Baja")) & " fuente de fibra" -> Alta fuente de fibra | BP59: =IF(BC59>1.5,"Alta fuente de calcio",IF(BC59>0.8,"Media fuente de calcio","Baja fuente de calcio")) -> Baja fuente de calcio | BQ59: =IF(BD59>0.015,"Alta fuente de hierro",IF(BD59>0.008,"Media fuente de hierro","Baja fuente de hierro")) -> Alta fuente de hierro | BR59: =IF(BE59>2,"Muy alto",IF(BE59>1,"Alto",IF(BE59>0.5,"Moderado","Bajo"))) & " en sodio" -> Muy alto en sodio | BS59: =IF(BF59>2,"Altamente antiinflamatorio",IF(BF59>1,"Ligeramente antiinflamatorio",IF(BF59>0.5,"Neutro","Proinflamatorio"))) -> Ligeramente antiinflamatorio | BT59: =IF(BL59>0.4,"Muy alto en grasas",IF(BL59>0.3,"Alto en grasas",IF(BL59>0.2,"Moderado en grasas","Bajo en grasas"))) -> Bajo en grasas | BU59: =IF(BI59>1,"Alto riesgo de retención de líquidos",IF(BI59>0.5,"Riesgo moderado de retención","Equilibrio de líquidos ideal")) -> Riesgo moderado de retención | BV59: =IF(BM59>0.5,"Alta",IF(BM59>0.2,"Media","Baja")) & " fuente de magnesio" -> Media fuente de magnesio | BW59: =IF(AV59>=0.5,"Alta fuente de Omega 3",IF(AV59>0.1,"Ligera fuente de Omega 3","Sin aporte de Omega 3")) -> Sin aporte de Omega 3 | BX59: =IF(AX59>0.5,"Alerta: Alto en grasas trans",IF(AX59>0,"Contiene grasas trans","Libre de grasas trans")) -> Libre de grasas trans | BY59: =IF(AY59>=50,"Alto",IF(AY59>=10,"Medio","Bajo")) & " poder antioxidante" -> Alto poder antioxidante | BZ59: =IF(AZ59>=1,"Probiótico activo","Sin probióticos") -> Sin probióticos | CA59: =IF(OR(AX59>0.5, O59>15, J59>0), "Altamente inflamatorio", IF(OR(AV59>=0.5, AY59>=50), "Antiinflamatorio", IF(OR(AX59>0, O59>5), "Moderadamente inflamatorio", "Poco inflamatorio"))) -> Antiinflamatorio | CB59: =IF(ISNUMBER(SEARCH("miel", D59)), "No irritante (Uso condicionado SII)", IF(OR(J59>0, ISNUMBER(SEARCH("cacao", D59)), ISNUMBER(SEARCH("chocolate puro", D59))), "Altamente irritante", IF(OR(AND(O59>15, BI59>1), ISNUMBER(SEARCH("chocolate", D59))), "Moderadamente irritante", "No irritante"))) -> No irritante | CC59: =IF(AV59=0,"Sin Omega 3 para evaluar",IFERROR(IF(((T59-AV59)/AV59)>4,"Exceso relativo de Omega 6","Balance de omegas favorable"),"Sin Omega 3 para evaluar")) -> Balance de omegas favorable
A60: =1+A59 -> 59 | B60: LEGUMBRES | C60: Legumbres en conserva | D60: Judía pinta en conserva | F60: 1.8 | G60: 1 | H60: 84.2 | I60: 76.9 | J60: 0 | K60: 8.4 | L60: 9.9 | M60: 9.4 | N60: 0.5 | O60: 0 | P60: 4.6 | Q60: 0.2 | R60: 0 | S60: 0 | T60: 0.16 | U60: 0 | V60: 0 | W60: 0 | X60: 0 | Y60: 0 | Z60: 0.24 | AA60: 9.5 | AB60: 0.16 | AC60: 0.07 | AD60: 2.2 | AE60: 0.1 | AF60: 60 | AG60: 0 | AH60: 0.14 | AI60: 0 | AJ60: 1 | AK60: 66 | AL60: 92 | AM60: 2.5 | AN60: 1 | AO60: 2.3 | AP60: 27 | AQ60: 294 | AR60: 420 | AS60: 0.22 | AT60: 0.14 | AU60: 7.1 | AV60: =IFERROR(VLOOKUP(IFERROR(VLOOKUP(D60,Mapa_Similitud!$A$2:$B$2000,2,FALSE()),D60),Hoja1!$A$2:$K$1000,2,FALSE()),IFERROR(VLOOKUP(IFERROR(VLOOKUP(D60,Mapa_Similitud!$A$2:$B$2000,2,FALSE()),D60),Omega3_Referencia!$A$2:$E$100,3,FALSE()),0)) -> 0.09 | AW60: =IFERROR(VLOOKUP(IFERROR(VLOOKUP(D60,Mapa_Similitud!$A$2:$B$2000,2,FALSE()),D60),Hoja1!$A$2:$K$1000,3,FALSE()),IFERROR(VLOOKUP(IFERROR(VLOOKUP(D60,Mapa_Similitud!$A$2:$B$2000,2,FALSE()),D60),Omega3_Referencia!$A$2:$E$100,4,FALSE()),"N/A")) -> ALA | AX60: =IFERROR(VLOOKUP(IFERROR(VLOOKUP(D60,Mapa_Similitud!$A$2:$B$2000,2,FALSE()),D60),Hoja1!$A$2:$K$1000,5,FALSE()),0) -> 0 | AY60: =IFERROR(VLOOKUP(IFERROR(VLOOKUP(D60,Mapa_Similitud!$A$2:$B$2000,2,FALSE()),D60),Hoja1!$A$2:$K$1000,7,FALSE()),0) -> 180 | AZ60: =IFERROR(VLOOKUP(IFERROR(VLOOKUP(D60,Mapa_Similitud!$A$2:$B$2000,2,FALSE()),D60),Hoja1!$A$2:$K$1000,9,FALSE()),0) -> 0 | BA60: =IFERROR(K60/H60,0) -> 0.09976247 | BB60: =IFERROR(P60/H60,0) -> 0.054631829 | BC60: =IFERROR(AK60/H60,0) -> 0.78384798 | BD60: =IFERROR(AM60/H60,0) -> 0.029691211 | BE60: =IFERROR(AQ60/H60,0) -> 3.4916865 | BF60: =IFERROR(T60/R60,0) -> 0 | BG60: =IFERROR(AK60/AL60,0) -> 0.7173913 | BH60: =IFERROR(R60/Q60,0) -> 0 | BI60: =IFERROR(AQ60/AR60,0) -> 0.7 | BJ60: =IFERROR(N60/L60,0) -> 0.050505051 | BK60: =IFERROR(P60/L60,0) -> 0.46464646 | BL60: =IFERROR((Q60*9)/H60,0) -> 0.021377672 | BM60: =IFERROR(AP60/H60,0) -> 0.32066508 | BN60: =IF(BA60>0.2,"Muy alta fuente de proteína",IF(BA60>0.15,"Alta fuente de proteína",IF(BA60>0.1,"Media fuente de proteína","Baja fuente de proteína"))) -> Baja fuente de proteína | BO60: =IF(BB60>0.03,"Alta",IF(BB60>0.015,"Media","Baja")) & " fuente de fibra" -> Alta fuente de fibra | BP60: =IF(BC60>1.5,"Alta fuente de calcio",IF(BC60>0.8,"Media fuente de calcio","Baja fuente de calcio")) -> Baja fuente de calcio | BQ60: =IF(BD60>0.015,"Alta fuente de hierro",IF(BD60>0.008,"Media fuente de hierro","Baja fuente de hierro")) -> Alta fuente de hierro | BR60: =IF(BE60>2,"Muy alto",IF(BE60>1,"Alto",IF(BE60>0.5,"Moderado","Bajo"))) & " en sodio" -> Muy alto en sodio | BS60: =IF(BF60>2,"Altamente antiinflamatorio",IF(BF60>1,"Ligeramente antiinflamatorio",IF(BF60>0.5,"Neutro","Proinflamatorio"))) -> Proinflamatorio | BT60: =IF(BL60>0.4,"Muy alto en grasas",IF(BL60>0.3,"Alto en grasas",IF(BL60>0.2,"Moderado en grasas","Bajo en grasas"))) -> Bajo en grasas | BU60: =IF(BI60>1,"Alto riesgo de retención de líquidos",IF(BI60>0.5,"Riesgo moderado de retención","Equilibrio de líquidos ideal")) -> Riesgo moderado de retención | BV60: =IF(BM60>0.5,"Alta",IF(BM60>0.2,"Media","Baja")) & " fuente de magnesio" -> Media fuente de magnesio | BW60: =IF(AV60>=0.5,"Alta fuente de Omega 3",IF(AV60>0.1,"Ligera fuente de Omega 3","Sin aporte de Omega 3")) -> Sin aporte de Omega 3 | BX60: =IF(AX60>0.5,"Alerta: Alto en grasas trans",IF(AX60>0,"Contiene grasas trans","Libre de grasas trans")) -> Libre de grasas trans | BY60: =IF(AY60>=50,"Alto",IF(AY60>=10,"Medio","Bajo")) & " poder antioxidante" -> Alto poder antioxidante | BZ60: =IF(AZ60>=1,"Probiótico activo","Sin probióticos") -> Sin probióticos | CA60: =IF(OR(AX60>0.5, O60>15, J60>0), "Altamente inflamatorio", IF(OR(AV60>=0.5, AY60>=50), "Antiinflamatorio", IF(OR(AX60>0, O60>5), "Moderadamente inflamatorio", "Poco inflamatorio"))) -> Antiinflamatorio | CB60: =IF(ISNUMBER(SEARCH("miel", D60)), "No irritante (Uso condicionado SII)", IF(OR(J60>0, ISNUMBER(SEARCH("cacao", D60)), ISNUMBER(SEARCH("chocolate puro", D60))), "Altamente irritante", IF(OR(AND(O60>15, BI60>1), ISNUMBER(SEARCH("chocolate", D60))), "Moderadamente irritante", "No irritante"))) -> No irritante | CC60: =IF(AV60=0,"Sin Omega 3 para evaluar",IFERROR(IF(((T60-AV60)/AV60)>4,"Exceso relativo de Omega 6","Balance de omegas favorable"),"Sin Omega 3 para evaluar")) -> Balance de omegas favorable
A61: =1+A60 -> 60 | B61: LEGUMBRES | C61: Legumbres en conserva | D61: Lenteja en conserva | F61: 1.8 | G61: 1 | H61: 109 | I61: 71.9 | J61: 0 | K61: 8.8 | L61: 14.9 | M61: 14.5 | N61: 0.4 | O61: 0 | P61: 3.8 | Q61: 0.7 | R61: 0.1 | S61: 0.1 | T61: 0.3 | U61: 0 | V61: 0 | W61: 0 | X61: 0 | Y61: 0 | Z61: 0 | AA61: 61.5 | AB61: 0.14 | AC61: 0.07 | AD61: 1.8 | AE61: 0.28 | AF61: 30 | AG61: 0 | AH61: 0.2 | AI61: 0 | AJ61: 0 | AK61: 22 | AL61: 130 | AM61: 3.5 | AN61: 1 | AO61: 1.4 | AP61: 16 | AQ61: 238 | AR61: 310 | AS61: 0.5 | AT61: 0.25 | AU61: 2.8 | AV61: =IFERROR(VLOOKUP(IFERROR(VLOOKUP(D61,Mapa_Similitud!$A$2:$B$2000,2,FALSE()),D61),Hoja1!$A$2:$K$1000,2,FALSE()),IFERROR(VLOOKUP(IFERROR(VLOOKUP(D61,Mapa_Similitud!$A$2:$B$2000,2,FALSE()),D61),Omega3_Referencia!$A$2:$E$100,3,FALSE()),0)) -> 0.08 | AW61: =IFERROR(VLOOKUP(IFERROR(VLOOKUP(D61,Mapa_Similitud!$A$2:$B$2000,2,FALSE()),D61),Hoja1!$A$2:$K$1000,3,FALSE()),IFERROR(VLOOKUP(IFERROR(VLOOKUP(D61,Mapa_Similitud!$A$2:$B$2000,2,FALSE()),D61),Omega3_Referencia!$A$2:$E$100,4,FALSE()),"N/A")) -> ALA | AX61: =IFERROR(VLOOKUP(IFERROR(VLOOKUP(D61,Mapa_Similitud!$A$2:$B$2000,2,FALSE()),D61),Hoja1!$A$2:$K$1000,5,FALSE()),0) -> 0 | AY61: =IFERROR(VLOOKUP(IFERROR(VLOOKUP(D61,Mapa_Similitud!$A$2:$B$2000,2,FALSE()),D61),Hoja1!$A$2:$K$1000,7,FALSE()),0) -> 80 | AZ61: =IFERROR(VLOOKUP(IFERROR(VLOOKUP(D61,Mapa_Similitud!$A$2:$B$2000,2,FALSE()),D61),Hoja1!$A$2:$K$1000,9,FALSE()),0) -> 0 | BA61: =IFERROR(K61/H61,0) -> 0.080733945 | BB61: =IFERROR(P61/H61,0) -> 0.034862385 | BC61: =IFERROR(AK61/H61,0) -> 0.20183486 | BD61: =IFERROR(AM61/H61,0) -> 0.032110092 | BE61: =IFERROR(AQ61/H61,0) -> 2.1834862 | BF61: =IFERROR(T61/R61,0) -> 3 | BG61: =IFERROR(AK61/AL61,0) -> 0.16923077 | BH61: =IFERROR(R61/Q61,0) -> 0.14285714 | BI61: =IFERROR(AQ61/AR61,0) -> 0.76774194 | BJ61: =IFERROR(N61/L61,0) -> 0.026845638 | BK61: =IFERROR(P61/L61,0) -> 0.25503356 | BL61: =IFERROR((Q61*9)/H61,0) -> 0.057798165 | BM61: =IFERROR(AP61/H61,0) -> 0.14678899 | BN61: =IF(BA61>0.2,"Muy alta fuente de proteína",IF(BA61>0.15,"Alta fuente de proteína",IF(BA61>0.1,"Media fuente de proteína","Baja fuente de proteína"))) -> Baja fuente de proteína | BO61: =IF(BB61>0.03,"Alta",IF(BB61>0.015,"Media","Baja")) & " fuente de fibra" -> Alta fuente de fibra | BP61: =IF(BC61>1.5,"Alta fuente de calcio",IF(BC61>0.8,"Media fuente de calcio","Baja fuente de calcio")) -> Baja fuente de calcio | BQ61: =IF(BD61>0.015,"Alta fuente de hierro",IF(BD61>0.008,"Media fuente de hierro","Baja fuente de hierro")) -> Alta fuente de hierro | BR61: =IF(BE61>2,"Muy alto",IF(BE61>1,"Alto",IF(BE61>0.5,"Moderado","Bajo"))) & " en sodio" -> Muy alto en sodio | BS61: =IF(BF61>2,"Altamente antiinflamatorio",IF(BF61>1,"Ligeramente antiinflamatorio",IF(BF61>0.5,"Neutro","Proinflamatorio"))) -> Altamente antiinflamatorio | BT61: =IF(BL61>0.4,"Muy alto en grasas",IF(BL61>0.3,"Alto en grasas",IF(BL61>0.2,"Moderado en grasas","Bajo en grasas"))) -> Bajo en grasas | BU61: =IF(BI61>1,"Alto riesgo de retención de líquidos",IF(BI61>0.5,"Riesgo moderado de retención","Equilibrio de líquidos ideal")) -> Riesgo moderado de retención | BV61: =IF(BM61>0.5,"Alta",IF(BM61>0.2,"Media","Baja")) & " fuente de magnesio" -> Baja fuente de magnesio | BW61: =IF(AV61>=0.5,"Alta fuente de Omega 3",IF(AV61>0.1,"Ligera fuente de Omega 3","Sin aporte de Omega 3")) -> Sin aporte de Omega 3 | BX61: =IF(AX61>0.5,"Alerta: Alto en grasas trans",IF(AX61>0,"Contiene grasas trans","Libre de grasas trans")) -> Libre de grasas trans | BY61: =IF(AY61>=50,"Alto",IF(AY61>=10,"Medio","Bajo")) & " poder antioxidante" -> Alto poder antioxidante | BZ61: =IF(AZ61>=1,"Probiótico activo","Sin probióticos") -> Sin probióticos | CA61: =IF(OR(AX61>0.5, O61>15, J61>0), "Altamente inflamatorio", IF(OR(AV61>=0.5, AY61>=50), "Antiinflamatorio", IF(OR(AX61>0, O61>5), "Moderadamente inflamatorio", "Poco inflamatorio"))) -> Antiinflamatorio | CB61: =IF(ISNUMBER(SEARCH("miel", D61)), "No irritante (Uso condicionado SII)", IF(OR(J61>0, ISNUMBER(SEARCH("cacao", D61)), ISNUMBER(SEARCH("chocolate puro", D61))), "Altamente irritante", IF(OR(AND(O61>15, BI61>1), ISNUMBER(SEARCH("chocolate", D61))), "Moderadamente irritante", "No irritante"))) -> No irritante | CC61: =IF(AV61=0,"Sin Omega 3 para evaluar",IFERROR(IF(((T61-AV61)/AV61)>4,"Exceso relativo de Omega 6","Balance de omegas favorable"),"Sin Omega 3 para evaluar")) -> Balance de omegas favorable
A62: =1+A61 -> 61 | B62: LEGUMBRES | C62: Legumbres secas | D62: Altramuz seco | F62: 1.2 | G62: 1 | H62: 394 | I62: 10.4 | J62: 0 | K62: 36.2 | L62: 40.4 | M62: 0 | N62: 0 | O62: 0 | P62: 0 | Q62: 9.7 | R62: 1.2 | S62: 3.9 | T62: 2.4 | U62: 0 | V62: 6.9 | W62: 0 | X62: 0 | Y62: 0 | Z62: 0 | AA62: 0 | AB62: 0.64 | AC62: 0.22 | AD62: 2.2 | AE62: 0.36 | AF62: 0 | AG62: 0 | AH62: 0 | AI62: 0 | AJ62: 4.8 | AK62: 176 | AL62: 440 | AM62: 4.4 | AN62: 0 | AO62: 4.8 | AP62: 198 | AQ62: 15 | AR62: 1013 | AS62: 0 | AT62: 0 | AU62: 8.2 | AV62: =IFERROR(VLOOKUP(IFERROR(VLOOKUP(D62,Mapa_Similitud!$A$2:$B$2000,2,FALSE()),D62),Hoja1!$A$2:$K$1000,2,FALSE()),IFERROR(VLOOKUP(IFERROR(VLOOKUP(D62,Mapa_Similitud!$A$2:$B$2000,2,FALSE()),D62),Omega3_Referencia!$A$2:$E$100,3,FALSE()),0)) -> 0.15 | AW62: =IFERROR(VLOOKUP(IFERROR(VLOOKUP(D62,Mapa_Similitud!$A$2:$B$2000,2,FALSE()),D62),Hoja1!$A$2:$K$1000,3,FALSE()),IFERROR(VLOOKUP(IFERROR(VLOOKUP(D62,Mapa_Similitud!$A$2:$B$2000,2,FALSE()),D62),Omega3_Referencia!$A$2:$E$100,4,FALSE()),"N/A")) -> ALA | AX62: =IFERROR(VLOOKUP(IFERROR(VLOOKUP(D62,Mapa_Similitud!$A$2:$B$2000,2,FALSE()),D62),Hoja1!$A$2:$K$1000,5,FALSE()),0) -> 0 | AY62: =IFERROR(VLOOKUP(IFERROR(VLOOKUP(D62,Mapa_Similitud!$A$2:$B$2000,2,FALSE()),D62),Hoja1!$A$2:$K$1000,7,FALSE()),0) -> 60 | AZ62: =IFERROR(VLOOKUP(IFERROR(VLOOKUP(D62,Mapa_Similitud!$A$2:$B$2000,2,FALSE()),D62),Hoja1!$A$2:$K$1000,9,FALSE()),0) -> 0 | BA62: =IFERROR(K62/H62,0) -> 0.091878173 | BB62: =IFERROR(P62/H62,0) -> 0 | BC62: =IFERROR(AK62/H62,0) -> 0.44670051 | BD62: =IFERROR(AM62/H62,0) -> 0.011167513 | BE62: =IFERROR(AQ62/H62,0) -> 0.038071066 | BF62: =IFERROR(T62/R62,0) -> 2 | BG62: =IFERROR(AK62/AL62,0) -> 0.4 | BH62: =IFERROR(R62/Q62,0) -> 0.12371134 | BI62: =IFERROR(AQ62/AR62,0) -> 0.014807502 | BJ62: =IFERROR(N62/L62,0) -> 0 | BK62: =IFERROR(P62/L62,0) -> 0 | BL62: =IFERROR((Q62*9)/H62,0) -> 0.2215736 | BM62: =IFERROR(AP62/H62,0) -> 0.50253807 | BN62: =IF(BA62>0.2,"Muy alta fuente de proteína",IF(BA62>0.15,"Alta fuente de proteína",IF(BA62>0.1,"Media fuente de proteína","Baja fuente de proteína"))) -> Baja fuente de proteína | BO62: =IF(BB62>0.03,"Alta",IF(BB62>0.015,"Media","Baja")) & " fuente de fibra" -> Baja fuente de fibra | BP62: =IF(BC62>1.5,"Alta fuente de calcio",IF(BC62>0.8,"Media fuente de calcio","Baja fuente de calcio")) -> Baja fuente de calcio | BQ62: =IF(BD62>0.015,"Alta fuente de hierro",IF(BD62>0.008,"Media fuente de hierro","Baja fuente de hierro")) -> Media fuente de hierro | BR62: =IF(BE62>2,"Muy alto",IF(BE62>1,"Alto",IF(BE62>0.5,"Moderado","Bajo"))) & " en sodio" -> Bajo en sodio | BS62: =IF(BF62>2,"Altamente antiinflamatorio",IF(BF62>1,"Ligeramente antiinflamatorio",IF(BF62>0.5,"Neutro","Proinflamatorio"))) -> Ligeramente antiinflamatorio | BT62: =IF(BL62>0.4,"Muy alto en grasas",IF(BL62>0.3,"Alto en grasas",IF(BL62>0.2,"Moderado en grasas","Bajo en grasas"))) -> Moderado en grasas | BU62: =IF(BI62>1,"Alto riesgo de retención de líquidos",IF(BI62>0.5,"Riesgo moderado de retención","Equilibrio de líquidos ideal")) -> Equilibrio de líquidos ideal | BV62: =IF(BM62>0.5,"Alta",IF(BM62>0.2,"Media","Baja")) & " fuente de magnesio" -> Alta fuente de magnesio | BW62: =IF(AV62>=0.5,"Alta fuente de Omega 3",IF(AV62>0.1,"Ligera fuente de Omega 3","Sin aporte de Omega 3")) -> Ligera fuente de Omega 3 | BX62: =IF(AX62>0.5,"Alerta: Alto en grasas trans",IF(AX62>0,"Contiene grasas trans","Libre de grasas trans")) -> Libre de grasas trans | BY62: =IF(AY62>=50,"Alto",IF(AY62>=10,"Medio","Bajo")) & " poder antioxidante" -> Alto poder antioxidante | BZ62: =IF(AZ62>=1,"Probiótico activo","Sin probióticos") -> Sin probióticos | CA62: =IF(OR(AX62>0.5, O62>15, J62>0), "Altamente inflamatorio", IF(OR(AV62>=0.5, AY62>=50), "Antiinflamatorio", IF(OR(AX62>0, O62>5), "Moderadamente inflamatorio", "Poco inflamatorio"))) -> Antiinflamatorio | CB62: =IF(ISNUMBER(SEARCH("miel", D62)), "No irritante (Uso condicionado SII)", IF(OR(J62>0, ISNUMBER(SEARCH("cacao", D62)), ISNUMBER(SEARCH("chocolate puro", D62))), "Altamente irritante", IF(OR(AND(O62>15, BI62>1), ISNUMBER(SEARCH("chocolate", D62))), "Moderadamente irritante", "No irritante"))) -> No irritante | CC62: =IF(AV62=0,"Sin Omega 3 para evaluar",IFERROR(IF(((T62-AV62)/AV62)>4,"Exceso relativo de Omega 6","Balance de omegas favorable"),"Sin Omega 3 para evaluar")) -> Exceso relativo de Omega 6
A63: =1+A62 -> 62 | B63: LEGUMBRES | C63: Legumbres secas | D63: Garbanzo | F63: 1 | G63: 1 | H63: 341 | I63: 11 | J63: 0 | K63: 20.8 | L63: 44.3 | M63: 41.9 | N63: 2.4 | O63: 0 | P63: 15.5 | Q63: 5.5 | R63: 0.36 | S63: 1.6 | T63: 2.5 | U63: 0 | V63: 33 | W63: 0 | X63: 198 | Y63: 0 | Z63: 0.82 | AA63: 264 | AB63: 0.45 | AC63: 0.14 | AD63: 4.6 | AE63: 0.55 | AF63: 185 | AG63: 0 | AH63: 1.3 | AI63: 0 | AJ63: 4.1 | AK63: 143 | AL63: 332 | AM63: 6.8 | AN63: 1.5 | AO63: 3.4 | AP63: 122 | AQ63: 25 | AR63: 875 | AS63: 2.7 | AT63: 0.84 | AU63: 8.2 | AV63: =IFERROR(VLOOKUP(IFERROR(VLOOKUP(D63,Mapa_Similitud!$A$2:$B$2000,2,FALSE()),D63),Hoja1!$A$2:$K$1000,2,FALSE()),IFERROR(VLOOKUP(IFERROR(VLOOKUP(D63,Mapa_Similitud!$A$2:$B$2000,2,FALSE()),D63),Omega3_Referencia!$A$2:$E$100,3,FALSE()),0)) -> 0.04 | AW63: =IFERROR(VLOOKUP(IFERROR(VLOOKUP(D63,Mapa_Similitud!$A$2:$B$2000,2,FALSE()),D63),Hoja1!$A$2:$K$1000,3,FALSE()),IFERROR(VLOOKUP(IFERROR(VLOOKUP(D63,Mapa_Similitud!$A$2:$B$2000,2,FALSE()),D63),Omega3_Referencia!$A$2:$E$100,4,FALSE()),"N/A")) -> ALA | AX63: =IFERROR(VLOOKUP(IFERROR(VLOOKUP(D63,Mapa_Similitud!$A$2:$B$2000,2,FALSE()),D63),Hoja1!$A$2:$K$1000,5,FALSE()),0) -> 0 | AY63: =IFERROR(VLOOKUP(IFERROR(VLOOKUP(D63,Mapa_Similitud!$A$2:$B$2000,2,FALSE()),D63),Hoja1!$A$2:$K$1000,7,FALSE()),0) -> 70 | AZ63: =IFERROR(VLOOKUP(IFERROR(VLOOKUP(D63,Mapa_Similitud!$A$2:$B$2000,2,FALSE()),D63),Hoja1!$A$2:$K$1000,9,FALSE()),0) -> 0 | BA63: =IFERROR(K63/H63,0) -> 0.060997067 | BB63: =IFERROR(P63/H63,0) -> 0.045454545 | BC63: =IFERROR(AK63/H63,0) -> 0.41935484 | BD63: =IFERROR(AM63/H63,0) -> 0.019941349 | BE63: =IFERROR(AQ63/H63,0) -> 0.073313783 | BF63: =IFERROR(T63/R63,0) -> 6.9444444 | BG63: =IFERROR(AK63/AL63,0) -> 0.43072289 | BH63: =IFERROR(R63/Q63,0) -> 0.065454545 | BI63: =IFERROR(AQ63/AR63,0) -> 0.028571429 | BJ63: =IFERROR(N63/L63,0) -> 0.054176072 | BK63: =IFERROR(P63/L63,0) -> 0.34988713 | BL63: =IFERROR((Q63*9)/H63,0) -> 0.14516129 | BM63: =IFERROR(AP63/H63,0) -> 0.35777126 | BN63: =IF(BA63>0.2,"Muy alta fuente de proteína",IF(BA63>0.15,"Alta fuente de proteína",IF(BA63>0.1,"Media fuente de proteína","Baja fuente de proteína"))) -> Baja fuente de proteína | BO63: =IF(BB63>0.03,"Alta",IF(BB63>0.015,"Media","Baja")) & " fuente de fibra" -> Alta fuente de fibra | BP63: =IF(BC63>1.5,"Alta fuente de calcio",IF(BC63>0.8,"Media fuente de calcio","Baja fuente de calcio")) -> Baja fuente de calcio | BQ63: =IF(BD63>0.015,"Alta fuente de hierro",IF(BD63>0.008,"Media fuente de hierro","Baja fuente de hierro")) -> Alta fuente de hierro | BR63: =IF(BE63>2,"Muy alto",IF(BE63>1,"Alto",IF(BE63>0.5,"Moderado","Bajo"))) & " en sodio" -> Bajo en sodio | BS63: =IF(BF63>2,"Altamente antiinflamatorio",IF(BF63>1,"Ligeramente antiinflamatorio",IF(BF63>0.5,"Neutro","Proinflamatorio"))) -> Altamente antiinflamatorio | BT63: =IF(BL63>0.4,"Muy alto en grasas",IF(BL63>0.3,"Alto en grasas",IF(BL63>0.2,"Moderado en grasas","Bajo en grasas"))) -> Bajo en grasas | BU63: =IF(BI63>1,"Alto riesgo de retención de líquidos",IF(BI63>0.5,"Riesgo moderado de retención","Equilibrio de líquidos ideal")) -> Equilibrio de líquidos ideal | BV63: =IF(BM63>0.5,"Alta",IF(BM63>0.2,"Media","Baja")) & " fuente de magnesio" -> Media fuente de magnesio | BW63: =IF(AV63>=0.5,"Alta fuente de Omega 3",IF(AV63>0.1,"Ligera fuente de Omega 3","Sin aporte de Omega 3")) -> Sin aporte de Omega 3 | BX63: =IF(AX63>0.5,"Alerta: Alto en grasas trans",IF(AX63>0,"Contiene grasas trans","Libre de grasas trans")) -> Libre de grasas trans | BY63: =IF(AY63>=50,"Alto",IF(AY63>=10,"Medio","Bajo")) & " poder antioxidante" -> Alto poder antioxidante | BZ63: =IF(AZ63>=1,"Probiótico activo","Sin probióticos") -> Sin probióticos | CA63: =IF(OR(AX63>0.5, O63>15, J63>0), "Altamente inflamatorio", IF(OR(AV63>=0.5, AY63>=50), "Antiinflamatorio", IF(OR(AX63>0, O63>5), "Moderadamente inflamatorio", "Poco inflamatorio"))) -> Antiinflamatorio | CB63: =IF(ISNUMBER(SEARCH("miel", D63)), "No irritante (Uso condicionado SII)", IF(OR(J63>0, ISNUMBER(SEARCH("cacao", D63)), ISNUMBER(SEARCH("chocolate puro", D63))), "Altamente irritante", IF(OR(AND(O63>15, BI63>1), ISNUMBER(SEARCH("chocolate", D63))), "Moderadamente irritante", "No irritante"))) -> No irritante | CC63: =IF(AV63=0,"Sin Omega 3 para evaluar",IFERROR(IF(((T63-AV63)/AV63)>4,"Exceso relativo de Omega 6","Balance de omegas favorable"),"Sin Omega 3 para evaluar")) -> Exceso relativo de Omega 6
A64: =1+A63 -> 63 | B64: LEGUMBRES | C64: Legumbres secas | D64: Haba seca | F64: 0.8 | G64: 1 | H64: 307 | I64: 10.4 | J64: 0 | K64: 26.1 | L64: 33.3 | M64: 30.8 | N64: 2.5 | O64: 0 | P64: 25 | Q64: 2.1 | R64: 0.3 | S64: 0.3 | T64: 1.1 | U64: 0 | V64: 5.3 | W64: 0 | X64: 32 | Y64: 0 | Z64: 0.09 | AA64: 19 | AB64: 0.5 | AC64: 0.26 | AD64: 6.9 | AE64: 0.37 | AF64: 423 | AG64: 0 | AH64: 0.98 | AI64: 0 | AJ64: 4 | AK64: 100 | AL64: 590 | AM64: 5.5 | AN64: 2 | AO64: 3.1 | AP64: 190 | AQ64: 11 | AR64: 1090 | AS64: 1.6 | AT64: 0.82 | AU64: 8.2 | AV64: =IFERROR(VLOOKUP(IFERROR(VLOOKUP(D64,Mapa_Similitud!$A$2:$B$2000,2,FALSE()),D64),Hoja1!$A$2:$K$1000,2,FALSE()),IFERROR(VLOOKUP(IFERROR(VLOOKUP(D64,Mapa_Similitud!$A$2:$B$2000,2,FALSE()),D64),Omega3_Referencia!$A$2:$E$100,3,FALSE()),0)) -> 0.03 | AW64: =IFERROR(VLOOKUP(IFERROR(VLOOKUP(D64,Mapa_Similitud!$A$2:$B$2000,2,FALSE()),D64),Hoja1!$A$2:$K$1000,3,FALSE()),IFERROR(VLOOKUP(IFERROR(VLOOKUP(D64,Mapa_Similitud!$A$2:$B$2000,2,FALSE()),D64),Omega3_Referencia!$A$2:$E$100,4,FALSE()),"N/A")) -> ALA | AX64: =IFERROR(VLOOKUP(IFERROR(VLOOKUP(D64,Mapa_Similitud!$A$2:$B$2000,2,FALSE()),D64),Hoja1!$A$2:$K$1000,5,FALSE()),0) -> 0 | AY64: =IFERROR(VLOOKUP(IFERROR(VLOOKUP(D64,Mapa_Similitud!$A$2:$B$2000,2,FALSE()),D64),Hoja1!$A$2:$K$1000,7,FALSE()),0) -> 50 | AZ64: =IFERROR(VLOOKUP(IFERROR(VLOOKUP(D64,Mapa_Similitud!$A$2:$B$2000,2,FALSE()),D64),Hoja1!$A$2:$K$1000,9,FALSE()),0) -> 0 | BA64: =IFERROR(K64/H64,0) -> 0.085016287 | BB64: =IFERROR(P64/H64,0) -> 0.081433225 | BC64: =IFERROR(AK64/H64,0) -> 0.3257329 | BD64: =IFERROR(AM64/H64,0) -> 0.017915309 | BE64: =IFERROR(AQ64/H64,0) -> 0.035830619 | BF64: =IFERROR(T64/R64,0) -> 3.6666667 | BG64: =IFERROR(AK64/AL64,0) -> 0.16949153 | BH64: =IFERROR(R64/Q64,0) -> 0.14285714 | BI64: =IFERROR(AQ64/AR64,0) -> 0.010091743 | BJ64: =IFERROR(N64/L64,0) -> 0.075075075 | BK64: =IFERROR(P64/L64,0) -> 0.75075075 | BL64: =IFERROR((Q64*9)/H64,0) -> 0.061563518 | BM64: =IFERROR(AP64/H64,0) -> 0.61889251 | BN64: =IF(BA64>0.2,"Muy alta fuente de proteína",IF(BA64>0.15,"Alta fuente de proteína",IF(BA64>0.1,"Media fuente de proteína","Baja fuente de proteína"))) -> Baja fuente de proteína | BO64: =IF(BB64>0.03,"Alta",IF(BB64>0.015,"Media","Baja")) & " fuente de fibra" -> Alta fuente de fibra | BP64: =IF(BC64>1.5,"Alta fuente de calcio",IF(BC64>0.8,"Media fuente de calcio","Baja fuente de calcio")) -> Baja fuente de calcio | BQ64: =IF(BD64>0.015,"Alta fuente de hierro",IF(BD64>0.008,"Media fuente de hierro","Baja fuente de hierro")) -> Alta fuente de hierro | BR64: =IF(BE64>2,"Muy alto",IF(BE64>1,"Alto",IF(BE64>0.5,"Moderado","Bajo"))) & " en sodio" -> Bajo en sodio | BS64: =IF(BF64>2,"Altamente antiinflamatorio",IF(BF64>1,"Ligeramente antiinflamatorio",IF(BF64>0.5,"Neutro","Proinflamatorio"))) -> Altamente antiinflamatorio | BT64: =IF(BL64>0.4,"Muy alto en grasas",IF(BL64>0.3,"Alto en grasas",IF(BL64>0.2,"Moderado en grasas","Bajo en grasas"))) -> Bajo en grasas | BU64: =IF(BI64>1,"Alto riesgo de retención de líquidos",IF(BI64>0.5,"Riesgo moderado de retención","Equilibrio de líquidos ideal")) -> Equilibrio de líquidos ideal | BV64: =IF(BM64>0.5,"Alta",IF(BM64>0.2,"Media","Baja")) & " fuente de magnesio" -> Alta fuente de magnesio | BW64: =IF(AV64>=0.5,"Alta fuente de Omega 3",IF(AV64>0.1,"Ligera fuente de Omega 3","Sin aporte de Omega 3")) -> Sin aporte de Omega 3 | BX64: =IF(AX64>0.5,"Alerta: Alto en grasas trans",IF(AX64>0,"Contiene grasas trans","Libre de grasas trans")) -> Libre de grasas trans | BY64: =IF(AY64>=50,"Alto",IF(AY64>=10,"Medio","Bajo")) & " poder antioxidante" -> Alto poder antioxidante | BZ64: =IF(AZ64>=1,"Probiótico activo","Sin probióticos") -> Sin probióticos | CA64: =IF(OR(AX64>0.5, O64>15, J64>0), "Altamente inflamatorio", IF(OR(AV64>=0.5, AY64>=50), "Antiinflamatorio", IF(OR(AX64>0, O64>5), "Moderadamente inflamatorio", "Poco inflamatorio"))) -> Antiinflamatorio | CB64: =IF(ISNUMBER(SEARCH("miel", D64)), "No irritante (Uso condicionado SII)", IF(OR(J64>0, ISNUMBER(SEARCH("cacao", D64)), ISNUMBER(SEARCH("chocolate puro", D64))), "Altamente irritante", IF(OR(AND(O64>15, BI64>1), ISNUMBER(SEARCH("chocolate", D64))), "Moderadamente irritante", "No irritante"))) -> No irritante | CC64: =IF(AV64=0,"Sin Omega 3 para evaluar",IFERROR(IF(((T64-AV64)/AV64)>4,"Exceso relativo de Omega 6","Balance de omegas favorable"),"Sin Omega 3 para evaluar")) -> Exceso relativo de Omega 6
A65: =1+A64 -> 64 | B65: LEGUMBRES | C65: Legumbres secas | D65: Harina de algarrobo | F65: 3.5 | G65: 1 | H65: 300 | I65: 3.6 | J65: 0 | K65: 4.6 | L65: 49.1 | M65: 0 | N65: 49.1 | O65: 0 | P65: 39.8 | Q65: 0.65 | R65: 0.09 | S65: 0.02 | T65: 0.22 | U65: 0 | V65: 1.3 | W65: 0 | X65: 8 | Y65: 0 | Z65: 0.63 | AA65: 0 | AB65: 0.053 | AC65: 0.46 | AD65: 1.9 | AE65: 0.37 | AF65: 21 | AG65: 0 | AH65: 0 | AI65: 0 | AJ65: 0.2 | AK65: 348 | AL65: 79 | AM65: 2.9 | AN65: 0 | AO65: 0.092 | AP65: 54 | AQ65: 35 | AR65: 827 | AS65: 0 | AT65: 0 | AU65: 5.3 | AV65: =IFERROR(VLOOKUP(IFERROR(VLOOKUP(D65,Mapa_Similitud!$A$2:$B$2000,2,FALSE()),D65),Hoja1!$A$2:$K$1000,2,FALSE()),IFERROR(VLOOKUP(IFERROR(VLOOKUP(D65,Mapa_Similitud!$A$2:$B$2000,2,FALSE()),D65),Omega3_Referencia!$A$2:$E$100,3,FALSE()),0)) -> 0 | AW65: =IFERROR(VLOOKUP(IFERROR(VLOOKUP(D65,Mapa_Similitud!$A$2:$B$2000,2,FALSE()),D65),Hoja1!$A$2:$K$1000,3,FALSE()),IFERROR(VLOOKUP(IFERROR(VLOOKUP(D65,Mapa_Similitud!$A$2:$B$2000,2,FALSE()),D65),Omega3_Referencia!$A$2:$E$100,4,FALSE()),"N/A")) -> N/A | AX65: =IFERROR(VLOOKUP(IFERROR(VLOOKUP(D65,Mapa_Similitud!$A$2:$B$2000,2,FALSE()),D65),Hoja1!$A$2:$K$1000,5,FALSE()),0) -> 0 | AY65: =IFERROR(VLOOKUP(IFERROR(VLOOKUP(D65,Mapa_Similitud!$A$2:$B$2000,2,FALSE()),D65),Hoja1!$A$2:$K$1000,7,FALSE()),0) -> 400 | AZ65: =IFERROR(VLOOKUP(IFERROR(VLOOKUP(D65,Mapa_Similitud!$A$2:$B$2000,2,FALSE()),D65),Hoja1!$A$2:$K$1000,9,FALSE()),0) -> 0 | BA65: =IFERROR(K65/H65,0) -> 0.015333333 | BB65: =IFERROR(P65/H65,0) -> 0.13266667 | BC65: =IFERROR(AK65/H65,0) -> 1.16 | BD65: =IFERROR(AM65/H65,0) -> 0.0096666667 | BE65: =IFERROR(AQ65/H65,0) -> 0.11666667 | BF65: =IFERROR(T65/R65,0) -> 2.4444444 | BG65: =IFERROR(AK65/AL65,0) -> 4.4050633 | BH65: =IFERROR(R65/Q65,0) -> 0.13846154 | BI65: =IFERROR(AQ65/AR65,0) -> 0.042321644 | BJ65: =IFERROR(N65/L65,0) -> 1 | BK65: =IFERROR(P65/L65,0) -> 0.81059063 | BL65: =IFERROR((Q65*9)/H65,0) -> 0.0195 | BM65: =IFERROR(AP65/H65,0) -> 0.18 | BN65: =IF(BA65>0.2,"Muy alta fuente de proteína",IF(BA65>0.15,"Alta fuente de proteína",IF(BA65>0.1,"Media fuente de proteína","Baja fuente de proteína"))) -> Baja fuente de proteína | BO65: =IF(BB65>0.03,"Alta",IF(BB65>0.015,"Media","Baja")) & " fuente de fibra" -> Alta fuente de fibra | BP65: =IF(BC65>1.5,"Alta fuente de calcio",IF(BC65>0.8,"Media fuente de calcio","Baja fuente de calcio")) -> Media fuente de calcio | BQ65: =IF(BD65>0.015,"Alta fuente de hierro",IF(BD65>0.008,"Media fuente de hierro","Baja fuente de hierro")) -> Media fuente de hierro | BR65: =IF(BE65>2,"Muy alto",IF(BE65>1,"Alto",IF(BE65>0.5,"Moderado","Bajo"))) & " en sodio" -> Bajo en sodio | BS65: =IF(BF65>2,"Altamente antiinflamatorio",IF(BF65>1,"Ligeramente antiinflamatorio",IF(BF65>0.5,"Neutro","Proinflamatorio"))) -> Altamente antiinflamatorio | BT65: =IF(BL65>0.4,"Muy alto en grasas",IF(BL65>0.3,"Alto en grasas",IF(BL65>0.2,"Moderado en grasas","Bajo en grasas"))) -> Bajo en grasas | BU65: =IF(BI65>1,"Alto riesgo de retención de líquidos",IF(BI65>0.5,"Riesgo moderado de retención","Equilibrio de líquidos ideal")) -> Equilibrio de líquidos ideal | BV65: =IF(BM65>0.5,"Alta",IF(BM65>0.2,"Media","Baja")) & " fuente de magnesio" -> Baja fuente de magnesio | BW65: =IF(AV65>=0.5,"Alta fuente de Omega 3",IF(AV65>0.1,"Ligera fuente de Omega 3","Sin aporte de Omega 3")) -> Sin aporte de Omega 3 | BX65: =IF(AX65>0.5,"Alerta: Alto en grasas trans",IF(AX65>0,"Contiene grasas trans","Libre de grasas trans")) -> Libre de grasas trans | BY65: =IF(AY65>=50,"Alto",IF(AY65>=10,"Medio","Bajo")) & " poder antioxidante" -> Alto poder antioxidante | BZ65: =IF(AZ65>=1,"Probiótico activo","Sin probióticos") -> Sin probióticos | CA65: =IF(OR(AX65>0.5, O65>15, J65>0), "Altamente inflamatorio", IF(OR(AV65>=0.5, AY65>=50), "Antiinflamatorio", IF(OR(AX65>0, O65>5), "Moderadamente inflamatorio", "Poco inflamatorio"))) -> Antiinflamatorio | CB65: =IF(ISNUMBER(SEARCH("miel", D65)), "No irritante (Uso condicionado SII)", IF(OR(J65>0, ISNUMBER(SEARCH("cacao", D65)), ISNUMBER(SEARCH("chocolate puro", D65))), "Altamente irritante", IF(OR(AND(O65>15, BI65>1), ISNUMBER(SEARCH("chocolate", D65))), "Moderadamente irritante", "No irritante"))) -> No irritante | CC65: =IF(AV65=0,"Sin Omega 3 para evaluar",IFERROR(IF(((T65-AV65)/AV65)>4,"Exceso relativo de Omega 6","Balance de omegas favorable"),"Sin Omega 3 para evaluar")) -> Sin Omega 3 para evaluar
A66: =1+A65 -> 65 | B66: LEGUMBRES | C66: Legumbres secas | D66: Judía blanca | F66: 1.1 | G66: 1 | H66: 284 | I66: 15.5 | J66: 0 | K66: 21.1 | L66: 34.7 | M66: 32.7 | N66: 2 | O66: 0 | P66: 23.2 | Q66: 1.6 | R66: 0.43 | S66: 0.14 | T66: 0.69 | U66: 0 | V66: 67 | W66: 0 | X66: 400 | Y66: 0 | Z66: 0.21 | AA66: 19 | AB66: 0.5 | AC66: 0.12 | AD66: 5.3 | AE66: 0.41 | AF66: 388 | AG66: 0 | AH66: 0.87 | AI66: 0 | AJ66: 2.5 | AK66: 113 | AL66: 426 | AM66: 6.2 | AN66: 1.8 | AO66: 2.6 | AP66: 140 | AQ66: 15 | AR66: 1337 | AS66: 1.6 | AT66: 0.98 | AU66: 12.8 | AV66: =IFERROR(VLOOKUP(IFERROR(VLOOKUP(D66,Mapa_Similitud!$A$2:$B$2000,2,FALSE()),D66),Hoja1!$A$2:$K$1000,2,FALSE()),IFERROR(VLOOKUP(IFERROR(VLOOKUP(D66,Mapa_Similitud!$A$2:$B$2000,2,FALSE()),D66),Omega3_Referencia!$A$2:$E$100,3,FALSE()),0)) -> 0.18 | AW66: =IFERROR(VLOOKUP(IFERROR(VLOOKUP(D66,Mapa_Similitud!$A$2:$B$2000,2,FALSE()),D66),Hoja1!$A$2:$K$1000,3,FALSE()),IFERROR(VLOOKUP(IFERROR(VLOOKUP(D66,Mapa_Similitud!$A$2:$B$2000,2,FALSE()),D66),Omega3_Referencia!$A$2:$E$100,4,FALSE()),"N/A")) -> ALA | AX66: =IFERROR(VLOOKUP(IFERROR(VLOOKUP(D66,Mapa_Similitud!$A$2:$B$2000,2,FALSE()),D66),Hoja1!$A$2:$K$1000,5,FALSE()),0) -> 0 | AY66: =IFERROR(VLOOKUP(IFERROR(VLOOKUP(D66,Mapa_Similitud!$A$2:$B$2000,2,FALSE()),D66),Hoja1!$A$2:$K$1000,7,FALSE()),0) -> 105.5 | AZ66: =IFERROR(VLOOKUP(IFERROR(VLOOKUP(D66,Mapa_Similitud!$A$2:$B$2000,2,FALSE()),D66),Hoja1!$A$2:$K$1000,9,FALSE()),0) -> 0 | BA66: =IFERROR(K66/H66,0) -> 0.074295775 | BB66: =IFERROR(P66/H66,0) -> 0.081690141 | BC66: =IFERROR(AK66/H66,0) -> 0.39788732 | BD66: =IFERROR(AM66/H66,0) -> 0.021830986 | BE66: =IFERROR(AQ66/H66,0) -> 0.052816901 | BF66: =IFERROR(T66/R66,0) -> 1.6046512 | BG66: =IFERROR(AK66/AL66,0) -> 0.26525822 | BH66: =IFERROR(R66/Q66,0) -> 0.26875 | BI66: =IFERROR(AQ66/AR66,0) -> 0.011219147 | BJ66: =IFERROR(N66/L66,0) -> 0.057636888 | BK66: =IFERROR(P66/L66,0) -> 0.6685879 | BL66: =IFERROR((Q66*9)/H66,0) -> 0.050704225 | BM66: =IFERROR(AP66/H66,0) -> 0.49295775 | BN66: =IF(BA66>0.2,"Muy alta fuente de proteína",IF(BA66>0.15,"Alta fuente de proteína",IF(BA66>0.1,"Media fuente de proteína","Baja fuente de proteína"))) -> Baja fuente de proteína | BO66: =IF(BB66>0.03,"Alta",IF(BB66>0.015,"Media","Baja")) & " fuente de fibra" -> Alta fuente de fibra | BP66: =IF(BC66>1.5,"Alta fuente de calcio",IF(BC66>0.8,"Media fuente de calcio","Baja fuente de calcio")) -> Baja fuente de calcio | BQ66: =IF(BD66>0.015,"Alta fuente de hierro",IF(BD66>0.008,"Media fuente de hierro","Baja fuente de hierro")) -> Alta fuente de hierro | BR66: =IF(BE66>2,"Muy alto",IF(BE66>1,"Alto",IF(BE66>0.5,"Moderado","Bajo"))) & " en sodio" -> Bajo en sodio | BS66: =IF(BF66>2,"Altamente antiinflamatorio",IF(BF66>1,"Ligeramente antiinflamatorio",IF(BF66>0.5,"Neutro","Proinflamatorio"))) -> Ligeramente antiinflamatorio | BT66: =IF(BL66>0.4,"Muy alto en grasas",IF(BL66>0.3,"Alto en grasas",IF(BL66>0.2,"Moderado en grasas","Bajo en grasas"))) -> Bajo en grasas | BU66: =IF(BI66>1,"Alto riesgo de retención de líquidos",IF(BI66>0.5,"Riesgo moderado de retención","Equilibrio de líquidos ideal")) -> Equilibrio de líquidos ideal | BV66: =IF(BM66>0.5,"Alta",IF(BM66>0.2,"Media","Baja")) & " fuente de magnesio" -> Media fuente de magnesio | BW66: =IF(AV66>=0.5,"Alta fuente de Omega 3",IF(AV66>0.1,"Ligera fuente de Omega 3","Sin aporte de Omega 3")) -> Ligera fuente de Omega 3 | BX66: =IF(AX66>0.5,"Alerta: Alto en grasas trans",IF(AX66>0,"Contiene grasas trans","Libre de grasas trans")) -> Libre de grasas trans | BY66: =IF(AY66>=50,"Alto",IF(AY66>=10,"Medio","Bajo")) & " poder antioxidante" -> Alto poder antioxidante | BZ66: =IF(AZ66>=1,"Probiótico activo","Sin probióticos") -> Sin probióticos | CA66: =IF(OR(AX66>0.5, O66>15, J66>0), "Altamente inflamatorio", IF(OR(AV66>=0.5, AY66>=50), "Antiinflamatorio", IF(OR(AX66>0, O66>5), "Moderadamente inflamatorio", "Poco inflamatorio"))) -> Antiinflamatorio | CB66: =IF(ISNUMBER(SEARCH("miel", D66)), "No irritante (Uso condicionado SII)", IF(OR(J66>0, ISNUMBER(SEARCH("cacao", D66)), ISNUMBER(SEARCH("chocolate puro", D66))), "Altamente irritante", IF(OR(AND(O66>15, BI66>1), ISNUMBER(SEARCH("chocolate", D66))), "Moderadamente irritante", "No irritante"))) -> No irritante | CC66: =IF(AV66=0,"Sin Omega 3 para evaluar",IFERROR(IF(((T66-AV66)/AV66)>4,"Exceso relativo de Omega 6","Balance de omegas favorable"),"Sin Omega 3 para evaluar")) -> Balance de omegas favorable
A67: =1+A66 -> 66 | B67: LEGUMBRES | C67: Legumbres secas | D67: Judía pinta | F67: 1 | G67: 1 | H67: 292 | I67: 11.8 | J67: 0 | K67: 23.6 | L67: 35.1 | M67: 32.9 | N67: 2.2 | O67: 0 | P67: 24.9 | Q67: 0.83 | R67: 0.12 | S67: 0.064 | T67: 0.46 | U67: 0 | V67: 67 | W67: 0 | X67: 400 | Y67: 0 | Z67: 0.22 | AA67: 19 | AB67: 0.53 | AC67: 0.22 | AD67: 6.8 | AE67: 0.4 | AF67: 394 | AG67: 0 | AH67: 0.78 | AI67: 0 | AJ67: 4.5 | AK67: 143 | AL67: 407 | AM67: 8.2 | AN67: 2 | AO67: 2.8 | AP67: 140 | AQ67: 24 | AR67: 1406 | AS67: 1 | AT67: 0.96 | AU67: 3.2 | AV67: =IFERROR(VLOOKUP(IFERROR(VLOOKUP(D67,Mapa_Similitud!$A$2:$B$2000,2,FALSE()),D67),Hoja1!$A$2:$K$1000,2,FALSE()),IFERROR(VLOOKUP(IFERROR(VLOOKUP(D67,Mapa_Similitud!$A$2:$B$2000,2,FALSE()),D67),Omega3_Referencia!$A$2:$E$100,3,FALSE()),0)) -> 0.15 | AW67: =IFERROR(VLOOKUP(IFERROR(VLOOKUP(D67,Mapa_Similitud!$A$2:$B$2000,2,FALSE()),D67),Hoja1!$A$2:$K$1000,3,FALSE()),IFERROR(VLOOKUP(IFERROR(VLOOKUP(D67,Mapa_Similitud!$A$2:$B$2000,2,FALSE()),D67),Omega3_Referencia!$A$2:$E$100,4,FALSE()),"N/A")) -> ALA | AX67: =IFERROR(VLOOKUP(IFERROR(VLOOKUP(D67,Mapa_Similitud!$A$2:$B$2000,2,FALSE()),D67),Hoja1!$A$2:$K$1000,5,FALSE()),0) -> 0 | AY67: =IFERROR(VLOOKUP(IFERROR(VLOOKUP(D67,Mapa_Similitud!$A$2:$B$2000,2,FALSE()),D67),Hoja1!$A$2:$K$1000,7,FALSE()),0) -> 325.3 | AZ67: =IFERROR(VLOOKUP(IFERROR(VLOOKUP(D67,Mapa_Similitud!$A$2:$B$2000,2,FALSE()),D67),Hoja1!$A$2:$K$1000,9,FALSE()),0) -> 0 | BA67: =IFERROR(K67/H67,0) -> 0.080821918 | BB67: =IFERROR(P67/H67,0) -> 0.085273973 | BC67: =IFERROR(AK67/H67,0) -> 0.48972603 | BD67: =IFERROR(AM67/H67,0) -> 0.028082192 | BE67: =IFERROR(AQ67/H67,0) -> 0.082191781 | BF67: =IFERROR(T67/R67,0) -> 3.8333333 | BG67: =IFERROR(AK67/AL67,0) -> 0.35135135 | BH67: =IFERROR(R67/Q67,0) -> 0.14457831 | BI67: =IFERROR(AQ67/AR67,0) -> 0.017069701 | BJ67: =IFERROR(N67/L67,0) -> 0.062678063 | BK67: =IFERROR(P67/L67,0) -> 0.70940171 | BL67: =IFERROR((Q67*9)/H67,0) -> 0.025582192 | BM67: =IFERROR(AP67/H67,0) -> 0.47945205 | BN67: =IF(BA67>0.2,"Muy alta fuente de proteína",IF(BA67>0.15,"Alta fuente de proteína",IF(BA67>0.1,"Media fuente de proteína","Baja fuente de proteína"))) -> Baja fuente de proteína | BO67: =IF(BB67>0.03,"Alta",IF(BB67>0.015,"Media","Baja")) & " fuente de fibra" -> Alta fuente de fibra | BP67: =IF(BC67>1.5,"Alta fuente de calcio",IF(BC67>0.8,"Media fuente de calcio","Baja fuente de calcio")) -> Baja fuente de calcio | BQ67: =IF(BD67>0.015,"Alta fuente de hierro",IF(BD67>0.008,"Media fuente de hierro","Baja fuente de hierro")) -> Alta fuente de hierro | BR67: =IF(BE67>2,"Muy alto",IF(BE67>1,"Alto",IF(BE67>0.5,"Moderado","Bajo"))) & " en sodio" -> Bajo en sodio | BS67: =IF(BF67>2,"Altamente antiinflamatorio",IF(BF67>1,"Ligeramente antiinflamatorio",IF(BF67>0.5,"Neutro","Proinflamatorio"))) -> Altamente antiinflamatorio | BT67: =IF(BL67>0.4,"Muy alto en grasas",IF(BL67>0.3,"Alto en grasas",IF(BL67>0.2,"Moderado en grasas","Bajo en grasas"))) -> Bajo en grasas | BU67: =IF(BI67>1,"Alto riesgo de retención de líquidos",IF(BI67>0.5,"Riesgo moderado de retención","Equilibrio de líquidos ideal")) -> Equilibrio de líquidos ideal | BV67: =IF(BM67>0.5,"Alta",IF(BM67>0.2,"Media","Baja")) & " fuente de magnesio" -> Media fuente de magnesio | BW67: =IF(AV67>=0.5,"Alta fuente de Omega 3",IF(AV67>0.1,"Ligera fuente de Omega 3","Sin aporte de Omega 3")) -> Ligera fuente de Omega 3 | BX67: =IF(AX67>0.5,"Alerta: Alto en grasas trans",IF(AX67>0,"Contiene grasas trans","Libre de grasas trans")) -> Libre de grasas trans | BY67: =IF(AY67>=50,"Alto",IF(AY67>=10,"Medio","Bajo")) & " poder antioxidante" -> Alto poder antioxidante | BZ67: =IF(AZ67>=1,"Probiótico activo","Sin probióticos") -> Sin probióticos | CA67: =IF(OR(AX67>0.5, O67>15, J67>0), "Altamente inflamatorio", IF(OR(AV67>=0.5, AY67>=50), "Antiinflamatorio", IF(OR(AX67>0, O67>5), "Moderadamente inflamatorio", "Poco inflamatorio"))) -> Antiinflamatorio | CB67: =IF(ISNUMBER(SEARCH("miel", D67)), "No irritante (Uso condicionado SII)", IF(OR(J67>0, ISNUMBER(SEARCH("cacao", D67)), ISNUMBER(SEARCH("chocolate puro", D67))), "Altamente irritante", IF(OR(AND(O67>15, BI67>1), ISNUMBER(SEARCH("chocolate", D67))), "Moderadamente irritante", "No irritante"))) -> No irritante | CC67: =IF(AV67=0,"Sin Omega 3 para evaluar",IFERROR(IF(((T67-AV67)/AV67)>4,"Exceso relativo de Omega 6","Balance de omegas favorable"),"Sin Omega 3 para evaluar")) -> Balance de omegas favorable
... A72: =1+A71 -> 71 | B72: VERDURAS Y HORTALIZAS | C72: Tubérculos y raíces | D72: Boniato | F72: 1 | G72: 0.84 | H72: 114 | I72: 70.5 | J72: 0 | K72: 1.6 | L72: 24.1 | M72: 19.5 | N72: 4.6 | O72: 0 | P72: 3.1 | Q72: 0.6 | R72: 0.23 | S72: 0.04 | T72: 0.2 | U72: 0 | V72: 1581 | W72: 0 | X72: 9488 | Y72: 0 | Z72: 4.6 | AA72: 1.8 | AB72: 0.17 | AC72: 0.06 | AD72: 0.97 | AE72: 0.27 | AF72: 17 | AG72: 0 | AH72: 0.59 | AI72: 4.3 | AJ72: 25 | AK72: 22 | AL72: 50 | AM72: 0.66 | AN72: 2.4 | AO72: 0.39 | AP72: 18 | AQ72: 19 | AR72: 300 | AS72: 0.24 | AT72: 0.13 | AU72: 1 | AV72: =IFERROR(VLOOKUP(IFERROR(VLOOKUP(D72,Mapa_Similitud!$A$2:$B$2000,2,FALSE()),D72),Hoja1!$A$2:$K$1000,2,FALSE()),IFERROR(VLOOKUP(IFERROR(VLOOKUP(D72,Mapa_Similitud!$A$2:$B$2000,2,FALSE()),D72),Omega3_Referencia!$A$2:$E$100,3,FALSE()),0)) -> 0.01 | AW72: =IFERROR(VLOOKUP(IFERROR(VLOOKUP(D72,Mapa_Similitud!$A$2:$B$2000,2,FALSE()),D72),Hoja1!$A$2:$K$1000,3,FALSE()),IFERROR(VLOOKUP(IFERROR(VLOOKUP(D72,Mapa_Similitud!$A$2:$B$2000,2,FALSE()),D72),Omega3_Referencia!$A$2:$E$100,4,FALSE()),"N/A")) -> ALA | AX72: =IFERROR(VLOOKUP(IFERROR(VLOOKUP(D72,Mapa_Similitud!$A$2:$B$2000,2,FALSE()),D72),Hoja1!$A$2:$K$1000,5,FALSE()),0) -> 0 | AY72: =IFERROR(VLOOKUP(IFERROR(VLOOKUP(D72,Mapa_Similitud!$A$2:$B$2000,2,FALSE()),D72),Hoja1!$A$2:$K$1000,7,FALSE()),0) -> 440 | AZ72: =IFERROR(VLOOKUP(IFERROR(VLOOKUP(D72,Mapa_Similitud!$A$2:$B$2000,2,FALSE()),D72),Hoja1!$A$2:$K$1000,9,FALSE()),0) -> 0 | BA72: =IFERROR(K72/H72,0) -> 0.014035088 | BB72: =IFERROR(P72/H72,0) -> 0.027192982 | BC72: =IFERROR(AK72/H72,0) -> 0.19298246 | BD72: =IFERROR(AM72/H72,0) -> 0.0057894737 | BE72: =IFERROR(AQ72/H72,0) -> 0.16666667 | BF72: =IFERROR(T72/R72,0) -> 0.86956522 | BG72: =IFERROR(AK72/AL72,0) -> 0.44 | BH72: =IFERROR(R72/Q72,0) -> 0.38333333 | BI72: =IFERROR(AQ72/AR72,0) -> 0.063333333 | BJ72: =IFERROR(N72/L72,0) -> 0.19087137 | BK72: =IFERROR(P72/L72,0) -> 0.12863071 | BL72: =IFERROR((Q72*9)/H72,0) -> 0.047368421 | BM72: =IFERROR(AP72/H72,0) -> 0.15789474 | BN72: =IF(BA72>0.2,"Muy alta fuente de proteína",IF(BA72>0.15,"Alta fuente de proteína",IF(BA72>0.1,"Media fuente de proteína","Baja fuente de proteína"))) -> Baja fuente de proteína | BO72: =IF(BB72>0.03,"Alta",IF(BB72>0.015,"Media","Baja")) & " fuente de fibra" -> Media fuente de fibra | BP72: =IF(BC72>1.5,"Alta fuente de calcio",IF(BC72>0.8,"Media fuente de calcio","Baja fuente de calcio")) -> Baja fuente de calcio | BQ72: =IF(BD72>0.015,"Alta fuente de hierro",IF(BD72>0.008,"Media fuente de hierro","Baja fuente de hierro")) -> Baja fuente de hierro | BR72: =IF(BE72>2,"Muy alto",IF(BE72>1,"Alto",IF(BE72>0.5,"Moderado","Bajo"))) & " en sodio" -> Bajo en sodio | BS72: =IF(BF72>2,"Altamente antiinflamatorio",IF(BF72>1,"Ligeramente antiinflamatorio",IF(BF72>0.5,"Neutro","Proinflamatorio"))) -> Neutro | BT72: =IF(BL72>0.4,"Muy alto en grasas",IF(BL72>0.3,"Alto en grasas",IF(BL72>0.2,"Moderado en grasas","Bajo en grasas"))) -> Bajo en grasas | BU72: =IF(BI72>1,"Alto riesgo de retención de líquidos",IF(BI72>0.5,"Riesgo moderado de retención","Equilibrio de líquidos ideal")) -> Equilibrio de líquidos ideal | BV72: =IF(BM72>0.5,"Alta",IF(BM72>0.2,"Media","Baja")) & " fuente de magnesio" -> Baja fuente de magnesio | BW72: =IF(AV72>=0.5,"Alta fuente de Omega 3",IF(AV72>0.1,"Ligera fuente de Omega 3","Sin aporte de Omega 3")) -> Sin aporte de Omega 3 | BX72: =IF(AX72>0.5,"Alerta: Alto en grasas trans",IF(AX72>0,"Contiene grasas trans","Libre de grasas trans")) -> Libre de grasas trans | BY72: =IF(AY72>=50,"Alto",IF(AY72>=10,"Medio","Bajo")) & " poder antioxidante" -> Alto poder antioxidante | BZ72: =IF(AZ72>=1,"Probiótico activo","Sin probióticos") -> Sin probióticos | CA72: =IF(OR(AX72>0.5, O72>15, J72>0), "Altamente inflamatorio", IF(OR(AV72>=0.5, AY72>=50), "Antiinflamatorio", IF(OR(AX72>0, O72>5), "Moderadamente inflamatorio", "Poco inflamatorio"))) -> Antiinflamatorio | CB72: =IF(ISNUMBER(SEARCH("miel", D72)), "No irritante (Uso condicionado SII)", IF(OR(J72>0, ISNUMBER(SEARCH("cacao", D72)), ISNUMBER(SEARCH("chocolate puro", D72))), "Altamente irritante", IF(OR(AND(O72>15, BI72>1), ISNUMBER(SEARCH("chocolate", D72))), "Moderadamente irritante", "No irritante"))) -> No irritante | CC72: =IF(AV72=0,"Sin Omega 3 para evaluar",IFERROR(IF(((T72-AV72)/AV72)>4,"Exceso relativo de Omega 6","Balance de omegas favorable"),"Sin Omega 3 para evaluar")) -> Exceso relativo de Omega 6
A73: =1+A72 -> 72 | B73: VERDURAS Y HORTALIZAS | C73: Tubérculos y raíces | D73: Fécula de patata | E73: Almido de papa | F73: 2 | G73: 1 | H73: 375 | I73: 3.8 | J73: 0 | K73: 6.9 | L73: 83.1 | M73: 79.6 | N73: 3.5 | O73: 0 | P73: 5.9 | Q73: 0.34 | R73: 0.09 | S73: 0.008 | T73: 0.15 | U73: 0 | V73: 0 | W73: 0 | X73: 0 | Y73: 0 | Z73: 0.25 | AA73: 0 | AB73: 0.23 | AC73: 0.051 | AD73: 3.5 | AE73: 0.77 | AF73: 25 | AG73: 0 | AH73: 0 | AI73: 0 | AJ73: 3.8 | AK73: 65 | AL73: 168 | AM73: 1.4 | AN73: 0 | AO73: 0.54 | AP73: 65 | AQ73: 55 | AR73: 1001 | AS73: 0 | AT73: 0 | AU73: 1.1 | AV73: =IFERROR(VLOOKUP(IFERROR(VLOOKUP(D73,Mapa_Similitud!$A$2:$B$2000,2,FALSE()),D73),Hoja1!$A$2:$K$1000,2,FALSE()),IFERROR(VLOOKUP(IFERROR(VLOOKUP(D73,Mapa_Similitud!$A$2:$B$2000,2,FALSE()),D73),Omega3_Referencia!$A$2:$E$100,3,FALSE()),0)) -> 0 | AW73: =IFERROR(VLOOKUP(IFERROR(VLOOKUP(D73,Mapa_Similitud!$A$2:$B$2000,2,FALSE()),D73),Hoja1!$A$2:$K$1000,3,FALSE()),IFERROR(VLOOKUP(IFERROR(VLOOKUP(D73,Mapa_Similitud!$A$2:$B$2000,2,FALSE()),D73),Omega3_Referencia!$A$2:$E$100,4,FALSE()),"N/A")) -> N/A | AX73: =IFERROR(VLOOKUP(IFERROR(VLOOKUP(D73,Mapa_Similitud!$A$2:$B$2000,2,FALSE()),D73),Hoja1!$A$2:$K$1000,5,FALSE()),0) -> 0 | AY73: =IFERROR(VLOOKUP(IFERROR(VLOOKUP(D73,Mapa_Similitud!$A$2:$B$2000,2,FALSE()),D73),Hoja1!$A$2:$K$1000,7,FALSE()),0) -> 0 | AZ73: =IFERROR(VLOOKUP(IFERROR(VLOOKUP(D73,Mapa_Similitud!$A$2:$B$2000,2,FALSE()),D73),Hoja1!$A$2:$K$1000,9,FALSE()),0) -> 0 | BA73: =IFERROR(K73/H73,0) -> 0.0184 | BB73: =IFERROR(P73/H73,0) -> 0.015733333 | BC73: =IFERROR(AK73/H73,0) -> 0.17333333 | BD73: =IFERROR(AM73/H73,0) -> 0.0037333333 | BE73: =IFERROR(AQ73/H73,0) -> 0.14666667 | BF73: =IFERROR(T73/R73,0) -> 1.6666667 | BG73: =IFERROR(AK73/AL73,0) -> 0.38690476 | BH73: =IFERROR(R73/Q73,0) -> 0.26470588 | BI73: =IFERROR(AQ73/AR73,0) -> 0.054945055 | BJ73: =IFERROR(N73/L73,0) -> 0.04211793 | BK73: =IFERROR(P73/L73,0) -> 0.070998797 | BL73: =IFERROR((Q73*9)/H73,0) -> 0.00816 | BM73: =IFERROR(AP73/H73,0) -> 0.17333333 | BN73: =IF(BA73>0.2,"Muy alta fuente de proteína",IF(BA73>0.15,"Alta fuente de proteína",IF(BA73>0.1,"Media fuente de proteína","Baja fuente de proteína"))) -> Baja fuente de proteína | BO73: =IF(BB73>0.03,"Alta",IF(BB73>0.015,"Media","Baja")) & " fuente de fibra" -> Media fuente de fibra | BP73: =IF(BC73>1.5,"Alta fuente de calcio",IF(BC73>0.8,"Media fuente de calcio","Baja fuente de calcio")) -> Baja fuente de calcio | BQ73: =IF(BD73>0.015,"Alta fuente de hierro",IF(BD73>0.008,"Media fuente de hierro","Baja fuente de hierro")) -> Baja fuente de hierro | BR73: =IF(BE73>2,"Muy alto",IF(BE73>1,"Alto",IF(BE73>0.5,"Moderado","Bajo"))) & " en sodio" -> Bajo en sodio | BS73: =IF(BF73>2,"Altamente antiinflamatorio",IF(BF73>1,"Ligeramente antiinflamatorio",IF(BF73>0.5,"Neutro","Proinflamatorio"))) -> Ligeramente antiinflamatorio | BT73: =IF(BL73>0.4,"Muy alto en grasas",IF(BL73>0.3,"Alto en grasas",IF(BL73>0.2,"Moderado en grasas","Bajo en grasas"))) -> Bajo en grasas | BU73: =IF(BI73>1,"Alto riesgo de retención de líquidos",IF(BI73>0.5,"Riesgo moderado de retención","Equilibrio de líquidos ideal")) -> Equilibrio de líquidos ideal | BV73: =IF(BM73>0.5,"Alta",IF(BM73>0.2,"Media","Baja")) & " fuente de magnesio" -> Baja fuente de magnesio | BW73: =IF(AV73>=0.5,"Alta fuente de Omega 3",IF(AV73>0.1,"Ligera fuente de Omega 3","Sin aporte de Omega 3")) -> Sin aporte de Omega 3 | BX73: =IF(AX73>0.5,"Alerta: Alto en grasas trans",IF(AX73>0,"Contiene grasas trans","Libre de grasas trans")) -> Libre de grasas trans | BY73: =IF(AY73>=50,"Alto",IF(AY73>=10,"Medio","Bajo")) & " poder antioxidante" -> Bajo poder antioxidante | BZ73: =IF(AZ73>=1,"Probiótico activo","Sin probióticos") -> Sin probióticos | CA73: =IF(OR(AX73>0.5, O73>15, J73>0), "Altamente inflamatorio", IF(OR(AV73>=0.5, AY73>=50), "Antiinflamatorio", IF(OR(AX73>0, O73>5), "Moderadamente inflamatorio", "Poco inflamatorio"))) -> Poco inflamatorio | CB73: =IF(ISNUMBER(SEARCH("miel", D73)), "No irritante (Uso condicionado SII)", IF(OR(J73>0, ISNUMBER(SEARCH("cacao", D73)), ISNUMBER(SEARCH("chocolate puro", D73))), "Altamente irritante", IF(OR(AND(O73>15, BI73>1), ISNUMBER(SEARCH("chocolate", D73))), "Moderadamente irritante", "No irritante"))) -> No irritante | CC73: =IF(AV73=0,"Sin Omega 3 para evaluar",IFERROR(IF(((T73-AV73)/AV73)>4,"Exceso relativo de Omega 6","Balance de omegas favorable"),"Sin Omega 3 para evaluar")) -> Sin Omega 3 para evaluar
A74: =1+A73 -> 73 | B74: VERDURAS Y HORTALIZAS | C74: Tubérculos y raíces | D74: Harina de tapioca | F74: 1.5 | G74: 1 | H74: 382 | I74: 4.6 | J74: 0 | K74: 0.5 | L74: 94.3 | M74: 94.3 | N74: 0 | O74: 0 | P74: 0.4 | Q74: 0.2 | R74: 0.05 | S74: 0.05 | T74: 0.03 | U74: 0 | V74: 0 | W74: 0 | X74: 0 | Y74: 0 | Z74: 0 | AA74: 0 | AB74: 0.01 | AC74: 0.01 | AD74: 0.01 | AE74: 0.01 | AF74: 0.01 | AG74: 0 | AH74: 0 | AI74: 0 | AJ74: 0 | AK74: 11 | AL74: 20 | AM74: 1 | AN74: 0 | AO74: 0 | AP74: 3 | AQ74: 4 | AR74: 20 | AS74: 0 | AT74: 0 | AU74: 0.8 | AV74: =IFERROR(VLOOKUP(IFERROR(VLOOKUP(D74,Mapa_Similitud!$A$2:$B$2000,2,FALSE()),D74),Hoja1!$A$2:$K$1000,2,FALSE()),IFERROR(VLOOKUP(IFERROR(VLOOKUP(D74,Mapa_Similitud!$A$2:$B$2000,2,FALSE()),D74),Omega3_Referencia!$A$2:$E$100,3,FALSE()),0)) -> 0 | AW74: =IFERROR(VLOOKUP(IFERROR(VLOOKUP(D74,Mapa_Similitud!$A$2:$B$2000,2,FALSE()),D74),Hoja1!$A$2:$K$1000,3,FALSE()),IFERROR(VLOOKUP(IFERROR(VLOOKUP(D74,Mapa_Similitud!$A$2:$B$2000,2,FALSE()),D74),Omega3_Referencia!$A$2:$E$100,4,FALSE()),"N/A")) -> N/A | AX74: =IFERROR(VLOOKUP(IFERROR(VLOOKUP(D74,Mapa_Similitud!$A$2:$B$2000,2,FALSE()),D74),Hoja1!$A$2:$K$1000,5,FALSE()),0) -> 0 | AY74: =IFERROR(VLOOKUP(IFERROR(VLOOKUP(D74,Mapa_Similitud!$A$2:$B$2000,2,FALSE()),D74),Hoja1!$A$2:$K$1000,7,FALSE()),0) -> 0 | AZ74: =IFERROR(VLOOKUP(IFERROR(VLOOKUP(D74,Mapa_Similitud!$A$2:$B$2000,2,FALSE()),D74),Hoja1!$A$2:$K$1000,9,FALSE()),0) -> 0 | BA74: =IFERROR(K74/H74,0) -> 0.0013089005 | BB74: =IFERROR(P74/H74,0) -> 0.0010471204 | BC74: =IFERROR(AK74/H74,0) -> 0.028795812 | BD74: =IFERROR(AM74/H74,0) -> 0.002617801 | BE74: =IFERROR(AQ74/H74,0) -> 0.010471204 | BF74: =IFERROR(T74/R74,0) -> 0.6 | BG74: =IFERROR(AK74/AL74,0) -> 0.55 | BH74: =IFERROR(R74/Q74,0) -> 0.25 | BI74: =IFERROR(AQ74/AR74,0) -> 0.2 | BJ74: =IFERROR(N74/L74,0) -> 0 | BK74: =IFERROR(P74/L74,0) -> 0.0042417815 | BL74: =IFERROR((Q74*9)/H74,0) -> 0.0047120419 | BM74: =IFERROR(AP74/H74,0) -> 0.0078534031 | BN74: =IF(BA74>0.2,"Muy alta fuente de proteína",IF(BA74>0.15,"Alta fuente de proteína",IF(BA74>0.1,"Media fuente de proteína","Baja fuente de proteína"))) -> Baja fuente de proteína | BO74: =IF(BB74>0.03,"Alta",IF(BB74>0.015,"Media","Baja")) & " fuente de fibra" -> Baja fuente de fibra | BP74: =IF(BC74>1.5,"Alta fuente de calcio",IF(BC74>0.8,"Media fuente de calcio","Baja fuente de calcio")) -> Baja fuente de calcio | BQ74: =IF(BD74>0.015,"Alta fuente de hierro",IF(BD74>0.008,"Media fuente de hierro","Baja fuente de hierro")) -> Baja fuente de hierro | BR74: =IF(BE74>2,"Muy alto",IF(BE74>1,"Alto",IF(BE74>0.5,"Moderado","Bajo"))) & " en sodio" -> Bajo en sodio | BS74: =IF(BF74>2,"Altamente antiinflamatorio",IF(BF74>1,"Ligeramente antiinflamatorio",IF(BF74>0.5,"Neutro","Proinflamatorio"))) -> Neutro | BT74: =IF(BL74>0.4,"Muy alto en grasas",IF(BL74>0.3,"Alto en grasas",IF(BL74>0.2,"Moderado en grasas","Bajo en grasas"))) -> Bajo en grasas | BU74: =IF(BI74>1,"Alto riesgo de retención de líquidos",IF(BI74>0.5,"Riesgo moderado de retención","Equilibrio de líquidos ideal")) -> Equilibrio de líquidos ideal | BV74: =IF(BM74>0.5,"Alta",IF(BM74>0.2,"Media","Baja")) & " fuente de magnesio" -> Baja fuente de magnesio | BW74: =IF(AV74>=0.5,"Alta fuente de Omega 3",IF(AV74>0.1,"Ligera fuente de Omega 3","Sin aporte de Omega 3")) -> Sin aporte de Omega 3 | BX74: =IF(AX74>0.5,"Alerta: Alto en grasas trans",IF(AX74>0,"Contiene grasas trans","Libre de grasas trans")) -> Libre de grasas trans | BY74: =IF(AY74>=50,"Alto",IF(AY74>=10,"Medio","Bajo")) & " poder antioxidante" -> Bajo poder antioxidante | BZ74: =IF(AZ74>=1,"Probiótico activo","Sin probióticos") -> Sin probióticos | CA74: =IF(OR(AX74>0.5, O74>15, J74>0), "Altamente inflamatorio", IF(OR(AV74>=0.5, AY74>=50), "Antiinflamatorio", IF(OR(AX74>0, O74>5), "Moderadamente inflamatorio", "Poco inflamatorio"))) -> Poco inflamatorio | CB74: =IF(ISNUMBER(SEARCH("miel", D74)), "No irritante (Uso condicionado SII)", IF(OR(J74>0, ISNUMBER(SEARCH("cacao", D74)), ISNUMBER(SEARCH("chocolate puro", D74))), "Altamente irritante", IF(OR(AND(O74>15, BI74>1), ISNUMBER(SEARCH("chocolate", D74))), "Moderadamente irritante", "No irritante"))) -> No irritante | CC74: =IF(AV74=0,"Sin Omega 3 para evaluar",IFERROR(IF(((T74-AV74)/AV74)>4,"Exceso relativo de Omega 6","Balance de omegas favorable"),"Sin Omega 3 para evaluar")) -> Sin Omega 3 para evaluar
A75: =1+A74 -> 74 | B75: VERDURAS Y HORTALIZAS | C75: Tubérculos y raíces | D75: Nabo | F75: 0.5 | G75: 0.75 | H75: 31.8 | I75: 90.6 | J75: 0 | K75: 1 | L75: 4.7 | M75: 0.69 | N75: 4 | O75: 0 | P75: 3.5 | Q75: 0.22 | R75: 0.052 | S75: 0.015 | T75: 0.088 | U75: 0 | V75: 12 | W75: 0 | X75: 72 | Y75: 0 | Z75: 0 | AA75: 0.1 | AB75: 0.04 | AC75: 0.051 | AD75: 0.68 | AE75: 0.08 | AF75: 20 | AG75: 0 | AH75: 0.2 | AI75: 2 | AJ75: 20 | AK75: 45 | AL75: 41 | AM75: 0.38 | AN75: 2 | AO75: 0.23 | AP75: 14 | AQ75: 58 | AR75: 269 | AS75: 0.068 | AT75: 0.056 | AU75: 1 | AV75: =IFERROR(VLOOKUP(IFERROR(VLOOKUP(D75,Mapa_Similitud!$A$2:$B$2000,2,FALSE()),D75),Hoja1!$A$2:$K$1000,2,FALSE()),IFERROR(VLOOKUP(IFERROR(VLOOKUP(D75,Mapa_Similitud!$A$2:$B$2000,2,FALSE()),D75),Omega3_Referencia!$A$2:$E$100,3,FALSE()),0)) -> 0.01 | AW75: =IFERROR(VLOOKUP(IFERROR(VLOOKUP(D75,Mapa_Similitud!$A$2:$B$2000,2,FALSE()),D75),Hoja1!$A$2:$K$1000,3,FALSE()),IFERROR(VLOOKUP(IFERROR(VLOOKUP(D75,Mapa_Similitud!$A$2:$B$2000,2,FALSE()),D75),Omega3_Referencia!$A$2:$E$100,4,FALSE()),"N/A")) -> ALA | AX75: =IFERROR(VLOOKUP(IFERROR(VLOOKUP(D75,Mapa_Similitud!$A$2:$B$2000,2,FALSE()),D75),Hoja1!$A$2:$K$1000,5,FALSE()),0) -> 0 | AY75: =IFERROR(VLOOKUP(IFERROR(VLOOKUP(D75,Mapa_Similitud!$A$2:$B$2000,2,FALSE()),D75),Hoja1!$A$2:$K$1000,7,FALSE()),0) -> 45 | AZ75: =IFERROR(VLOOKUP(IFERROR(VLOOKUP(D75,Mapa_Similitud!$A$2:$B$2000,2,FALSE()),D75),Hoja1!$A$2:$K$1000,9,FALSE()),0) -> 0 | BA75: =IFERROR(K75/H75,0) -> 0.031446541 | BB75: =IFERROR(P75/H75,0) -> 0.11006289 | BC75: =IFERROR(AK75/H75,0) -> 1.4150943 | BD75: =IFERROR(AM75/H75,0) -> 0.011949686 | BE75: =IFERROR(AQ75/H75,0) -> 1.8238994 | BF75: =IFERROR(T75/R75,0) -> 1.6923077 | BG75: =IFERROR(AK75/AL75,0) -> 1.097561 | BH75: =IFERROR(R75/Q75,0) -> 0.23636364 | BI75: =IFERROR(AQ75/AR75,0) -> 0.21561338 | BJ75: =IFERROR(N75/L75,0) -> 0.85106383 | BK75: =IFERROR(P75/L75,0) -> 0.74468085 | BL75: =IFERROR((Q75*9)/H75,0) -> 0.062264151 | BM75: =IFERROR(AP75/H75,0) -> 0.44025157 | BN75: =IF(BA75>0.2,"Muy alta fuente de proteína",IF(BA75>0.15,"Alta fuente de proteína",IF(BA75>0.1,"Media fuente de proteína","Baja fuente de proteína"))) -> Baja fuente de proteína | BO75: =IF(BB75>0.03,"Alta",IF(BB75>0.015,"Media","Baja")) & " fuente de fibra" -> Alta fuente de fibra | BP75: =IF(BC75>1.5,"Alta fuente de calcio",IF(BC75>0.8,"Media fuente de calcio","Baja fuente de calcio")) -> Media fuente de calcio | BQ75: =IF(BD75>0.015,"Alta fuente de hierro",IF(BD75>0.008,"Media fuente de hierro","Baja fuente de hierro")) -> Media fuente de hierro | BR75: =IF(BE75>2,"Muy alto",IF(BE75>1,"Alto",IF(BE75>0.5,"Moderado","Bajo"))) & " en sodio" -> Alto en sodio | BS75: =IF(BF75>2,"Altamente antiinflamatorio",IF(BF75>1,"Ligeramente antiinflamatorio",IF(BF75>0.5,"Neutro","Proinflamatorio"))) -> Ligeramente antiinflamatorio | BT75: =IF(BL75>0.4,"Muy alto en grasas",IF(BL75>0.3,"Alto en grasas",IF(BL75>0.2,"Moderado en grasas","Bajo en grasas"))) -> Bajo en grasas | BU75: =IF(BI75>1,"Alto riesgo de retención de líquidos",IF(BI75>0.5,"Riesgo moderado de retención","Equilibrio de líquidos ideal")) -> Equilibrio de líquidos ideal | BV75: =IF(BM75>0.5,"Alta",IF(BM75>0.2,"Media","Baja")) & " fuente de magnesio" -> Media fuente de magnesio | BW75: =IF(AV75>=0.5,"Alta fuente de Omega 3",IF(AV75>0.1,"Ligera fuente de Omega 3","Sin aporte de Omega 3")) -> Sin aporte de Omega 3 | BX75: =IF(AX75>0.5,"Alerta: Alto en grasas trans",IF(AX75>0,"Contiene grasas trans","Libre de grasas trans")) -> Libre de grasas trans | BY75: =IF(AY75>=50,"Alto",IF(AY75>=10,"Medio","Bajo")) & " poder antioxidante" -> Medio poder antioxidante | BZ75: =IF(AZ75>=1,"Probiótico activo","Sin probióticos") -> Sin probióticos | CA75: =IF(OR(AX75>0.5, O75>15, J75>0), "Altamente inflamatorio", IF(OR(AV75>=0.5, AY75>=50), "Antiinflamatorio", IF(OR(AX75>0, O75>5), "Moderadamente inflamatorio", "Poco inflamatorio"))) -> Poco inflamatorio | CB75: =IF(ISNUMBER(SEARCH("miel", D75)), "No irritante (Uso condicionado SII)", IF(OR(J75>0, ISNUMBER(SEARCH("cacao", D75)), ISNUMBER(SEARCH("chocolate puro", D75))), "Altamente irritante", IF(OR(AND(O75>15, BI75>1), ISNUMBER(SEARCH("chocolate", D75))), "Moderadamente irritante", "No irritante"))) -> No irritante | CC75: =IF(AV75=0,"Sin Omega 3 para evaluar",IFERROR(IF(((T75-AV75)/AV75)>4,"Exceso relativo de Omega 6","Balance de omegas favorable"),"Sin Omega 3 para evaluar")) -> Exceso relativo de Omega 6
A76: =1+A75 -> 75 | B76: VERDURAS Y HORTALIZAS | C76: Tubérculos y raíces | D76: Patata nueva | F76: 0.35 | G76: 0.8 | H76: 73.6 | I76: 80.7 | J76: 0 | K76: 2.3 | L76: 14.8 | M76: 14.1 | N76: 0.7 | O76: 0 | P76: 2.1 | Q76: 0.11 | R76: 0.026 | S76: 0.002 | T76: 0.056 | U76: 0 | V76: 0.17 | W76: 0 | X76: 1 | Y76: 0 | Z76: 0.053 | AA76: 2.1 | AB76: 0.11 | AC76: 0.047 | AD76: 1.7 | AE76: 0.31 | AF76: 22 | AG76: 0 | AH76: 0.4 | AI76: 0.4 | AJ76: 17 | AK76: 6.4 | AL76: 50 | AM76: 0.43 | AN76: 2.6 | AO76: 0.34 | AP76: 21 | AQ76: 2.7 | AR76: 418 | AS76: 0.15 | AT76: 0.091 | AU76: 1.5 | AV76: =IFERROR(VLOOKUP(IFERROR(VLOOKUP(D76,Mapa_Similitud!$A$2:$B$2000,2,FALSE()),D76),Hoja1!$A$2:$K$1000,2,FALSE()),IFERROR(VLOOKUP(IFERROR(VLOOKUP(D76,Mapa_Similitud!$A$2:$B$2000,2,FALSE()),D76),Omega3_Referencia!$A$2:$E$100,3,FALSE()),0)) -> 0.01 | AW76: =IFERROR(VLOOKUP(IFERROR(VLOOKUP(D76,Mapa_Similitud!$A$2:$B$2000,2,FALSE()),D76),Hoja1!$A$2:$K$1000,3,FALSE()),IFERROR(VLOOKUP(IFERROR(VLOOKUP(D76,Mapa_Similitud!$A$2:$B$2000,2,FALSE()),D76),Omega3_Referencia!$A$2:$E$100,4,FALSE()),"N/A")) -> ALA | AX76: =IFERROR(VLOOKUP(IFERROR(VLOOKUP(D76,Mapa_Similitud!$A$2:$B$2000,2,FALSE()),D76),Hoja1!$A$2:$K$1000,5,FALSE()),0) -> 0 | AY76: =IFERROR(VLOOKUP(IFERROR(VLOOKUP(D76,Mapa_Similitud!$A$2:$B$2000,2,FALSE()),D76),Hoja1!$A$2:$K$1000,7,FALSE()),0) -> 25 | AZ76: =IFERROR(VLOOKUP(IFERROR(VLOOKUP(D76,Mapa_Similitud!$A$2:$B$2000,2,FALSE()),D76),Hoja1!$A$2:$K$1000,9,FALSE()),0) -> 0 | BA76: =IFERROR(K76/H76,0) -> 0.03125 | BB76: =IFERROR(P76/H76,0) -> 0.028532609 | BC76: =IFERROR(AK76/H76,0) -> 0.086956522 | BD76: =IFERROR(AM76/H76,0) -> 0.0058423913 | BE76: =IFERROR(AQ76/H76,0) -> 0.036684783 | BF76: =IFERROR(T76/R76,0) -> 2.1538462 | BG76: =IFERROR(AK76/AL76,0) -> 0.128 | BH76: =IFERROR(R76/Q76,0) -> 0.23636364 | BI76: =IFERROR(AQ76/AR76,0) -> 0.0064593301 | BJ76: =IFERROR(N76/L76,0) -> 0.047297297 | BK76: =IFERROR(P76/L76,0) -> 0.14189189 | BL76: =IFERROR((Q76*9)/H76,0) -> 0.013451087 | BM76: =IFERROR(AP76/H76,0) -> 0.28532609 | BN76: =IF(BA76>0.2,"Muy alta fuente de proteína",IF(BA76>0.15,"Alta fuente de proteína",IF(BA76>0.1,"Media fuente de proteína","Baja fuente de proteína"))) -> Baja fuente de proteína | BO76: =IF(BB76>0.03,"Alta",IF(BB76>0.015,"Media","Baja")) & " fuente de fibra" -> Media fuente de fibra | BP76: =IF(BC76>1.5,"Alta fuente de calcio",IF(BC76>0.8,"Media fuente de calcio","Baja fuente de calcio")) -> Baja fuente de calcio | BQ76: =IF(BD76>0.015,"Alta fuente de hierro",IF(BD76>0.008,"Media fuente de hierro","Baja fuente de hierro")) -> Baja fuente de hierro | BR76: =IF(BE76>2,"Muy alto",IF(BE76>1,"Alto",IF(BE76>0.5,"Moderado","Bajo"))) & " en sodio" -> Bajo en sodio | BS76: =IF(BF76>2,"Altamente antiinflamatorio",IF(BF76>1,"Ligeramente antiinflamatorio",IF(BF76>0.5,"Neutro","Proinflamatorio"))) -> Altamente antiinflamatorio | BT76: =IF(BL76>0.4,"Muy alto en grasas",IF(BL76>0.3,"Alto en grasas",IF(BL76>0.2,"Moderado en grasas","Bajo en grasas"))) -> Bajo en grasas | BU76: =IF(BI76>1,"Alto riesgo de retención de líquidos",IF(BI76>0.5,"Riesgo moderado de retención","Equilibrio de líquidos ideal")) -> Equilibrio de líquidos ideal | BV76: =IF(BM76>0.5,"Alta",IF(BM76>0.2,"Media","Baja")) & " fuente de magnesio" -> Media fuente de magnesio | BW76: =IF(AV76>=0.5,"Alta fuente de Omega 3",IF(AV76>0.1,"Ligera fuente de Omega 3","Sin aporte de Omega 3")) -> Sin aporte de Omega 3 | BX76: =IF(AX76>0.5,"Alerta: Alto en grasas trans",IF(AX76>0,"Contiene grasas trans","Libre de grasas trans")) -> Libre de grasas trans | BY76: =IF(AY76>=50,"Alto",IF(AY76>=10,"Medio","Bajo")) & " poder antioxidante" -> Medio poder antioxidante | BZ76: =IF(AZ76>=1,"Probiótico activo","Sin probióticos") -> Sin probióticos | CA76: =IF(OR(AX76>0.5, O76>15, J76>0), "Altamente inflamatorio", IF(OR(AV76>=0.5, AY76>=50), "Antiinflamatorio", IF(OR(AX76>0, O76>5), "Moderadamente inflamatorio", "Poco inflamatorio"))) -> Poco inflamatorio | CB76: =IF(ISNUMBER(SEARCH("miel", D76)), "No irritante (Uso condicionado SII)", IF(OR(J76>0, ISNUMBER(SEARCH("cacao", D76)), ISNUMBER(SEARCH("chocolate puro", D76))), "Altamente irritante", IF(OR(AND(O76>15, BI76>1), ISNUMBER(SEARCH("chocolate", D76))), "Moderadamente irritante", "No irritante"))) -> No irritante | CC76: =IF(AV76=0,"Sin Omega 3 para evaluar",IFERROR(IF(((T76-AV76)/AV76)>4,"Exceso relativo de Omega 6","Balance de omegas favorable"),"Sin Omega 3 para evaluar")) -> Exceso relativo de Omega 6
